Workbook
Name AbastOrganitzatiu: Llistes!$T$2:$T$6
Name AltValor: Llistes!$AA$2:$AA$10
Name Àmbit: Llistes!$R$2:$R$6
Name AnàlisiRiscos: Llistes!$BS$2:$BS$10
Name AnàlisiRiscosGrau: Llistes!$BT$2:$BT$10
Name Àrea: Llistes!$D$5:$D$37
Name ArquitecturaCloud: Llistes!$J$2:$J$7
Name Cadencia: Llistes!$AC$2:$AC$10
Name CategoriaConjuntDades: Llistes!$AO$2:$AO$7
Name Confidencialitat: Llistes!$BG$2:$BG$5
Name ConjuntsDades: 'Conjunts de dades'!$B$9:$B$200
Name ControlRelacions: 'Rel.Conjunts-Sistemes'!$G$9:$G$200
Name Criticitat: Llistes!$P$2:$P$6
Name DadesObertes: Llistes!$AM$2:$AM$8
Name Dominis: 'Dominis de dades'!$B$8:$B$62
Name Dominis_a_ConjuntsDades: 'Conjunts de dades'!$D$9:INDEX('Conjunts de dades'!$D:$D,COUNTA('Conjunts de dades'!$D:$D))
Name DominisDades: 'Dominis de dades'!$B$9:$E$62
Name EntitatsGlobals: Llistes!$AS$2:$AS$38
Name EstatSistemes: Llistes!$L$2:$L$12
Name Format: Llistes!$BI$2:$BI$12
Name LlistaConjunts: Llistes!$F$2:INDEX(Llistes!$F:$F,COUNTA(Llistes!$F:$F))
Name LlistaDominis: Llistes!$D$2:INDEX(Llistes!$D:$D,COUNTA(Llistes!$D:$D))
Name LlistaSistemes: Llistes!$B$2:INDEX(Llistes!$B:$B,COUNTA(Llistes!$B:$B))
Name NivellAccés: Llistes!$AE$2:$AE$10
Name Nom_Conjunt_de_dades: 'Conjunts de dades'!$B$8:$B$200
Name Origens: Llistes!$AK$2:$AK$9
Name Orígens: Llistes!$AK$2:$AK$7
Name Persistencia: Llistes!$AG$2:$AG$12
Name Prioritats: Llistes!$BQ$2:$BQ$6
Name Rel_Sistemes_Conjunts: 'Rel.Conjunts-Sistemes'!$C$9:$C$200
Name RelacióGlosari: Llistes!$BE$2:$BE$8
Name RelacionsConjuntsDades: 'Rel.Conjunts-Sistemes'!$B$9:$B$200
Name RelacionsConjuntsDades: 'Rel.Conjunts-Sistemes'!$B$9:$B$200
Name Retenció: Llistes!$AI$3:$AI$12
Name Reutilitzacio: Llistes!$BO$2:$BO$8
Name Seguretat: Llistes!$BK$2:$BK$7
Name SensibilitatDades: Llistes!$N$2:$N$8
Name SiNo: Llistes!$BV$2:$BV$3
Name SiNoParcialment: Llistes!$BV$2:$BV$4
Name Sistemes: Sistemes!$B$9:$B$66
Name TipusAtributs: Llistes!$AY$2:$AY$15
Name TipusConjunt: Llistes!$V$2:$V$7
Name TipusInformació: Llistes!$X$2:$X$12
Name TipusRelEntitats: Llistes!$BC$2:$BC$7
Name TipusServei: Llistes!$H$2:$H$7

Sheet Instruccions
B5: Instruccions
C8: La plantilla de l'inventari d'actius de dades s'organitza en les pestanyes següents:
D10: Sistemes: Registre i descripció dels sistemes d'informació de l'ens local vinculats a les dades.
D11: Dominis de dades: Recull els dominis de dades més habituals en un ens local. Per a cadascun cal completar la informació específica del domini. Es poden afegir dominis addicionals que no figurin a la proposta inicial.
D12: Conjunts de dades: Identificació, registre i descripció dels conjunts de dades associats a cada domini.
D13: Entitats: Identificació, registre i descripció de les entitats vinculades als conjunts de dades.
D14: Rel. Conjunts–Entitats: Documentació de les relacions entre conjunts de dades i entitats.
D15: Atributs: Registre i descripció dels atributs de cada entitat.
D16: Rel. Entitats–Entitats: Documentació de les relacions entre entitats.
D17: Qualitat: Avaluació de la completitud i la coherència de l'inventari.
D18: Llegenda: Instruccions per complimentar correctament totes les pestanyes.
D19: Relació inventaris: Fonts i referents tinguts en compte en el disseny de la plantilla.
D20: Llistes: Valors de referència vàlids per a les columnes amb valors restringits
C22: L'àmbit de suport en governança de dades municipal i el responsable de dades de l'ens local són els responsables de documentar, mantenir i gestionar l'inventari d'actius de dades.
C23: Dominis de dades. S'han agrupat en àmbits:
D25: Govern i administració: tot allò que té a veure amb la gestió administrativa.
D26: Gestió de l'espai públic: tot allò que te a veure amb la gestió de la ciutat (residus, clavegueram, informació geogràfica, etc.).
D27: Serveis a les persones: tot el que fa referència a serveis municipals.
D28: Corporatiu (dades mestres i de referència): Les dades de referència haurien de ser comunes a tot l'espai de dades

Sheet Sistemes
B5: Sistemes de dades
B7: =COUNTA(Sistemes) -> 40 | C7: =COUNTA(C$9:INDEX(C:C,$B7+8))/$B7 -> 0.5 | D7: =COUNTA(D$9:INDEX(D:D,$B7+8))/$B7 -> 0.625 | E7: =COUNTA(E$9:INDEX(E:E,$B7+8))/$B7 -> 0.975 | F7: =COUNTA(F$9:INDEX(F:F,$B7+8))/$B7 -> 0 | G7: =COUNTA(G$9:INDEX(G:G,$B7+8))/$B7 -> 0 | H7: =COUNTA(H$9:INDEX(H:H,$B7+8))/$B7 -> 0 | I7: =COUNTA(I$9:INDEX(I:I,$B7+8))/$B7 -> 0 | J7: =COUNTA(J$9:INDEX(J:J,$B7+8))/$B7 -> 0 | K7: =COUNTA(K$9:INDEX(K:K,$B7+8))/$B7 -> 0 | L7: =COUNTA(L$9:INDEX(L:L,$B7+8))/$B7 -> 0 | M7: =COUNTA(M$9:INDEX(M:M,$B7+8))/$B7 -> 0 | N7: =COUNTA(N$9:INDEX(N:N,$B7+8))/$B7 -> 0
B8: Sistema de dades | C8: Descripció | D8: Tecnologies principals | E8: Proveïdor | F8: Tipus de servei | G8: Arquitectura cloud | H8: Estat Sistema | I8: Data revisió estat | J8: Administrador del sistema (nom) | K8: Administrador del sistema (rol) | L8: Criticitat | M8: Integracions | N8: Model d’autenticació | O8: Núm. Conjunts de dades
B9: Padró municipal d’habitants | C9: Padró municipal d’habitants | D9: PMH - Berger levrault | E9: Diputació | O9: =IF(B9="","",COUNTIF('Rel.Conjunts-Sistemes'!$C:$C,$B9)) -> 0
B10: Enquesta retributiva per a ús municipal | C10: ERET Enquesta retributiva per a ús municipal | D10: Desenvolupament propi | E10: Diputació | O10: =IF(B10="","",COUNTIF('Rel.Conjunts-Sistemes'!$C:$C,$B10)) -> 0
B11: Tramitació d’expedients administratius | C11: SeTDIBA Registre i tramitació d’expedients als ajuntaments. | D11: Gestiona | E11: Diputació | O11: =IF(B11="","",COUNTIF('Rel.Conjunts-Sistemes'!$C:$C,$B11)) -> 0
B12: Registre d'entrada i sortida | C12: SeTDIBA-SECRETARIA Aplicació per gestionar els òrgans col·legiats | D12: Gestiona | E12: Diputació | O12: =IF(B12="","",COUNTIF('Rel.Conjunts-Sistemes'!$C:$C,$B12)) -> 0
B13: Registre d'analítiques de la qualitat de l’aigua | C13: ORALIMS Anàlisi de la qualitat de l’aigua | D13: ORACLE | E13: Diputació | O13: =IF(B13="","",COUNTIF('Rel.Conjunts-Sistemes'!$C:$C,$B13)) -> 1
B14: Gestió de nòmines municipals | C14: EPSILON Gestió de nòmines municipals | D14: EPSILOM | E14: Diputació | O14: =IF(B14="","",COUNTIF('Rel.Conjunts-Sistemes'!$C:$C,$B14)) -> 0
B15: Registre d'activitats econòmiques (GIA) | C15: GIA Expedients d’activitats econòmiques | D15: GIA - desenvolupament propi | E15: Diputació | O15: =IF(B15="","",COUNTIF('Rel.Conjunts-Sistemes'!$C:$C,$B15)) -> 1
B16: Gestió dels plans de protecció civil municipal | C16: PCOM Gestió dels plans de protecció civil municipal | D16: PCOM - desenvolupament propi | E16: Diputació | O16: =IF(B16="","",COUNTIF('Rel.Conjunts-Sistemes'!$C:$C,$B16)) -> 0
B17: Repositori imatges arxius municipals (IMAGINA ) | C17: IMAGINA Repositori imatges arxius municipals | D17: IMAGINA - desenvolupament propi | E17: Diputació | O17: =IF(B17="","",COUNTIF('Rel.Conjunts-Sistemes'!$C:$C,$B17)) -> 0
B18: Sistema per a la gestió de serveis locals d’ocupació (XALOC) | C18: XALOC Serveis locals d’ocupació | D18: XALOC - desenvolupament propi | E18: Diputació | O18: =IF(B18="","",COUNTIF('Rel.Conjunts-Sistemes'!$C:$C,$B18)) -> 3
B19: Comptabilitat municipal | C19: SICALWIN Comptabilitat per als ajuntaments | D19: SICALWIN - Berger Levrault | E19: Diputació | O19: =IF(B19="","",COUNTIF('Rel.Conjunts-Sistemes'!$C:$C,$B19)) -> 0
B20: Gestió de subvencions | C20: ACCEDE-SUB Subvencions | D20: ACCEDE-SUB - Berger Levrault | E20: Diputació | O20: =IF(B20="","",COUNTIF('Rel.Conjunts-Sistemes'!$C:$C,$B20)) -> 0
... B26: Sistema de gestió de les auditories pobresa energètica | C26: SIAPE Auditories pobresa energètica | D26: SIAPE - desenvolupament propi | E26: Diputació | O26: =IF(B26="","",COUNTIF('Rel.Conjunts-Sistemes'!$C:$C,$B26)) -> 0
B27: Portal de transparència municipal | E27: Consorci AOC | O27: =IF(B27="","",COUNTIF('Rel.Conjunts-Sistemes'!$C:$C,$B27)) -> 0
B28: Portal de dades obertes municipal | D28: CKAN | E28: Consorci AOC | O28: =IF(B28="","",COUNTIF('Rel.Conjunts-Sistemes'!$C:$C,$B28)) -> 0
B29: Catàleg de tràmits i eina de tramitació digital | D29: Gestiona | E29: Diputació | O29: =IF(B29="","",COUNTIF('Rel.Conjunts-Sistemes'!$C:$C,$B29)) -> 0
B30: Seu electrònica | E30: Consorci AOC | O30: =IF(B30="","",COUNTIF('Rel.Conjunts-Sistemes'!$C:$C,$B30)) -> 0
B31: Gestió de serveis bibliotecaris | C31: SIERRA - eina de gestió de serveis bibliotecaris | D31: SIERRA - desenvolupament propi | E31: Diputació | O31: =IF(B31="","",COUNTIF('Rel.Conjunts-Sistemes'!$C:$C,$B31)) -> 0
B32: GIAM | C32: Gestió de fons de l'arxiu municipal | D32: Base de dades Access | E32: Diputació | O32: =IF(B32="","",COUNTIF('Rel.Conjunts-Sistemes'!$C:$C,$B32)) -> 0
B33: Gestió de cementiris | E33: Ajuntament | O33: =IF(B33="","",COUNTIF('Rel.Conjunts-Sistemes'!$C:$C,$B33)) -> 0
B34: Gestió de queixes i suggeriments | E34: Ajuntament | O34: =IF(B34="","",COUNTIF('Rel.Conjunts-Sistemes'!$C:$C,$B34)) -> 0
B35: Gestió de representacions | D35: Representa | E35: Consorci AOC | O35: =IF(B35="","",COUNTIF('Rel.Conjunts-Sistemes'!$C:$C,$B35)) -> 0
B36: Sistema de cita prèvia | E36: Ajuntament | O36: =IF(B36="","",COUNTIF('Rel.Conjunts-Sistemes'!$C:$C,$B36)) -> 0
B37: Sistema de gestió d'impostos municipals | D37: ORGT | E37: Ajuntament | O37: =IF(B37="","",COUNTIF('Rel.Conjunts-Sistemes'!$C:$C,$B37)) -> 0
B38: Sistema de gestió de personal | E38: Ajuntament | O38: =IF(B38="","",COUNTIF('Rel.Conjunts-Sistemes'!$C:$C,$B38)) -> 0
B39: Control horari | E39: Ajuntament | O39: =IF(B39="","",COUNTIF('Rel.Conjunts-Sistemes'!$C:$C,$B39)) -> 0
B40: Gestió d'incidències a la via pública i manteniment d'equipaments | E40: Ajuntament | O40: =IF(B40="","",COUNTIF('Rel.Conjunts-Sistemes'!$C:$C,$B40)) -> 0
B41: Gestió de residus | E41: Ajuntament | O41: =IF(B41="","",COUNTIF('Rel.Conjunts-Sistemes'!$C:$C,$B41)) -> 0
B42: Gestió policial d'atestats | E42: Ajuntament | O42: =IF(B42="","",COUNTIF('Rel.Conjunts-Sistemes'!$C:$C,$B42)) -> 0
B43: Gestió dels sistemes de videovigilància | E43: Ajuntament | O43: =IF(B43="","",COUNTIF('Rel.Conjunts-Sistemes'!$C:$C,$B43)) -> 0
B44: Gestió de sancions | E44: Ajuntament | O44: =IF(B44="","",COUNTIF('Rel.Conjunts-Sistemes'!$C:$C,$B44)) -> 0
B45: Gestió d'aparcaments | E45: Ajuntament | O45: =IF(B45="","",COUNTIF('Rel.Conjunts-Sistemes'!$C:$C,$B45)) -> 0
B46: Web municipal | E46: Diputació | O46: =IF(B46="","",COUNTIF('Rel.Conjunts-Sistemes'!$C:$C,$B46)) -> 0
B47: Eina de gestió de la participació | D47: Participa311 | E47: Diputació | O47: =IF(B47="","",COUNTIF('Rel.Conjunts-Sistemes'!$C:$C,$B47)) -> 0
B48: Plataforma de gestió d'informació de sensors | O48: =IF(B48="","",COUNTIF('Rel.Conjunts-Sistemes'!$C:$C,$B48)) -> 0
O49: =IF(B49="","",COUNTIF('Rel.Conjunts-Sistemes'!$C:$C,$B49))
O50: =IF(B50="","",COUNTIF('Rel.Conjunts-Sistemes'!$C:$C,$B50))
O51: =IF(B51="","",COUNTIF('Rel.Conjunts-Sistemes'!$C:$C,$B51))
O52: =IF(B52="","",COUNTIF('Rel.Conjunts-Sistemes'!$C:$C,$B52))
O53: =IF(B53="","",COUNTIF('Rel.Conjunts-Sistemes'!$C:$C,$B53))
O54: =IF(B54="","",COUNTIF('Rel.Conjunts-Sistemes'!$C:$C,$B54))
O55: =IF(B55="","",COUNTIF('Rel.Conjunts-Sistemes'!$C:$C,$B55))
O56: =IF(B56="","",COUNTIF('Rel.Conjunts-Sistemes'!$C:$C,$B56))
O57: =IF(B57="","",COUNTIF('Rel.Conjunts-Sistemes'!$C:$C,$B57))
O58: =IF(B58="","",COUNTIF('Rel.Conjunts-Sistemes'!$C:$C,$B58))
O59: =IF(B59="","",COUNTIF('Rel.Conjunts-Sistemes'!$C:$C,$B59))
O60: =IF(B60="","",COUNTIF('Rel.Conjunts-Sistemes'!$C:$C,$B60))
... O66: =IF(B66="","",COUNTIF('Rel.Conjunts-Sistemes'!$C:$C,$B66))

Sheet Dominis de dades
B5: Dominis de dades
B6: =COUNTA(Dominis) -> 36 | C6: =COUNTA(C$8:INDEX(C:C,$B6+7))/$B6 -> 0.97222222 | D6: =COUNTA(D$8:INDEX(D:D,$B6+7))/$B6 -> 0.97222222 | E6: =COUNTA(E$8:INDEX(E:E,$B6+7))/$B6 -> 0.97222222
B7: Domini de dades | C7: Descripció | D7: Àmbit | E7: Àrea propietària | F7: Núm. Conjunts de dades
B8: Patrimoni i actius municipals (nou) | C8: Inclou edificis, locals, solars, vehicles, equipaments, mobiliari urbà, punts enllumenat, inventari patrimonial, sensors, equip informàtic, llicències, etc. | D8: Corporatiu (Dades mestres i de referència) | E8: Obres i Manteniment | F8: =IF(B8="","",COUNTIF('Conjunts de dades'!$D:$D,$B8)) -> 11
B9: Padró i identitat ciutadana (antic Població) | C9: Inclou el padró, altes i baixes, canvis de domicili i certificats. És clau per a serveis municipals, estadística i finançament. Permet garantir adreces correctes i traçabilitat de moviments de veïns. | D9: Corporatiu (Dades mestres i de referència) | E9: Padró i Estadística | F9: =IF(B9="","",COUNTIF('Conjunts de dades'!$D:$D,$B9)) -> 1
B10: Dades de referència (comú a tot l'ecosistema de dades de país) | C10: Inclou codis, classificacions, declaració d'unitats administratives, països. Etc | D10: Corporatiu (Dades mestres i de referència) | E10: Padró i Estadística | F10: =IF(B10="","",COUNTIF('Conjunts de dades'!$D:$D,$B10)) -> 0
B11: Medi ambient | C11: Inclou controls de qualitat de l'aire i soroll, gestió d'espais naturals, permisos ambientals i seguiment de sancions. Permet planificar campanyes, gestionar denúncies i elaborar indicadors per a informes i transparència. | D11: Gestió de l'espai públic i serveis al territori | E11: Medi Ambient | F11: =IF(B11="","",COUNTIF('Conjunts de dades'!$D:$D,$B11)) -> 4
B12: Residus | C12: Inclou recollida, contenidors, rutes, incidències, inspeccions i dades de pes o volum. Ajuda a millorar el servei, controlar objectius de reciclatge i gestionar contractes i campanyes amb la ciutadania. | D12: Gestió de l'espai públic i serveis al territori | E12: Medi Ambient | F12: =IF(B12="","",COUNTIF('Conjunts de dades'!$D:$D,$B12)) -> 1
B13: Mobilitat i trànsit | C13: Recull regulació de trànsit, zones d'estacionament, sancions, incidències, aforaments i informació de transport. Ajuda a prendre decisions de circulació, millorar el servei i coordinar actuacions amb operadors i policia. | D13: Gestió de l'espai públic i serveis al territori | E13: Mobilitat | F13: =IF(B13="","",COUNTIF('Conjunts de dades'!$D:$D,$B13)) -> 6
B14: Obres públiques i manteniment | C14: Inventari de projectes d'obres municipals, plans de manteniment i afectacions a la via. Serveix per controlar terminis, pressupostos i coordinació amb serveis afectats, incloent empreses contractistes i permisos. | D14: Gestió de l'espai públic i serveis al territori | E14: Obres i Manteniment | F14: =IF(B14="","",COUNTIF('Conjunts de dades'!$D:$D,$B14)) -> 1
B15: Protecció civil i emergències | C15: Reuneix plans d'emergència, inventari de recursos, avisos, activacions i informes d'incidents. Ajuda a coordinar operatius, gestionar comunicacions amb altres cossos i conservar evidències per avaluar i millorar respostes. | D15: Gestió de l'espai públic i serveis al territori | E15: Protecció Civil | F15: =IF(B15="","",COUNTIF('Conjunts de dades'!$D:$D,$B15)) -> 2
B16: Aigua i sanejament | C16: Inclou dades d'abonats, comptadors, lectures, incidències de xarxa i actuacions de manteniment. Serveix per planificar reparacions, controlar el consum i coordinar les empreses concessionàries amb el servei municipal. | D16: Gestió de l'espai públic i serveis al territori | E16: Serveis Urbans | F16: =IF(B16="","",COUNTIF('Conjunts de dades'!$D:$D,$B16)) -> 2
B17: Consum energètic | C17: Conté informació de consums, avaries i ordres de treball. Ajuda a prioritzar reparacions, optimitzar energia i comprovar el compliment del contracte de manteniment. | D17: Gestió de l'espai públic i serveis al territori | E17: Serveis Urbans | F17: =IF(B17="","",COUNTIF('Conjunts de dades'!$D:$D,$B17)) -> 1
B18: Neteja viària | C18: Inclou rutes de neteja, planificació de torns, incidències, inspeccions i control de qualitat del servei. Permet fer seguiment del contracte, registrar queixes i ajustar recursos segons zones i esdeveniments. | D18: Gestió de l'espai públic i serveis al territori | E18: Serveis Urbans | F18: =IF(B18="","",COUNTIF('Conjunts de dades'!$D:$D,$B18)) -> 1
B19: Informació territorial i geoespacial | C19: Agrupa cartografia, carrers, adreces, parcel·les, equipaments i capes temàtiques. Serveix per suportar tràmits, planificació i consultes internes, i per compartir mapes amb altres organismes quan cal. | D19: Gestió de l'espai públic i serveis al territori | E19: Urbanisme | F19: =IF(B19="","",COUNTIF('Conjunts de dades'!$D:$D,$B19)) -> 4
... B42: Turisme i oci | C42: Inclou recursos turístics, agenda d'activitats, reserves de visites, consultes i estadístiques de demanda. Permet informar visitants, coordinar agents locals i avaluar l'impacte d'esdeveniments amb dades clares i comparables. | D42: Serveis a les persones | E42: Turisme | F42: =IF(B42="","",COUNTIF('Conjunts de dades'!$D:$D,$B42)) -> 2
B43: Un domini de dades és una classificació lògica que agrupa dades relacionades per un significat, tema o propòsit comú, independentment de l’aplicació
F44: =IF(B44="","",COUNTIF('Conjunts de dades'!$D:$D,$B44))
F45: =IF(B45="","",COUNTIF('Conjunts de dades'!$D:$D,$B45))
F46: =IF(B46="","",COUNTIF('Conjunts de dades'!$D:$D,$B46))
F47: =IF(B47="","",COUNTIF('Conjunts de dades'!$D:$D,$B47))
F48: =IF(B48="","",COUNTIF('Conjunts de dades'!$D:$D,$B48))
F49: =IF(B49="","",COUNTIF('Conjunts de dades'!$D:$D,$B49))
F50: =IF(B50="","",COUNTIF('Conjunts de dades'!$D:$D,$B50))
F51: =IF(B51="","",COUNTIF('Conjunts de dades'!$D:$D,$B51))
F52: =IF(B52="","",COUNTIF('Conjunts de dades'!$D:$D,$B52))
F53: =IF(B53="","",COUNTIF('Conjunts de dades'!$D:$D,$B53))
F54: =IF(B54="","",COUNTIF('Conjunts de dades'!$D:$D,$B54))
F55: =IF(B55="","",COUNTIF('Conjunts de dades'!$D:$D,$B55))
... F62: =IF(B62="","",COUNTIF('Conjunts de dades'!$D:$D,$B62))

Sheet Conjunts de dades
B5: Conjunts de dades
B6: =COUNTA(ConjuntsDades) -> 111 | C6: =COUNTA(C$9:INDEX(C:C,$B6+8))/$B6 -> 1 | D6: =COUNTA(D$9:INDEX(D:D,$B6+8))/$B6 -> 1 | E6: =COUNTA(E$9:INDEX(E:E,$B6+8))/$B6 -> 1 | F6: =COUNTA(F$9:INDEX(F:F,$B6+8))/$B6 -> 0.009009009 | G6: =COUNTA(G$9:INDEX(G:G,$B6+8))/$B6 -> 0.009009009 | H6: =COUNTA(H$9:INDEX(H:H,$B6+8))/$B6 -> 0 | I6: =COUNTA(I$9:INDEX(I:I,$B6+8))/$B6 -> 0 | J6: =COUNTA(J$9:INDEX(J:J,$B6+8))/$B6 -> 0 | K6: =COUNTA(K$9:INDEX(K:K,$B6+8))/$B6 -> 0 | L6: =COUNTA(L$9:INDEX(L:L,$B6+8))/$B6 -> 0 | M6: =COUNTA(M$9:INDEX(M:M,$B6+8))/$B6 -> 0 | N6: =COUNTA(N$9:INDEX(N:N,$B6+8))/$B6 -> 0 | O6: =COUNTA(O$9:INDEX(O:O,$B6+8))/$B6 -> 0 | P6: =COUNTA(P$9:INDEX(P:P,$B6+8))/$B6 -> 0 | Q6: =COUNTA(Q$9:INDEX(Q:Q,$B6+8))/$B6 -> 0 | R6: =COUNTA(R$9:INDEX(R:R,$B6+8))/$B6 -> 0 | S6: =COUNTA(S$9:INDEX(S:S,$B6+8))/$B6 -> 0 | T6: =COUNTA(T$9:INDEX(T:T,$B6+8))/$B6 -> 0 | U6: =COUNTA(U$9:INDEX(U:U,$B6+8))/$B6 -> 0 | V6: =COUNTA(V$9:INDEX(V:V,$B6+8))/$B6 -> 0 | W6: =COUNTA(W$9:INDEX(W:W,$B6+8))/$B6 -> 0 | X6: =COUNTA(X$9:INDEX(X:X,$B6+8))/$B6 -> 0 | Y6: =COUNTA(Y$9:INDEX(Y:Y,$B6+8))/$B6 -> 0 | Z6: =COUNTA(Z$9:INDEX(Z:Z,$B6+8))/$B6 -> 0 | AA6: =COUNTA(AA$9:INDEX(AA:AA,$B6+8))/$B6 -> 0 | AB6: =COUNTA(AB$9:INDEX(AB:AB,$B6+8))/$B6 -> 0 | AC6: =COUNTA(AC$9:INDEX(AC:AC,$B6+8))/$B6 -> 0.009009009 | AD6: =COUNTA(AD$9:INDEX(AD:AD,$B6+8))/$B6 -> 0.009009009 | AE6: =COUNTA(AE$9:INDEX(AE:AE,$B6+8))/$B6 -> 0.009009009 | AF6: =COUNTA(AF$9:INDEX(AF:AF,$B6+8))/$B6 -> 0.009009009 | AG6: =COUNTA(AG$9:INDEX(AG:AG,$B6+8))/$B6 -> 0.009009009 | AH6: =COUNTA(AH$9:INDEX(AH:AH,$B6+8))/$B6 -> 0.009009009 | AI6: =COUNTA(AI$9:INDEX(AI:AI,$B6+8))/$B6 -> 0.009009009 | AJ6: =COUNTA(AJ$9:INDEX(AJ:AJ,$B6+8))/$B6 -> 0.009009009 | AK6: =COUNTA(AK$9:INDEX(AK:AK,$B6+8))/$B6 -> 0.009009009 | AL6: =COUNTA(AL$9:INDEX(AL:AL,$B6+8))/$B6 -> 0.009009009 | AM6: =COUNTA(AM$9:INDEX(AM:AM,$B6+8))/$B6 -> 0.009009009 | AN6: =COUNTA(AN$9:INDEX(AN:AN,$B6+8))/$B6 -> 0.009009009 | AO6: =COUNTA(AO$9:INDEX(AO:AO,$B6+8))/$B6 -> 0.009009009
H7: Sensibilitat de les dades | O7: Rols i responsabilitats | AC7: Riscos associats
B8: Nom Conjunt de dades | C8: Descripció | D8: Domini de dades | E8: Àrea propietària (Calculat pel Domini) | F8: Tipus conjunt de dades | G8: Ús previst de les dades | H8: Conté dades personals? | I8: Conté dades de gènere u orientació sexual? | J8: Conté dades d'ideologia o creences? | K8: Conté dades biomètriques? | L8: Conté dades de salut? | M8: Conté dades confidencials de l'ens local? | N8: Conté dades de seguretat i accés? | O8: Nom del responsable del Conjunt de dades (Propietari de dades) | P8: Càrrec del responsable del conjunt de dades | Q8: Nom del gestor del Conjunt de dades | R8: Càrrec del gestor del conjunt de dades | S8: Nom del custodi del Conjunt de dades | T8: Càrrec del custodi del conjunt de dades | U8: Categoria de les dades d'alt valor | V8: Cadència d'actualització | W8: Origen de les dades | X8: Persistència | Y8: Retenció | Z8: Disponibilitat històrica | AA8: Restriccions dades obertes | AB8: Reutilització de dades | AC8: Incoherència de dades | AD8: Informació desactualitzada | AE8: Publicació d'informació incorrecta | AF8: Registres duplicats | AG8: Accés a dades sensibles | AH8: Accés o ús indegut | AI8: Exposició de dades (menors, personals, sensibles o socials) | AJ8: Filtració o fuita de dades | AK8: Indisponiblitat del sistema | AL8: Pèrdua de dades | AM8: Falta de traçabilitat i evidències sobre la gestió de les dades | AN8: Falta de seguiment o auditories sobre accessos i usos | AO8: Falta de pla de resposta a incidents | AP8: Nivell de risc general | AQ8: Observacions | AR8: Núm. Sistemes d'informació | AS8: Núm. Dominis de dades
B9: Sol·licitants d'ocupació del servei local d'ocupació | C9: Registre anonimitzat del perfil sociodemogràfic dels demandants d'ocupació (edat, gènere, nivell d'estudis, sector professional, temps en atur). | D9: Formació i ocupació | E9: =IF(D9="","-",IF(ISERROR(VLOOKUP(D9,DominisDades,3,0)),"<<Domini erroni>>",VLOOKUP(D9,DominisDades,3,0))) -> Serveis a les persones | F9: Dades de referència / mestres no homogeneïtzades | G9: Intern transversal | AC9: Probabilitat: Baixa Impacte: Alt (2) | AD9: Probabilitat: Baixa Impacte: Moderat (1) | AE9: Probabilitat: Mitja Impacte: Baix (1) | AF9: Probabilitat: Mitja Impacte: Baix (1) | AG9: Probabilitat: Alta Impacte: Moderat (4) | AH9: Probabilitat: Mitja Impacte: Alt (4) | AI9: Probabilitat: Baixa Impacte: Alt (2) | AJ9: Probabilitat: Mitja Impacte: Alt (4) | AK9: Probabilitat: Mitja Impacte: Alt (4) | AL9: Probabilitat: Baixa Impacte: Alt (2) | AM9: Probabilitat: Baixa Impacte: Moderat (1) | AN9: Probabilitat: Baixa Impacte: Baix (1) | AO9: Probabilitat: Alta Impacte: Baix (3) | AP9: =AVERAGE(SUMIF(AnàlisiRiscos,AC9,AnàlisiRiscosGrau),SUMIF(AnàlisiRiscos,AD9,AnàlisiRiscosGrau),SUMIF(AnàlisiRiscos,AE9,AnàlisiRiscosGrau),SUMIF(AnàlisiRiscos,AF9,AnàlisiRiscosGrau),SUMIF(AnàlisiRiscos,AG9,AnàlisiRiscosGrau),SUMIF(AnàlisiRiscos,AH9,AnàlisiRiscosGrau),SUMIF(AnàlisiRiscos,AI9,AnàlisiRiscosGrau),SUMIF(AnàlisiRiscos,AJ9,AnàlisiRiscosGrau),SUMIF(AnàlisiRiscos,AK9,AnàlisiRiscosGrau),SUMIF(AnàlisiRiscos,AL9,AnàlisiRiscosGrau),SUMIF(AnàlisiRiscos,AM9,AnàlisiRiscosGrau),SUMIF(AnàlisiRiscos,AN9,AnàlisiRiscosGrau),SUMIF(AnàlisiRiscos,AO9,AnàlisiRiscosGrau)) -> 2.3076923 | AR9: =IF(B9="","",COUNTIF('Rel.Conjunts-Sistemes'!$B:$B,$B9)) -> 1 | AS9: =IF(B9="","",COUNTIF('Dominis de dades'!$B:$B,$D9)) -> 1
B10: Ofertes de treball del servei local d'ocupació | C10: Detall de les ofertes gestionades (sector, tipus de contracte, requisits) i indicadors d'eficiència (temps mitjà per cobrir la vacant). | D10: Formació i ocupació | E10: =IF(D10="","-",IF(ISERROR(VLOOKUP(D10,DominisDades,3,0)),"<<Domini erroni>>",VLOOKUP(D10,DominisDades,3,0))) -> Serveis a les persones | AP10: =AVERAGE(SUMIF(AnàlisiRiscos,AC10,AnàlisiRiscosGrau),SUMIF(AnàlisiRiscos,AD10,AnàlisiRiscosGrau),SUMIF(AnàlisiRiscos,AE10,AnàlisiRiscosGrau),SUMIF(AnàlisiRiscos,AF10,AnàlisiRiscosGrau),SUMIF(AnàlisiRiscos,AG10,AnàlisiRiscosGrau),SUMIF(AnàlisiRiscos,AH10,AnàlisiRiscosGrau),SUMIF(AnàlisiRiscos,AI10,AnàlisiRiscosGrau),SUMIF(AnàlisiRiscos,AJ10,AnàlisiRiscosGrau),SUMIF(AnàlisiRiscos,AK10,AnàlisiRiscosGrau),SUMIF(AnàlisiRiscos,AL10,AnàlisiRiscosGrau),SUMIF(AnàlisiRiscos,AM10,AnàlisiRiscosGrau),SUMIF(AnàlisiRiscos,AN10,AnàlisiRiscosGrau),SUMIF(AnàlisiRiscos,AO10,AnàlisiRiscosGrau)) -> 0 | AR10: =IF(B10="","",COUNTIF('Rel.Conjunts-Sistemes'!$B:$B,$B10)) -> 1 | AS10: =IF(B10="","",COUNTIF('Dominis de dades'!$B:$B,$D10)) -> 1
B11: Cens de locals comercials buits | C11: Indicador econòmic i cens geolocalitzat dels establiments comercials sense activitat a peu de carrer, orientat a plans de dinamització comercial. | D11: Economia local, comerç i mercats | E11: =IF(D11="","-",IF(ISERROR(VLOOKUP(D11,DominisDades,3,0)),"<<Domini erroni>>",VLOOKUP(D11,DominisDades,3,0))) -> Serveis a les persones | AP11: =AVERAGE(SUMIF(AnàlisiRiscos,AC11,AnàlisiRiscosGrau),SUMIF(AnàlisiRiscos,AD11,AnàlisiRiscosGrau),SUMIF(AnàlisiRiscos,AE11,AnàlisiRiscosGrau),SUMIF(AnàlisiRiscos,AF11,AnàlisiRiscosGrau),SUMIF(AnàlisiRiscos,AG11,AnàlisiRiscosGrau),SUMIF(AnàlisiRiscos,AH11,AnàlisiRiscosGrau),SUMIF(AnàlisiRiscos,AI11,AnàlisiRiscosGrau),SUMIF(AnàlisiRiscos,AJ11,AnàlisiRiscosGrau),SUMIF(AnàlisiRiscos,AK11,AnàlisiRiscosGrau),SUMIF(AnàlisiRiscos,AL11,AnàlisiRiscosGrau),SUMIF(AnàlisiRiscos,AM11,AnàlisiRiscosGrau),SUMIF(AnàlisiRiscos,AN11,AnàlisiRiscosGrau),SUMIF(AnàlisiRiscos,AO11,AnàlisiRiscosGrau)) -> 0 | AR11: =IF(B11="","",COUNTIF('Rel.Conjunts-Sistemes'!$B:$B,$B11)) -> 1 | AS11: =IF(B11="","",COUNTIF('Dominis de dades'!$B:$B,$D11)) -> 1
B12: Cens d'empreses, comerços i establiments | C12: Registre d'activitats econòmiques de la ciutat actives a peu de carrer o en oficines, classificades per sector econòmic. | D12: Economia local, comerç i mercats | E12: =IF(D12="","-",IF(ISERROR(VLOOKUP(D12,DominisDades,3,0)),"<<Domini erroni>>",VLOOKUP(D12,DominisDades,3,0))) -> Serveis a les persones | AP12: =AVERAGE(SUMIF(AnàlisiRiscos,AC12,AnàlisiRiscosGrau),SUMIF(AnàlisiRiscos,AD12,AnàlisiRiscosGrau),SUMIF(AnàlisiRiscos,AE12,AnàlisiRiscosGrau),SUMIF(AnàlisiRiscos,AF12,AnàlisiRiscosGrau),SUMIF(AnàlisiRiscos,AG12,AnàlisiRiscosGrau),SUMIF(AnàlisiRiscos,AH12,AnàlisiRiscosGrau),SUMIF(AnàlisiRiscos,AI12,AnàlisiRiscosGrau),SUMIF(AnàlisiRiscos,AJ12,AnàlisiRiscosGrau),SUMIF(AnàlisiRiscos,AK12,AnàlisiRiscosGrau),SUMIF(AnàlisiRiscos,AL12,AnàlisiRiscosGrau),SUMIF(AnàlisiRiscos,AM12,AnàlisiRiscosGrau),SUMIF(AnàlisiRiscos,AN12,AnàlisiRiscosGrau),SUMIF(AnàlisiRiscos,AO12,AnàlisiRiscosGrau)) -> 0 | AR12: =IF(B12="","",COUNTIF('Rel.Conjunts-Sistemes'!$B:$B,$B12)) -> 1 | AS12: =IF(B12="","",COUNTIF('Dominis de dades'!$B:$B,$D12)) -> 1
B13: Polígons de l'activitat econòmica i industrial | C13: Delimitació geogràfica, parcel·lari, serveis disponibles i directori d'empreses ubicades a les zones industrials de la localitat. | D13: Economia local, comerç i mercats | E13: =IF(D13="","-",IF(ISERROR(VLOOKUP(D13,DominisDades,3,0)),"<<Domini erroni>>",VLOOKUP(D13,DominisDades,3,0))) -> Serveis a les persones | AP13: =AVERAGE(SUMIF(AnàlisiRiscos,AC13,AnàlisiRiscosGrau),SUMIF(AnàlisiRiscos,AD13,AnàlisiRiscosGrau),SUMIF(AnàlisiRiscos,AE13,AnàlisiRiscosGrau),SUMIF(AnàlisiRiscos,AF13,AnàlisiRiscosGrau),SUMIF(AnàlisiRiscos,AG13,AnàlisiRiscosGrau),SUMIF(AnàlisiRiscos,AH13,AnàlisiRiscosGrau),SUMIF(AnàlisiRiscos,AI13,AnàlisiRiscosGrau),SUMIF(AnàlisiRiscos,AJ13,AnàlisiRiscosGrau),SUMIF(AnàlisiRiscos,AK13,AnàlisiRiscosGrau),SUMIF(AnàlisiRiscos,AL13,AnàlisiRiscosGrau),SUMIF(AnàlisiRiscos,AM13,AnàlisiRiscosGrau),SUMIF(AnàlisiRiscos,AN13,AnàlisiRiscosGrau),SUMIF(AnàlisiRiscos,AO13,AnàlisiRiscosGrau)) -> 0 | AR13: =IF(B13="","",COUNTIF('Rel.Conjunts-Sistemes'!$B:$B,$B13)) -> 1 | AS13: =IF(B13="","",COUNTIF('Dominis de dades'!$B:$B,$D13)) -> 1
B14: Tramitació i expedients administratius | C14: Traçabilitat de la gestió interna: expedients oberts, procediment, sèrie documental, àrea responsable, terminis de resolució i estat actual. | D14: Secretaria | E14: =IF(D14="","-",IF(ISERROR(VLOOKUP(D14,DominisDades,3,0)),"<<Domini erroni>>",VLOOKUP(D14,DominisDades,3,0))) -> Govern i administració | AP14: =AVERAGE(SUMIF(AnàlisiRiscos,AC14,AnàlisiRiscosGrau),SUMIF(AnàlisiRiscos,AD14,AnàlisiRiscosGrau),SUMIF(AnàlisiRiscos,AE14,AnàlisiRiscosGrau),SUMIF(AnàlisiRiscos,AF14,AnàlisiRiscosGrau),SUMIF(AnàlisiRiscos,AG14,AnàlisiRiscosGrau),SUMIF(AnàlisiRiscos,AH14,AnàlisiRiscosGrau),SUMIF(AnàlisiRiscos,AI14,AnàlisiRiscosGrau),SUMIF(AnàlisiRiscos,AJ14,AnàlisiRiscosGrau),SUMIF(AnàlisiRiscos,AK14,AnàlisiRiscosGrau),SUMIF(AnàlisiRiscos,AL14,AnàlisiRiscosGrau),SUMIF(AnàlisiRiscos,AM14,AnàlisiRiscosGrau),SUMIF(AnàlisiRiscos,AN14,AnàlisiRiscosGrau),SUMIF(AnàlisiRiscos,AO14,AnàlisiRiscosGrau)) -> 0 | AR14: =IF(B14="","",COUNTIF('Rel.Conjunts-Sistemes'!$B:$B,$B14)) -> 1 | AS14: =IF(B14="","",COUNTIF('Dominis de dades'!$B:$B,$D14)) -> 1
B15: Registre general d'entrada i sortida de documents | C15: Flux de documents de la corporació (presencial i online) amb indicació del canal d'entrada/sortida, tipus de document i classificació. | D15: Activitat administrativa | E15: =IF(D15="","-",IF(ISERROR(VLOOKUP(D15,DominisDades,3,0)),"<<Domini erroni>>",VLOOKUP(D15,DominisDades,3,0))) -> Govern i administració | AP15: =AVERAGE(SUMIF(AnàlisiRiscos,AC15,AnàlisiRiscosGrau),SUMIF(AnàlisiRiscos,AD15,AnàlisiRiscosGrau),SUMIF(AnàlisiRiscos,AE15,AnàlisiRiscosGrau),SUMIF(AnàlisiRiscos,AF15,AnàlisiRiscosGrau),SUMIF(AnàlisiRiscos,AG15,AnàlisiRiscosGrau),SUMIF(AnàlisiRiscos,AH15,AnàlisiRiscosGrau),SUMIF(AnàlisiRiscos,AI15,AnàlisiRiscosGrau),SUMIF(AnàlisiRiscos,AJ15,AnàlisiRiscosGrau),SUMIF(AnàlisiRiscos,AK15,AnàlisiRiscosGrau),SUMIF(AnàlisiRiscos,AL15,AnàlisiRiscosGrau),SUMIF(AnàlisiRiscos,AM15,AnàlisiRiscosGrau),SUMIF(AnàlisiRiscos,AN15,AnàlisiRiscosGrau),SUMIF(AnàlisiRiscos,AO15,AnàlisiRiscosGrau)) -> 0 | AR15: =IF(B15="","",COUNTIF('Rel.Conjunts-Sistemes'!$B:$B,$B15)) -> 1 | AS15: =IF(B15="","",COUNTIF('Dominis de dades'!$B:$B,$D15)) -> 1
B16: Registre municipal de convenis i acords institucionals | C16: Llistat i detall de convenis signats per l'Ajuntament amb altres administracions, entitats del tercer sector o empreses. | D16: Secretaria | E16: =IF(D16="","-",IF(ISERROR(VLOOKUP(D16,DominisDades,3,0)),"<<Domini erroni>>",VLOOKUP(D16,DominisDades,3,0))) -> Govern i administració | AP16: =AVERAGE(SUMIF(AnàlisiRiscos,AC16,AnàlisiRiscosGrau),SUMIF(AnàlisiRiscos,AD16,AnàlisiRiscosGrau),SUMIF(AnàlisiRiscos,AE16,AnàlisiRiscosGrau),SUMIF(AnàlisiRiscos,AF16,AnàlisiRiscosGrau),SUMIF(AnàlisiRiscos,AG16,AnàlisiRiscosGrau),SUMIF(AnàlisiRiscos,AH16,AnàlisiRiscosGrau),SUMIF(AnàlisiRiscos,AI16,AnàlisiRiscosGrau),SUMIF(AnàlisiRiscos,AJ16,AnàlisiRiscosGrau),SUMIF(AnàlisiRiscos,AK16,AnàlisiRiscosGrau),SUMIF(AnàlisiRiscos,AL16,AnàlisiRiscosGrau),SUMIF(AnàlisiRiscos,AM16,AnàlisiRiscosGrau),SUMIF(AnàlisiRiscos,AN16,AnàlisiRiscosGrau),SUMIF(AnàlisiRiscos,AO16,AnàlisiRiscosGrau)) -> 0 | AR16: =IF(B16="","",COUNTIF('Rel.Conjunts-Sistemes'!$B:$B,$B16)) -> 1 | AS16: =IF(B16="","",COUNTIF('Dominis de dades'!$B:$B,$D16)) -> 1
B17: Taulell d'anuncis i edictes oficials | C17: Registre de les publicacions obligatòries, ordenances aprovades, anuncis de licitació i notificacions exposades al tauler digital. | D17: Secretaria | E17: =IF(D17="","-",IF(ISERROR(VLOOKUP(D17,DominisDades,3,0)),"<<Domini erroni>>",VLOOKUP(D17,DominisDades,3,0))) -> Govern i administració | AP17: =AVERAGE(SUMIF(AnàlisiRiscos,AC17,AnàlisiRiscosGrau),SUMIF(AnàlisiRiscos,AD17,AnàlisiRiscosGrau),SUMIF(AnàlisiRiscos,AE17,AnàlisiRiscosGrau),SUMIF(AnàlisiRiscos,AF17,AnàlisiRiscosGrau),SUMIF(AnàlisiRiscos,AG17,AnàlisiRiscosGrau),SUMIF(AnàlisiRiscos,AH17,AnàlisiRiscosGrau),SUMIF(AnàlisiRiscos,AI17,AnàlisiRiscosGrau),SUMIF(AnàlisiRiscos,AJ17,AnàlisiRiscosGrau),SUMIF(AnàlisiRiscos,AK17,AnàlisiRiscosGrau),SUMIF(AnàlisiRiscos,AL17,AnàlisiRiscosGrau),SUMIF(AnàlisiRiscos,AM17,AnàlisiRiscosGrau),SUMIF(AnàlisiRiscos,AN17,AnàlisiRiscosGrau),SUMIF(AnàlisiRiscos,AO17,AnàlisiRiscosGrau)) -> 0 | AR17: =IF(B17="","",COUNTIF('Rel.Conjunts-Sistemes'!$B:$B,$B17)) -> 1 | AS17: =IF(B17="","",COUNTIF('Dominis de dades'!$B:$B,$D17)) -> 1
B18: Quadre de classificació documental | C18: Estructura jeràrquica de referència utilitzada per a l'organització, codificació i emmagatzematgede la informació dins de l'organització. | D18: Secretaria | E18: =IF(D18="","-",IF(ISERROR(VLOOKUP(D18,DominisDades,3,0)),"<<Domini erroni>>",VLOOKUP(D18,DominisDades,3,0))) -> Govern i administració | AP18: =AVERAGE(SUMIF(AnàlisiRiscos,AC18,AnàlisiRiscosGrau),SUMIF(AnàlisiRiscos,AD18,AnàlisiRiscosGrau),SUMIF(AnàlisiRiscos,AE18,AnàlisiRiscosGrau),SUMIF(AnàlisiRiscos,AF18,AnàlisiRiscosGrau),SUMIF(AnàlisiRiscos,AG18,AnàlisiRiscosGrau),SUMIF(AnàlisiRiscos,AH18,AnàlisiRiscosGrau),SUMIF(AnàlisiRiscos,AI18,AnàlisiRiscosGrau),SUMIF(AnàlisiRiscos,AJ18,AnàlisiRiscosGrau),SUMIF(AnàlisiRiscos,AK18,AnàlisiRiscosGrau),SUMIF(AnàlisiRiscos,AL18,AnàlisiRiscosGrau),SUMIF(AnàlisiRiscos,AM18,AnàlisiRiscosGrau),SUMIF(AnàlisiRiscos,AN18,AnàlisiRiscosGrau),SUMIF(AnàlisiRiscos,AO18,AnàlisiRiscosGrau)) -> 0 | AR18: =IF(B18="","",COUNTIF('Rel.Conjunts-Sistemes'!$B:$B,$B18)) -> 1 | AS18: =IF(B18="","",COUNTIF('Dominis de dades'!$B:$B,$D18)) -> 1
B19: Resultats electorals per mesa i secció censal | C19: Resultats històrics d'eleccions (municipals, autonòmiques, generals) desglossats per partits, vots en blanc, nuls i abstenció per mesa. | D19: Secretaria | E19: =IF(D19="","-",IF(ISERROR(VLOOKUP(D19,DominisDades,3,0)),"<<Domini erroni>>",VLOOKUP(D19,DominisDades,3,0))) -> Govern i administració | AP19: =AVERAGE(SUMIF(AnàlisiRiscos,AC19,AnàlisiRiscosGrau),SUMIF(AnàlisiRiscos,AD19,AnàlisiRiscosGrau),SUMIF(AnàlisiRiscos,AE19,AnàlisiRiscosGrau),SUMIF(AnàlisiRiscos,AF19,AnàlisiRiscosGrau),SUMIF(AnàlisiRiscos,AG19,AnàlisiRiscosGrau),SUMIF(AnàlisiRiscos,AH19,AnàlisiRiscosGrau),SUMIF(AnàlisiRiscos,AI19,AnàlisiRiscosGrau),SUMIF(AnàlisiRiscos,AJ19,AnàlisiRiscosGrau),SUMIF(AnàlisiRiscos,AK19,AnàlisiRiscosGrau),SUMIF(AnàlisiRiscos,AL19,AnàlisiRiscosGrau),SUMIF(AnàlisiRiscos,AM19,AnàlisiRiscosGrau),SUMIF(AnàlisiRiscos,AN19,AnàlisiRiscosGrau),SUMIF(AnàlisiRiscos,AO19,AnàlisiRiscosGrau)) -> 0 | AR19: =IF(B19="","",COUNTIF('Rel.Conjunts-Sistemes'!$B:$B,$B19)) -> 1 | AS19: =IF(B19="","",COUNTIF('Dominis de dades'!$B:$B,$D19)) -> 1
B20: Registre municipal de parelles de fet | C20: Llistat històric i vigent de les inscripcions d'unions civils no matrimonials formalitzades a l'ajuntament. | D20: Secretaria | E20: =IF(D20="","-",IF(ISERROR(VLOOKUP(D20,DominisDades,3,0)),"<<Domini erroni>>",VLOOKUP(D20,DominisDades,3,0))) -> Govern i administració | AP20: =AVERAGE(SUMIF(AnàlisiRiscos,AC20,AnàlisiRiscosGrau),SUMIF(AnàlisiRiscos,AD20,AnàlisiRiscosGrau),SUMIF(AnàlisiRiscos,AE20,AnàlisiRiscosGrau),SUMIF(AnàlisiRiscos,AF20,AnàlisiRiscosGrau),SUMIF(AnàlisiRiscos,AG20,AnàlisiRiscosGrau),SUMIF(AnàlisiRiscos,AH20,AnàlisiRiscosGrau),SUMIF(AnàlisiRiscos,AI20,AnàlisiRiscosGrau),SUMIF(AnàlisiRiscos,AJ20,AnàlisiRiscosGrau),SUMIF(AnàlisiRiscos,AK20,AnàlisiRiscosGrau),SUMIF(AnàlisiRiscos,AL20,AnàlisiRiscosGrau),SUMIF(AnàlisiRiscos,AM20,AnàlisiRiscosGrau),SUMIF(AnàlisiRiscos,AN20,AnàlisiRiscosGrau),SUMIF(AnàlisiRiscos,AO20,AnàlisiRiscosGrau)) -> 0 | AR20: =IF(B20="","",COUNTIF('Rel.Conjunts-Sistemes'!$B:$B,$B20)) -> 1 | AS20: =IF(B20="","",COUNTIF('Dominis de dades'!$B:$B,$D20)) -> 1
B21: Subvencions i ajuts atorgats | C21: Registre oficial de subvencions concedides a entitats i ciutadans, estructurat segons els camps de la Base de Dades Nacional de Subvencions (BDNS). | D21: Contractació, convenis i subvencions | E21: =IF(D21="","-",IF(ISERROR(VLOOKUP(D21,DominisDades,3,0)),"<<Domini erroni>>",VLOOKUP(D21,DominisDades,3,0))) -> Govern i administració | AP21: =AVERAGE(SUMIF(AnàlisiRiscos,AC21,AnàlisiRiscosGrau),SUMIF(AnàlisiRiscos,AD21,AnàlisiRiscosGrau),SUMIF(AnàlisiRiscos,AE21,AnàlisiRiscosGrau),SUMIF(AnàlisiRiscos,AF21,AnàlisiRiscosGrau),SUMIF(AnàlisiRiscos,AG21,AnàlisiRiscosGrau),SUMIF(AnàlisiRiscos,AH21,AnàlisiRiscosGrau),SUMIF(AnàlisiRiscos,AI21,AnàlisiRiscosGrau),SUMIF(AnàlisiRiscos,AJ21,AnàlisiRiscosGrau),SUMIF(AnàlisiRiscos,AK21,AnàlisiRiscosGrau),SUMIF(AnàlisiRiscos,AL21,AnàlisiRiscosGrau),SUMIF(AnàlisiRiscos,AM21,AnàlisiRiscosGrau),SUMIF(AnàlisiRiscos,AN21,AnàlisiRiscosGrau),SUMIF(AnàlisiRiscos,AO21,AnàlisiRiscosGrau)) -> 0 | AR21: =IF(B21="","",COUNTIF('Rel.Conjunts-Sistemes'!$B:$B,$B21)) -> 1 | AS21: =IF(B21="","",COUNTIF('Dominis de dades'!$B:$B,$D21)) -> 1
... B119: Tramitació administrativa | C119: Conjunt de dades amb el detall dels expedients administratius, el seu estat, tipus d'interessat, sèrie documental, temps de resolució entre d'altres | D119: Activitat administrativa | E119: =IF(D119="","-",IF(ISERROR(VLOOKUP(D119,DominisDades,3,0)),"<<Domini erroni>>",VLOOKUP(D119,DominisDades,3,0))) -> Govern i administració | AP119: =AVERAGE(SUMIF(AnàlisiRiscos,AC119,AnàlisiRiscosGrau),SUMIF(AnàlisiRiscos,AD119,AnàlisiRiscosGrau),SUMIF(AnàlisiRiscos,AE119,AnàlisiRiscosGrau),SUMIF(AnàlisiRiscos,AF119,AnàlisiRiscosGrau),SUMIF(AnàlisiRiscos,AG119,AnàlisiRiscosGrau),SUMIF(AnàlisiRiscos,AH119,AnàlisiRiscosGrau),SUMIF(AnàlisiRiscos,AI119,AnàlisiRiscosGrau),SUMIF(AnàlisiRiscos,AJ119,AnàlisiRiscosGrau),SUMIF(AnàlisiRiscos,AK119,AnàlisiRiscosGrau),SUMIF(AnàlisiRiscos,AL119,AnàlisiRiscosGrau),SUMIF(AnàlisiRiscos,AM119,AnàlisiRiscosGrau),SUMIF(AnàlisiRiscos,AN119,AnàlisiRiscosGrau),SUMIF(AnàlisiRiscos,AO119,AnàlisiRiscosGrau)) -> 0 | AR119: =IF(B119="","",COUNTIF('Rel.Conjunts-Sistemes'!$B:$B,$B119)) -> 0 | AS119: =IF(B119="","",COUNTIF('Dominis de dades'!$B:$B,$D119)) -> 1
E120: =IF(D120="","-",IF(ISERROR(VLOOKUP(D120,DominisDades,3,0)),"<<Domini erroni>>",VLOOKUP(D120,DominisDades,3,0))) -> - | AP120: =AVERAGE(SUMIF(AnàlisiRiscos,AC120,AnàlisiRiscosGrau),SUMIF(AnàlisiRiscos,AD120,AnàlisiRiscosGrau),SUMIF(AnàlisiRiscos,AE120,AnàlisiRiscosGrau),SUMIF(AnàlisiRiscos,AF120,AnàlisiRiscosGrau),SUMIF(AnàlisiRiscos,AG120,AnàlisiRiscosGrau),SUMIF(AnàlisiRiscos,AH120,AnàlisiRiscosGrau),SUMIF(AnàlisiRiscos,AI120,AnàlisiRiscosGrau),SUMIF(AnàlisiRiscos,AJ120,AnàlisiRiscosGrau),SUMIF(AnàlisiRiscos,AK120,AnàlisiRiscosGrau),SUMIF(AnàlisiRiscos,AL120,AnàlisiRiscosGrau),SUMIF(AnàlisiRiscos,AM120,AnàlisiRiscosGrau),SUMIF(AnàlisiRiscos,AN120,AnàlisiRiscosGrau),SUMIF(AnàlisiRiscos,AO120,AnàlisiRiscosGrau)) -> 0 | AR120: =IF(B120="","",COUNTIF('Rel.Conjunts-Sistemes'!$B:$B,$B120)) | AS120: =IF(B120="","",COUNTIF('Dominis de dades'!$B:$B,$D120))
E121: =IF(D121="","-",IF(ISERROR(VLOOKUP(D121,DominisDades,3,0)),"<<Domini erroni>>",VLOOKUP(D121,DominisDades,3,0))) -> - | AP121: =AVERAGE(SUMIF(AnàlisiRiscos,AC121,AnàlisiRiscosGrau),SUMIF(AnàlisiRiscos,AD121,AnàlisiRiscosGrau),SUMIF(AnàlisiRiscos,AE121,AnàlisiRiscosGrau),SUMIF(AnàlisiRiscos,AF121,AnàlisiRiscosGrau),SUMIF(AnàlisiRiscos,AG121,AnàlisiRiscosGrau),SUMIF(AnàlisiRiscos,AH121,AnàlisiRiscosGrau),SUMIF(AnàlisiRiscos,AI121,AnàlisiRiscosGrau),SUMIF(AnàlisiRiscos,AJ121,AnàlisiRiscosGrau),SUMIF(AnàlisiRiscos,AK121,AnàlisiRiscosGrau),SUMIF(AnàlisiRiscos,AL121,AnàlisiRiscosGrau),SUMIF(AnàlisiRiscos,AM121,AnàlisiRiscosGrau),SUMIF(AnàlisiRiscos,AN121,AnàlisiRiscosGrau),SUMIF(AnàlisiRiscos,AO121,AnàlisiRiscosGrau)) -> 0 | AR121: =IF(B121="","",COUNTIF('Rel.Conjunts-Sistemes'!$B:$B,$B121)) | AS121: =IF(B121="","",COUNTIF('Dominis de dades'!$B:$B,$D121))
E122: =IF(D122="","-",IF(ISERROR(VLOOKUP(D122,DominisDades,3,0)),"<<Domini erroni>>",VLOOKUP(D122,DominisDades,3,0))) -> - | AP122: =AVERAGE(SUMIF(AnàlisiRiscos,AC122,AnàlisiRiscosGrau),SUMIF(AnàlisiRiscos,AD122,AnàlisiRiscosGrau),SUMIF(AnàlisiRiscos,AE122,AnàlisiRiscosGrau),SUMIF(AnàlisiRiscos,AF122,AnàlisiRiscosGrau),SUMIF(AnàlisiRiscos,AG122,AnàlisiRiscosGrau),SUMIF(AnàlisiRiscos,AH122,AnàlisiRiscosGrau),SUMIF(AnàlisiRiscos,AI122,AnàlisiRiscosGrau),SUMIF(AnàlisiRiscos,AJ122,AnàlisiRiscosGrau),SUMIF(AnàlisiRiscos,AK122,AnàlisiRiscosGrau),SUMIF(AnàlisiRiscos,AL122,AnàlisiRiscosGrau),SUMIF(AnàlisiRiscos,AM122,AnàlisiRiscosGrau),SUMIF(AnàlisiRiscos,AN122,AnàlisiRiscosGrau),SUMIF(AnàlisiRiscos,AO122,AnàlisiRiscosGrau)) -> 0 | AR122: =IF(B122="","",COUNTIF('Rel.Conjunts-Sistemes'!$B:$B,$B122)) | AS122: =IF(B122="","",COUNTIF('Dominis de dades'!$B:$B,$D122))
E123: =IF(D123="","-",IF(ISERROR(VLOOKUP(D123,DominisDades,3,0)),"<<Domini erroni>>",VLOOKUP(D123,DominisDades,3,0))) -> - | AP123: =AVERAGE(SUMIF(AnàlisiRiscos,AC123,AnàlisiRiscosGrau),SUMIF(AnàlisiRiscos,AD123,AnàlisiRiscosGrau),SUMIF(AnàlisiRiscos,AE123,AnàlisiRiscosGrau),SUMIF(AnàlisiRiscos,AF123,AnàlisiRiscosGrau),SUMIF(AnàlisiRiscos,AG123,AnàlisiRiscosGrau),SUMIF(AnàlisiRiscos,AH123,AnàlisiRiscosGrau),SUMIF(AnàlisiRiscos,AI123,AnàlisiRiscosGrau),SUMIF(AnàlisiRiscos,AJ123,AnàlisiRiscosGrau),SUMIF(AnàlisiRiscos,AK123,AnàlisiRiscosGrau),SUMIF(AnàlisiRiscos,AL123,AnàlisiRiscosGrau),SUMIF(AnàlisiRiscos,AM123,AnàlisiRiscosGrau),SUMIF(AnàlisiRiscos,AN123,AnàlisiRiscosGrau),SUMIF(AnàlisiRiscos,AO123,AnàlisiRiscosGrau)) -> 0 | AR123: =IF(B123="","",COUNTIF('Rel.Conjunts-Sistemes'!$B:$B,$B123)) | AS123: =IF(B123="","",COUNTIF('Dominis de dades'!$B:$B,$D123))
E124: =IF(D124="","-",IF(ISERROR(VLOOKUP(D124,DominisDades,3,0)),"<<Domini erroni>>",VLOOKUP(D124,DominisDades,3,0))) -> - | AP124: =AVERAGE(SUMIF(AnàlisiRiscos,AC124,AnàlisiRiscosGrau),SUMIF(AnàlisiRiscos,AD124,AnàlisiRiscosGrau),SUMIF(AnàlisiRiscos,AE124,AnàlisiRiscosGrau),SUMIF(AnàlisiRiscos,AF124,AnàlisiRiscosGrau),SUMIF(AnàlisiRiscos,AG124,AnàlisiRiscosGrau),SUMIF(AnàlisiRiscos,AH124,AnàlisiRiscosGrau),SUMIF(AnàlisiRiscos,AI124,AnàlisiRiscosGrau),SUMIF(AnàlisiRiscos,AJ124,AnàlisiRiscosGrau),SUMIF(AnàlisiRiscos,AK124,AnàlisiRiscosGrau),SUMIF(AnàlisiRiscos,AL124,AnàlisiRiscosGrau),SUMIF(AnàlisiRiscos,AM124,AnàlisiRiscosGrau),SUMIF(AnàlisiRiscos,AN124,AnàlisiRiscosGrau),SUMIF(AnàlisiRiscos,AO124,AnàlisiRiscosGrau)) -> 0 | AR124: =IF(B124="","",COUNTIF('Rel.Conjunts-Sistemes'!$B:$B,$B124)) | AS124: =IF(B124="","",COUNTIF('Dominis de dades'!$B:$B,$D124))
E125: =IF(D125="","-",IF(ISERROR(VLOOKUP(D125,DominisDades,3,0)),"<<Domini erroni>>",VLOOKUP(D125,DominisDades,3,0))) -> - | AP125: =AVERAGE(SUMIF(AnàlisiRiscos,AC125,AnàlisiRiscosGrau),SUMIF(AnàlisiRiscos,AD125,AnàlisiRiscosGrau),SUMIF(AnàlisiRiscos,AE125,AnàlisiRiscosGrau),SUMIF(AnàlisiRiscos,AF125,AnàlisiRiscosGrau),SUMIF(AnàlisiRiscos,AG125,AnàlisiRiscosGrau),SUMIF(AnàlisiRiscos,AH125,AnàlisiRiscosGrau),SUMIF(AnàlisiRiscos,AI125,AnàlisiRiscosGrau),SUMIF(AnàlisiRiscos,AJ125,AnàlisiRiscosGrau),SUMIF(AnàlisiRiscos,AK125,AnàlisiRiscosGrau),SUMIF(AnàlisiRiscos,AL125,AnàlisiRiscosGrau),SUMIF(AnàlisiRiscos,AM125,AnàlisiRiscosGrau),SUMIF(AnàlisiRiscos,AN125,AnàlisiRiscosGrau),SUMIF(AnàlisiRiscos,AO125,AnàlisiRiscosGrau)) -> 0 | AR125: =IF(B125="","",COUNTIF('Rel.Conjunts-Sistemes'!$B:$B,$B125)) | AS125: =IF(B125="","",COUNTIF('Dominis de dades'!$B:$B,$D125))
E126: =IF(D126="","-",IF(ISERROR(VLOOKUP(D126,DominisDades,3,0)),"<<Domini erroni>>",VLOOKUP(D126,DominisDades,3,0))) -> - | AP126: =AVERAGE(SUMIF(AnàlisiRiscos,AC126,AnàlisiRiscosGrau),SUMIF(AnàlisiRiscos,AD126,AnàlisiRiscosGrau),SUMIF(AnàlisiRiscos,AE126,AnàlisiRiscosGrau),SUMIF(AnàlisiRiscos,AF126,AnàlisiRiscosGrau),SUMIF(AnàlisiRiscos,AG126,AnàlisiRiscosGrau),SUMIF(AnàlisiRiscos,AH126,AnàlisiRiscosGrau),SUMIF(AnàlisiRiscos,AI126,AnàlisiRiscosGrau),SUMIF(AnàlisiRiscos,AJ126,AnàlisiRiscosGrau),SUMIF(AnàlisiRiscos,AK126,AnàlisiRiscosGrau),SUMIF(AnàlisiRiscos,AL126,AnàlisiRiscosGrau),SUMIF(AnàlisiRiscos,AM126,AnàlisiRiscosGrau),SUMIF(AnàlisiRiscos,AN126,AnàlisiRiscosGrau),SUMIF(AnàlisiRiscos,AO126,AnàlisiRiscosGrau)) -> 0 | AR126: =IF(B126="","",COUNTIF('Rel.Conjunts-Sistemes'!$B:$B,$B126)) | AS126: =IF(B126="","",COUNTIF('Dominis de dades'!$B:$B,$D126))
E127: =IF(D127="","-",IF(ISERROR(VLOOKUP(D127,DominisDades,3,0)),"<<Domini erroni>>",VLOOKUP(D127,DominisDades,3,0))) -> - | AP127: =AVERAGE(SUMIF(AnàlisiRiscos,AC127,AnàlisiRiscosGrau),SUMIF(AnàlisiRiscos,AD127,AnàlisiRiscosGrau),SUMIF(AnàlisiRiscos,AE127,AnàlisiRiscosGrau),SUMIF(AnàlisiRiscos,AF127,AnàlisiRiscosGrau),SUMIF(AnàlisiRiscos,AG127,AnàlisiRiscosGrau),SUMIF(AnàlisiRiscos,AH127,AnàlisiRiscosGrau),SUMIF(AnàlisiRiscos,AI127,AnàlisiRiscosGrau),SUMIF(AnàlisiRiscos,AJ127,AnàlisiRiscosGrau),SUMIF(AnàlisiRiscos,AK127,AnàlisiRiscosGrau),SUMIF(AnàlisiRiscos,AL127,AnàlisiRiscosGrau),SUMIF(AnàlisiRiscos,AM127,AnàlisiRiscosGrau),SUMIF(AnàlisiRiscos,AN127,AnàlisiRiscosGrau),SUMIF(AnàlisiRiscos,AO127,AnàlisiRiscosGrau)) -> 0 | AR127: =IF(B127="","",COUNTIF('Rel.Conjunts-Sistemes'!$B:$B,$B127)) | AS127: =IF(B127="","",COUNTIF('Dominis de dades'!$B:$B,$D127))
E128: =IF(D128="","-",IF(ISERROR(VLOOKUP(D128,DominisDades,3,0)),"<<Domini erroni>>",VLOOKUP(D128,DominisDades,3,0))) -> - | AP128: =AVERAGE(SUMIF(AnàlisiRiscos,AC128,AnàlisiRiscosGrau),SUMIF(AnàlisiRiscos,AD128,AnàlisiRiscosGrau),SUMIF(AnàlisiRiscos,AE128,AnàlisiRiscosGrau),SUMIF(AnàlisiRiscos,AF128,AnàlisiRiscosGrau),SUMIF(AnàlisiRiscos,AG128,AnàlisiRiscosGrau),SUMIF(AnàlisiRiscos,AH128,AnàlisiRiscosGrau),SUMIF(AnàlisiRiscos,AI128,AnàlisiRiscosGrau),SUMIF(AnàlisiRiscos,AJ128,AnàlisiRiscosGrau),SUMIF(AnàlisiRiscos,AK128,AnàlisiRiscosGrau),SUMIF(AnàlisiRiscos,AL128,AnàlisiRiscosGrau),SUMIF(AnàlisiRiscos,AM128,AnàlisiRiscosGrau),SUMIF(AnàlisiRiscos,AN128,AnàlisiRiscosGrau),SUMIF(AnàlisiRiscos,AO128,AnàlisiRiscosGrau)) -> 0 | AR128: =IF(B128="","",COUNTIF('Rel.Conjunts-Sistemes'!$B:$B,$B128)) | AS128: =IF(B128="","",COUNTIF('Dominis de dades'!$B:$B,$D128))
E129: =IF(D129="","-",IF(ISERROR(VLOOKUP(D129,DominisDades,3,0)),"<<Domini erroni>>",VLOOKUP(D129,DominisDades,3,0))) -> - | AP129: =AVERAGE(SUMIF(AnàlisiRiscos,AC129,AnàlisiRiscosGrau),SUMIF(AnàlisiRiscos,AD129,AnàlisiRiscosGrau),SUMIF(AnàlisiRiscos,AE129,AnàlisiRiscosGrau),SUMIF(AnàlisiRiscos,AF129,AnàlisiRiscosGrau),SUMIF(AnàlisiRiscos,AG129,AnàlisiRiscosGrau),SUMIF(AnàlisiRiscos,AH129,AnàlisiRiscosGrau),SUMIF(AnàlisiRiscos,AI129,AnàlisiRiscosGrau),SUMIF(AnàlisiRiscos,AJ129,AnàlisiRiscosGrau),SUMIF(AnàlisiRiscos,AK129,AnàlisiRiscosGrau),SUMIF(AnàlisiRiscos,AL129,AnàlisiRiscosGrau),SUMIF(AnàlisiRiscos,AM129,AnàlisiRiscosGrau),SUMIF(AnàlisiRiscos,AN129,AnàlisiRiscosGrau),SUMIF(AnàlisiRiscos,AO129,AnàlisiRiscosGrau)) -> 0 | AR129: =IF(B129="","",COUNTIF('Rel.Conjunts-Sistemes'!$B:$B,$B129)) | AS129: =IF(B129="","",COUNTIF('Dominis de dades'!$B:$B,$D129))
E130: =IF(D130="","-",IF(ISERROR(VLOOKUP(D130,DominisDades,3,0)),"<<Domini erroni>>",VLOOKUP(D130,DominisDades,3,0))) -> - | AP130: =AVERAGE(SUMIF(AnàlisiRiscos,AC130,AnàlisiRiscosGrau),SUMIF(AnàlisiRiscos,AD130,AnàlisiRiscosGrau),SUMIF(AnàlisiRiscos,AE130,AnàlisiRiscosGrau),SUMIF(AnàlisiRiscos,AF130,AnàlisiRiscosGrau),SUMIF(AnàlisiRiscos,AG130,AnàlisiRiscosGrau),SUMIF(AnàlisiRiscos,AH130,AnàlisiRiscosGrau),SUMIF(AnàlisiRiscos,AI130,AnàlisiRiscosGrau),SUMIF(AnàlisiRiscos,AJ130,AnàlisiRiscosGrau),SUMIF(AnàlisiRiscos,AK130,AnàlisiRiscosGrau),SUMIF(AnàlisiRiscos,AL130,AnàlisiRiscosGrau),SUMIF(AnàlisiRiscos,AM130,AnàlisiRiscosGrau),SUMIF(AnàlisiRiscos,AN130,AnàlisiRiscosGrau),SUMIF(AnàlisiRiscos,AO130,AnàlisiRiscosGrau)) -> 0 | AR130: =IF(B130="","",COUNTIF('Rel.Conjunts-Sistemes'!$B:$B,$B130)) | AS130: =IF(B130="","",COUNTIF('Dominis de dades'!$B:$B,$D130))
E131: =IF(D131="","-",IF(ISERROR(VLOOKUP(D131,DominisDades,3,0)),"<<Domini erroni>>",VLOOKUP(D131,DominisDades,3,0))) -> - | AP131: =AVERAGE(SUMIF(AnàlisiRiscos,AC131,AnàlisiRiscosGrau),SUMIF(AnàlisiRiscos,AD131,AnàlisiRiscosGrau),SUMIF(AnàlisiRiscos,AE131,AnàlisiRiscosGrau),SUMIF(AnàlisiRiscos,AF131,AnàlisiRiscosGrau),SUMIF(AnàlisiRiscos,AG131,AnàlisiRiscosGrau),SUMIF(AnàlisiRiscos,AH131,AnàlisiRiscosGrau),SUMIF(AnàlisiRiscos,AI131,AnàlisiRiscosGrau),SUMIF(AnàlisiRiscos,AJ131,AnàlisiRiscosGrau),SUMIF(AnàlisiRiscos,AK131,AnàlisiRiscosGrau),SUMIF(AnàlisiRiscos,AL131,AnàlisiRiscosGrau),SUMIF(AnàlisiRiscos,AM131,AnàlisiRiscosGrau),SUMIF(AnàlisiRiscos,AN131,AnàlisiRiscosGrau),SUMIF(AnàlisiRiscos,AO131,AnàlisiRiscosGrau)) -> 0 | AR131: =IF(B131="","",COUNTIF('Rel.Conjunts-Sistemes'!$B:$B,$B131)) | AS131: =IF(B131="","",COUNTIF('Dominis de dades'!$B:$B,$D131))
... E200: =IF(D200="","-",IF(ISERROR(VLOOKUP(D200,DominisDades,3,0)),"<<Domini erroni>>",VLOOKUP(D200,DominisDades,3,0))) -> - | AP200: =AVERAGE(SUMIF(AnàlisiRiscos,AC200,AnàlisiRiscosGrau),SUMIF(AnàlisiRiscos,AD200,AnàlisiRiscosGrau),SUMIF(AnàlisiRiscos,AE200,AnàlisiRiscosGrau),SUMIF(AnàlisiRiscos,AF200,AnàlisiRiscosGrau),SUMIF(AnàlisiRiscos,AG200,AnàlisiRiscosGrau),SUMIF(AnàlisiRiscos,AH200,AnàlisiRiscosGrau),SUMIF(AnàlisiRiscos,AI200,AnàlisiRiscosGrau),SUMIF(AnàlisiRiscos,AJ200,AnàlisiRiscosGrau),SUMIF(AnàlisiRiscos,AK200,AnàlisiRiscosGrau),SUMIF(AnàlisiRiscos,AL200,AnàlisiRiscosGrau),SUMIF(AnàlisiRiscos,AM200,AnàlisiRiscosGrau),SUMIF(AnàlisiRiscos,AN200,AnàlisiRiscosGrau),SUMIF(AnàlisiRiscos,AO200,AnàlisiRiscosGrau)) -> 0 | AR200: =IF(B200="","",COUNTIF('Rel.Conjunts-Sistemes'!$B:$B,$B200)) | AS200: =IF(B200="","",COUNTIF('Dominis de dades'!$B:$B,$D200))

Sheet Rel.Conjunts-Sistemes
B5: Relacions de Conjunts de dades amb sistemes | E5: PENDENTS DE DADES COHERENTS
B8: Conjunt de dades | C8: Sistema de dades | D8: Descripció de la relació | E8: Control conjunts de dades | F8: Control sistemes d'informació | G8: Control relacións correctes
B9: Sol·licitants d'ocupació del servei local d'ocupació | C9: Sistema per a la gestió de serveis locals d’ocupació (XALOC) | D9: Ajut | E9: =IF('Rel.Conjunts-Sistemes'!B9="","",IF(COUNTIF(ConjuntsDades,'Rel.Conjunts-Sistemes'!B9)>0,"OK","Conjunt de dades erroni")) -> OK | F9: =IF('Rel.Conjunts-Sistemes'!C9="","",IF(COUNTIF(Sistemes,'Rel.Conjunts-Sistemes'!C9)>0,"OK","Conjunt de dades erroni")) -> OK | G9: =IF(AND(E9="",F9=""),"",IF(AND(E9="OK",F9="OK"),"OK","Error")) -> OK
B10: Ofertes de treball del servei local d'ocupació | C10: Sistema per a la gestió de serveis locals d’ocupació (XALOC) | D10: Sol·licitud d'ajut | E10: =IF('Rel.Conjunts-Sistemes'!B10="","",IF(COUNTIF(ConjuntsDades,'Rel.Conjunts-Sistemes'!B10)>0,"OK","Conjunt de dades erroni")) -> OK | F10: =IF('Rel.Conjunts-Sistemes'!C10="","",IF(COUNTIF(Sistemes,'Rel.Conjunts-Sistemes'!C10)>0,"OK","Conjunt de dades erroni")) -> OK | G10: =IF(AND(E10="",F10=""),"",IF(AND(E10="OK",F10="OK"),"OK","Error")) -> OK
B11: Cens de locals comercials buits | C11: Eina per al càlcul del copagament SSAD i teleassistència | D11: Persona sol·licitant d'ajut | E11: =IF('Rel.Conjunts-Sistemes'!B11="","",IF(COUNTIF(ConjuntsDades,'Rel.Conjunts-Sistemes'!B11)>0,"OK","Conjunt de dades erroni")) -> OK | F11: =IF('Rel.Conjunts-Sistemes'!C11="","",IF(COUNTIF(Sistemes,'Rel.Conjunts-Sistemes'!C11)>0,"OK","Conjunt de dades erroni")) -> OK | G11: =IF(AND(E11="",F11=""),"",IF(AND(E11="OK",F11="OK"),"OK","Error")) -> OK
B12: Cens d'empreses, comerços i establiments | C12: Eina per al càlcul del copagament SSAD i teleassistència | D12: Persones que estan inscrites al registre de voluntaris | E12: =IF('Rel.Conjunts-Sistemes'!B12="","",IF(COUNTIF(ConjuntsDades,'Rel.Conjunts-Sistemes'!B12)>0,"OK","Conjunt de dades erroni")) -> OK | F12: =IF('Rel.Conjunts-Sistemes'!C12="","",IF(COUNTIF(Sistemes,'Rel.Conjunts-Sistemes'!C12)>0,"OK","Conjunt de dades erroni")) -> OK | G12: =IF(AND(E12="",F12=""),"",IF(AND(E12="OK",F12="OK"),"OK","Error")) -> OK
B13: Polígons de l'activitat econòmica i industrial | C13: Registre d'activitats econòmiques (GIA) | D13: Documentació ajut aportada | E13: =IF('Rel.Conjunts-Sistemes'!B13="","",IF(COUNTIF(ConjuntsDades,'Rel.Conjunts-Sistemes'!B13)>0,"OK","Conjunt de dades erroni")) -> OK | F13: =IF('Rel.Conjunts-Sistemes'!C13="","",IF(COUNTIF(Sistemes,'Rel.Conjunts-Sistemes'!C13)>0,"OK","Conjunt de dades erroni")) -> OK | G13: =IF(AND(E13="",F13=""),"",IF(AND(E13="OK",F13="OK"),"OK","Error")) -> OK
B14: Tramitació i expedients administratius | C14: Registre d'analítiques de la qualitat de l’aigua | D14: Resolució ajut | E14: =IF('Rel.Conjunts-Sistemes'!B14="","",IF(COUNTIF(ConjuntsDades,'Rel.Conjunts-Sistemes'!B14)>0,"OK","Conjunt de dades erroni")) -> OK | F14: =IF('Rel.Conjunts-Sistemes'!C14="","",IF(COUNTIF(Sistemes,'Rel.Conjunts-Sistemes'!C14)>0,"OK","Conjunt de dades erroni")) -> OK | G14: =IF(AND(E14="",F14=""),"",IF(AND(E14="OK",F14="OK"),"OK","Error")) -> OK
B15: Registre general d'entrada i sortida de documents | C15: Sistema per a la gestió de serveis locals d’ocupació (XALOC) | E15: =IF('Rel.Conjunts-Sistemes'!B15="","",IF(COUNTIF(ConjuntsDades,'Rel.Conjunts-Sistemes'!B15)>0,"OK","Conjunt de dades erroni")) -> OK | F15: =IF('Rel.Conjunts-Sistemes'!C15="","",IF(COUNTIF(Sistemes,'Rel.Conjunts-Sistemes'!C15)>0,"OK","Conjunt de dades erroni")) -> OK | G15: =IF(AND(E15="",F15=""),"",IF(AND(E15="OK",F15="OK"),"OK","Error")) -> OK
B16: Registre municipal de convenis i acords institucionals | E16: =IF('Rel.Conjunts-Sistemes'!B16="","",IF(COUNTIF(ConjuntsDades,'Rel.Conjunts-Sistemes'!B16)>0,"OK","Conjunt de dades erroni")) -> OK | F16: =IF('Rel.Conjunts-Sistemes'!C16="","",IF(COUNTIF(Sistemes,'Rel.Conjunts-Sistemes'!C16)>0,"OK","Conjunt de dades erroni")) | G16: =IF(AND(E16="",F16=""),"",IF(AND(E16="OK",F16="OK"),"OK","Error")) -> Error
B17: Taulell d'anuncis i edictes oficials | E17: =IF('Rel.Conjunts-Sistemes'!B17="","",IF(COUNTIF(ConjuntsDades,'Rel.Conjunts-Sistemes'!B17)>0,"OK","Conjunt de dades erroni")) -> OK | F17: =IF('Rel.Conjunts-Sistemes'!C17="","",IF(COUNTIF(Sistemes,'Rel.Conjunts-Sistemes'!C17)>0,"OK","Conjunt de dades erroni")) | G17: =IF(AND(E17="",F17=""),"",IF(AND(E17="OK",F17="OK"),"OK","Error")) -> Error
B18: Quadre de classificació documental | E18: =IF('Rel.Conjunts-Sistemes'!B18="","",IF(COUNTIF(ConjuntsDades,'Rel.Conjunts-Sistemes'!B18)>0,"OK","Conjunt de dades erroni")) -> OK | F18: =IF('Rel.Conjunts-Sistemes'!C18="","",IF(COUNTIF(Sistemes,'Rel.Conjunts-Sistemes'!C18)>0,"OK","Conjunt de dades erroni")) | G18: =IF(AND(E18="",F18=""),"",IF(AND(E18="OK",F18="OK"),"OK","Error")) -> Error
B19: Resultats electorals per mesa i secció censal | E19: =IF('Rel.Conjunts-Sistemes'!B19="","",IF(COUNTIF(ConjuntsDades,'Rel.Conjunts-Sistemes'!B19)>0,"OK","Conjunt de dades erroni")) -> OK | F19: =IF('Rel.Conjunts-Sistemes'!C19="","",IF(COUNTIF(Sistemes,'Rel.Conjunts-Sistemes'!C19)>0,"OK","Conjunt de dades erroni")) | G19: =IF(AND(E19="",F19=""),"",IF(AND(E19="OK",F19="OK"),"OK","Error")) -> Error
B20: Registre Municipal de Parelles de Fet | E20: =IF('Rel.Conjunts-Sistemes'!B20="","",IF(COUNTIF(ConjuntsDades,'Rel.Conjunts-Sistemes'!B20)>0,"OK","Conjunt de dades erroni")) -> OK | F20: =IF('Rel.Conjunts-Sistemes'!C20="","",IF(COUNTIF(Sistemes,'Rel.Conjunts-Sistemes'!C20)>0,"OK","Conjunt de dades erroni")) | G20: =IF(AND(E20="",F20=""),"",IF(AND(E20="OK",F20="OK"),"OK","Error")) -> Error
B21: Subvencions i ajuts Atorgats | E21: =IF('Rel.Conjunts-Sistemes'!B21="","",IF(COUNTIF(ConjuntsDades,'Rel.Conjunts-Sistemes'!B21)>0,"OK","Conjunt de dades erroni")) -> OK | F21: =IF('Rel.Conjunts-Sistemes'!C21="","",IF(COUNTIF(Sistemes,'Rel.Conjunts-Sistemes'!C21)>0,"OK","Conjunt de dades erroni")) | G21: =IF(AND(E21="",F21=""),"",IF(AND(E21="OK",F21="OK"),"OK","Error")) -> Error
B22: Tresoreria: pagaments, ingressos i indicador de morositat | E22: =IF('Rel.Conjunts-Sistemes'!B22="","",IF(COUNTIF(ConjuntsDades,'Rel.Conjunts-Sistemes'!B22)>0,"OK","Conjunt de dades erroni")) -> OK | F22: =IF('Rel.Conjunts-Sistemes'!C22="","",IF(COUNTIF(Sistemes,'Rel.Conjunts-Sistemes'!C22)>0,"OK","Conjunt de dades erroni")) | G22: =IF(AND(E22="",F22=""),"",IF(AND(E22="OK",F22="OK"),"OK","Error")) -> Error
B23: Pressupost municipal i previsions financeres | E23: =IF('Rel.Conjunts-Sistemes'!B23="","",IF(COUNTIF(ConjuntsDades,'Rel.Conjunts-Sistemes'!B23)>0,"OK","Conjunt de dades erroni")) -> OK | F23: =IF('Rel.Conjunts-Sistemes'!C23="","",IF(COUNTIF(Sistemes,'Rel.Conjunts-Sistemes'!C23)>0,"OK","Conjunt de dades erroni")) | G23: =IF(AND(E23="",F23=""),"",IF(AND(E23="OK",F23="OK"),"OK","Error")) -> Error
B24: Execució del presupost municipal | E24: =IF('Rel.Conjunts-Sistemes'!B24="","",IF(COUNTIF(ConjuntsDades,'Rel.Conjunts-Sistemes'!B24)>0,"OK","Conjunt de dades erroni")) -> OK | F24: =IF('Rel.Conjunts-Sistemes'!C24="","",IF(COUNTIF(Sistemes,'Rel.Conjunts-Sistemes'!C24)>0,"OK","Conjunt de dades erroni")) | G24: =IF(AND(E24="",F24=""),"",IF(AND(E24="OK",F24="OK"),"OK","Error")) -> Error
B25: Padrons fiscals i tributs locals | E25: =IF('Rel.Conjunts-Sistemes'!B25="","",IF(COUNTIF(ConjuntsDades,'Rel.Conjunts-Sistemes'!B25)>0,"OK","Conjunt de dades erroni")) -> OK | F25: =IF('Rel.Conjunts-Sistemes'!C25="","",IF(COUNTIF(Sistemes,'Rel.Conjunts-Sistemes'!C25)>0,"OK","Conjunt de dades erroni")) | G25: =IF(AND(E25="",F25=""),"",IF(AND(E25="OK",F25="OK"),"OK","Error")) -> Error
B26: Relació de contractes menors | E26: =IF('Rel.Conjunts-Sistemes'!B26="","",IF(COUNTIF(ConjuntsDades,'Rel.Conjunts-Sistemes'!B26)>0,"OK","Conjunt de dades erroni")) -> OK | F26: =IF('Rel.Conjunts-Sistemes'!C26="","",IF(COUNTIF(Sistemes,'Rel.Conjunts-Sistemes'!C26)>0,"OK","Conjunt de dades erroni")) | G26: =IF(AND(E26="",F26=""),"",IF(AND(E26="OK",F26="OK"),"OK","Error")) -> Error
B27: Licitacions de l'ens local | E27: =IF('Rel.Conjunts-Sistemes'!B27="","",IF(COUNTIF(ConjuntsDades,'Rel.Conjunts-Sistemes'!B27)>0,"OK","Conjunt de dades erroni")) -> OK | F27: =IF('Rel.Conjunts-Sistemes'!C27="","",IF(COUNTIF(Sistemes,'Rel.Conjunts-Sistemes'!C27)>0,"OK","Conjunt de dades erroni")) | G27: =IF(AND(E27="",F27=""),"",IF(AND(E27="OK",F27="OK"),"OK","Error")) -> Error
... B111: Cens d'Activitats de Risc i Plans d'Autoprotecció (PAU) | E111: =IF('Rel.Conjunts-Sistemes'!B111="","",IF(COUNTIF(ConjuntsDades,'Rel.Conjunts-Sistemes'!B111)>0,"OK","Conjunt de dades erroni")) -> Conjunt de dades erroni | F111: =IF('Rel.Conjunts-Sistemes'!C111="","",IF(COUNTIF(Sistemes,'Rel.Conjunts-Sistemes'!C111)>0,"OK","Conjunt de dades erroni")) | G111: =IF(AND(E111="",F111=""),"",IF(AND(E111="OK",F111="OK"),"OK","Error")) -> Error
E112: =IF('Rel.Conjunts-Sistemes'!B112="","",IF(COUNTIF(ConjuntsDades,'Rel.Conjunts-Sistemes'!B112)>0,"OK","Conjunt de dades erroni")) | F112: =IF('Rel.Conjunts-Sistemes'!C112="","",IF(COUNTIF(Sistemes,'Rel.Conjunts-Sistemes'!C112)>0,"OK","Conjunt de dades erroni")) | G112: =IF(AND(E112="",F112=""),"",IF(AND(E112="OK",F112="OK"),"OK","Error"))
E113: =IF('Rel.Conjunts-Sistemes'!B113="","",IF(COUNTIF(ConjuntsDades,'Rel.Conjunts-Sistemes'!B113)>0,"OK","Conjunt de dades erroni")) | F113: =IF('Rel.Conjunts-Sistemes'!C113="","",IF(COUNTIF(Sistemes,'Rel.Conjunts-Sistemes'!C113)>0,"OK","Conjunt de dades erroni")) | G113: =IF(AND(E113="",F113=""),"",IF(AND(E113="OK",F113="OK"),"OK","Error"))
E114: =IF('Rel.Conjunts-Sistemes'!B114="","",IF(COUNTIF(ConjuntsDades,'Rel.Conjunts-Sistemes'!B114)>0,"OK","Conjunt de dades erroni")) | F114: =IF('Rel.Conjunts-Sistemes'!C114="","",IF(COUNTIF(Sistemes,'Rel.Conjunts-Sistemes'!C114)>0,"OK","Conjunt de dades erroni")) | G114: =IF(AND(E114="",F114=""),"",IF(AND(E114="OK",F114="OK"),"OK","Error"))
E115: =IF('Rel.Conjunts-Sistemes'!B115="","",IF(COUNTIF(ConjuntsDades,'Rel.Conjunts-Sistemes'!B115)>0,"OK","Conjunt de dades erroni")) | F115: =IF('Rel.Conjunts-Sistemes'!C115="","",IF(COUNTIF(Sistemes,'Rel.Conjunts-Sistemes'!C115)>0,"OK","Conjunt de dades erroni")) | G115: =IF(AND(E115="",F115=""),"",IF(AND(E115="OK",F115="OK"),"OK","Error"))
E116: =IF('Rel.Conjunts-Sistemes'!B116="","",IF(COUNTIF(ConjuntsDades,'Rel.Conjunts-Sistemes'!B116)>0,"OK","Conjunt de dades erroni")) | F116: =IF('Rel.Conjunts-Sistemes'!C116="","",IF(COUNTIF(Sistemes,'Rel.Conjunts-Sistemes'!C116)>0,"OK","Conjunt de dades erroni")) | G116: =IF(AND(E116="",F116=""),"",IF(AND(E116="OK",F116="OK"),"OK","Error"))
E117: =IF('Rel.Conjunts-Sistemes'!B117="","",IF(COUNTIF(ConjuntsDades,'Rel.Conjunts-Sistemes'!B117)>0,"OK","Conjunt de dades erroni")) | F117: =IF('Rel.Conjunts-Sistemes'!C117="","",IF(COUNTIF(Sistemes,'Rel.Conjunts-Sistemes'!C117)>0,"OK","Conjunt de dades erroni")) | G117: =IF(AND(E117="",F117=""),"",IF(AND(E117="OK",F117="OK"),"OK","Error"))
E118: =IF('Rel.Conjunts-Sistemes'!B118="","",IF(COUNTIF(ConjuntsDades,'Rel.Conjunts-Sistemes'!B118)>0,"OK","Conjunt de dades erroni")) | F118: =IF('Rel.Conjunts-Sistemes'!C118="","",IF(COUNTIF(Sistemes,'Rel.Conjunts-Sistemes'!C118)>0,"OK","Conjunt de dades erroni")) | G118: =IF(AND(E118="",F118=""),"",IF(AND(E118="OK",F118="OK"),"OK","Error"))
E119: =IF('Rel.Conjunts-Sistemes'!B119="","",IF(COUNTIF(ConjuntsDades,'Rel.Conjunts-Sistemes'!B119)>0,"OK","Conjunt de dades erroni")) | F119: =IF('Rel.Conjunts-Sistemes'!C119="","",IF(COUNTIF(Sistemes,'Rel.Conjunts-Sistemes'!C119)>0,"OK","Conjunt de dades erroni")) | G119: =IF(AND(E119="",F119=""),"",IF(AND(E119="OK",F119="OK"),"OK","Error"))
E120: =IF('Rel.Conjunts-Sistemes'!B120="","",IF(COUNTIF(ConjuntsDades,'Rel.Conjunts-Sistemes'!B120)>0,"OK","Conjunt de dades erroni")) | F120: =IF('Rel.Conjunts-Sistemes'!C120="","",IF(COUNTIF(Sistemes,'Rel.Conjunts-Sistemes'!C120)>0,"OK","Conjunt de dades erroni")) | G120: =IF(AND(E120="",F120=""),"",IF(AND(E120="OK",F120="OK"),"OK","Error"))
E121: =IF('Rel.Conjunts-Sistemes'!B121="","",IF(COUNTIF(ConjuntsDades,'Rel.Conjunts-Sistemes'!B121)>0,"OK","Conjunt de dades erroni")) | F121: =IF('Rel.Conjunts-Sistemes'!C121="","",IF(COUNTIF(Sistemes,'Rel.Conjunts-Sistemes'!C121)>0,"OK","Conjunt de dades erroni")) | G121: =IF(AND(E121="",F121=""),"",IF(AND(E121="OK",F121="OK"),"OK","Error"))
E122: =IF('Rel.Conjunts-Sistemes'!B122="","",IF(COUNTIF(ConjuntsDades,'Rel.Conjunts-Sistemes'!B122)>0,"OK","Conjunt de dades erroni")) | F122: =IF('Rel.Conjunts-Sistemes'!C122="","",IF(COUNTIF(Sistemes,'Rel.Conjunts-Sistemes'!C122)>0,"OK","Conjunt de dades erroni")) | G122: =IF(AND(E122="",F122=""),"",IF(AND(E122="OK",F122="OK"),"OK","Error"))
E123: =IF('Rel.Conjunts-Sistemes'!B123="","",IF(COUNTIF(ConjuntsDades,'Rel.Conjunts-Sistemes'!B123)>0,"OK","Conjunt de dades erroni")) | F123: =IF('Rel.Conjunts-Sistemes'!C123="","",IF(COUNTIF(Sistemes,'Rel.Conjunts-Sistemes'!C123)>0,"OK","Conjunt de dades erroni")) | G123: =IF(AND(E123="",F123=""),"",IF(AND(E123="OK",F123="OK"),"OK","Error"))
... E200: =IF('Rel.Conjunts-Sistemes'!B200="","",IF(COUNTIF(ConjuntsDades,'Rel.Conjunts-Sistemes'!B200)>0,"OK","Conjunt de dades erroni")) | F200: =IF('Rel.Conjunts-Sistemes'!C200="","",IF(COUNTIF(Sistemes,'Rel.Conjunts-Sistemes'!C200)>0,"OK","Conjunt de dades erroni")) | G200: =IF(AND(E200="",F200=""),"",IF(AND(E200="OK",F200="OK"),"OK","Error"))

Sheet Qualitat
B5: Qualitat i completitut de l'inventari d'actius de dades
C7: Sistemes
D8: Sistemes identificats | E8: =COUNTA(Sistemes) -> 40
D9: Completitut informació | E9: =AVERAGE(Sistemes!C7:N7) -> 0.175 | F9: =IF(E9<0.9,"Falta un "&INT((1-E9)*1000)/10&"% de la informació descriptiva dels sistemes de dades identificats","") -> Falta un 82,5% de la informació descriptiva dels sistemes de dades identificats
D10: Sistemes amb informació de Conjunts de dades | E10: =E11/E8 -> 0.1 | F10: =IF(E8>E11,"Hi ha "&E8-E11&" sistemes sense cap Conjunt de dades identificat") -> Hi ha 36 sistemes sense cap Conjunt de dades identificat
D11: Sistemes amb Conjunts de dades | E11: {=ROWS(_xlfn.UNIQUE(_xlfn._xlws.FILTER(Rel_Sistemes_Conjunts,ControlRelacions="OK")))} -> 4
D12: Sistemes sense relacions correctes amb Conjunt de dades | E12: =E8-E11 -> 36
C15: Dominis de dades
D16: Dominis identificats | E16: =COUNTA(Dominis) -> 36
D17: Completitut informació | E17: =AVERAGE('Dominis de dades'!C6:E6) -> 0.97222222 | F17: =IF(E17<0.9,"Falta un "&INT((1-E17)*1000)/10&"% de la informació descriptiva dels dominis de dades identificats","")
D18: Dominis amb informació de conjunts de dades | E18: =E19/E16 -> 0.80555556 | F18: =IF(E16>E19,"Hi ha "&E16-E19&" dominis de dades sense cap conjunt de dades identificat") -> Hi ha 7 dominis de dades sense cap conjunt de dades identificat
D19: Dominis amb conjunts de dades | E19: =COUNTA(_xlfn.UNIQUE(Dominis_a_ConjuntsDades))-1 -> 29
D20: Dominis sense cap Conjunt de dades | E20: =E16-E19 -> 7
C23: Conjunts de dades
D24: Conjunts de dades identificats | E24: =COUNTA(ConjuntsDades) -> 111
D25: Completitut informació | E25: =AVERAGE('Conjunts de dades'!C6:AB6) -> 0.11607762 | F25: =IF(E25<0.9,"Falta un "&INT((1-E25)*1000)/10&"% de la informació descriptiva dels conjunts de dades identificats") -> Falta un 88,3% de la informació descriptiva dels conjunts de dades identificats
D26: Conjunts de dades relacionats amb Sistemes de dades | E26: =E27/E24 -> 0.063063063 | F26: =IF(E26<0.9,"Hi ha un "&INT((1-E26)*1000)/10&"% de conjunts de dades no relacionades amb sistemes de dades") -> Hi ha un 93,6% de conjunts de dades no relacionades amb sistemes de dades
D27: Relacions correctes Conjunts i Sistemes de dades | E27: =COUNTIF('Rel.Conjunts-Sistemes'!G:G,"OK") -> 7
D28: Relacions Conjunts i Sistemes de dades amb errors | E28: =COUNTIF('Rel.Conjunts-Sistemes'!G:G,"Error") -> 96

Sheet Llegenda
B4: Llegenda
B7: Sistemes d'informació | D7: Format
B8: Sistema de dades | C8: Nom amb què s’identifica el sistema o aplicació dins de l’organització. Ha de ser clar i recognoscible per a tots els equips. | D8: Text
B9: Descripció | C9: Explicació breu i entenedora de per a què serveix el sistema i quins processos o serveis municipals hi dona suport. Indica també des de quan conté dades. | D9: Text
B10: Tecnologies principals | C10: Tecnologies, programes, o plataformes principals utilitza el sistema. Això dona una idea senzilla del seu entorn tècnic. | D10: Text
B11: Proveïdor | C11: Nom de l’empresa o entitat que subministra el sistema, el manté o dona suport tècnic, addicionalment es pot afegeix el NIF. | D11: Text
B12: Tipus de servei | C12: Model de provisió i responsabilitat amb què es presta o s’utilitza el sistema, indicant el nivell de gestió que recau internament i quin sobre proveïdors externs. El tipus de servei pot ser: - On-premise, si es basa en infraestructura pròpia i l’ens local assumeix la gestió completa de maquinari, programari i dades. - IaaS, si un proveïdor extern facilita la infraestructura bàsica (servidors virtuals, emmagatzematge i xarxa), i l’ens local gestiona el sistema operatiu, el programari i les dades. - PaaS, si un proveïdor extern facilita la infraestructura i l’entorn de la plataforma (bàsica (sistema operatiu, bases de dades, entorns d'execució), i l’ens local gestiona el programari i les dades. - SaaS, si un proveïdor extern gestiona la totalitat de la solució, incloent-hi el programari. | D12: Selecció
B13: Arquitectura cloud | C13: Indica on s’allotja el sistema: en servidors municipals (local), en plataformes de núvol (cloud) o en un model mixt (híbrid). L’arquitectura pot ser: - On-premise (local), si el sistema s’allotja en servidors propis de l’ens local gestionats per ells mateixos i les dades no surten en cap moment de la infraestructura pròpia. - Pública (núvol públic), si el sistema s’allotja a la infraestructura d’un proveïdor de serveis al núvol de manera compartida amb altres clients amb un aïllament lògic. - Privada (núvol privat), si el sistema s’allotja a la infraestructura d’un proveïdor de serveis al núvol de dedicada en exclusiva a l’ens local. - Híbrida, si el sistema combina components allotjats de manera local amb components al núvol (públic o privat). | D13: Selecció
B14: Estat Sistema | C14: Situació actual del sistema dins del seu cicle de vida, indicant si està operatiu o en una altra fase. | D14: Selecció
B15: Data revisió estat | C15: Data en què es va revisar per última vegada l’estat del sistema, per garantir que la informació és actualitzada. | D15: Data
B16: És extern? | C16: El sistema d'informació és propi i l'administra l'ens local? | D16: Si / No
B17: Administrador del sistema (nom) | C17: Nom de la persona que gestiona i administra el sistema de dades actualment. És qui pot resoldre dubtes o incidències. | D17: Text
B18: Administrador del sistema (rol) | C18: Funció o responsabilitat que exerceix la persona administradora del sistema dins de l'organització. | D18: Text
B19: Sensibilitat de les dades | C19: Nivell de sensibilitat de la informació que tracta el sistema, rellevant per a la protecció de dades i el compliment normatiu. | D19: Selecció
... B24: Núm. Conjunts de dades | C24: Càlcul automàtic de quants conjunts de dades hi ha relacionats amb el sistema d'informació, es calcula a partir de les dades de la pestanya "Rel.Conjunts-Sistemes". Les caselles en vermell corresponen als registres que descriuen sistemes d'informació sense cap conjunt de dades relacionat. | D24: Calculat automàticament
B27: Dominis de dades | D27: Format
B28: Domini de dades | C28: Nom de la classificació lògica que permeten agrupar Conjunts de dades que comparteixen un mateix significat, àmbit temàtic o propòsit funcional. | D28: Text
B29: Descripció | C29: Una explicació clara i sintètica que ajuda a comprendre per què existeix el domini de dades i quin tipus d'informació recull, de manera que qualsevol persona el pugui interpretar sense dificultat. | D29: Text
B30: Àmbit | C30: És la categoria d’alt nivell que indica l’àmbit general al qual pertany el domini de dades, aquest pot agrupar més d'un domini de dades. | D30: Text
B31: Àrea propietària | C31: És l'àrea organitzativa de l’ens local que assumeix la responsabilitat funcional i operativa de les dades, més enllà del lloc on es trobin allotjades o gestionades. | D31: Text
B32: Núm. Conjunts de dades | C32: Càlcul automàtic de quants conjunts de dades hi ha relacionats amb el domini de dades, es calcula a partir de les dades de la pestanya "Conjunts de dades". Les caselles en vermell corresponen als registres que descriuen dominis de dades sense cap conjunt de dades relacionat. | D32: Calculat automàticament
B35: Conjunts de dades | D35: Format
B36: Nom Conjunt de dades | C36: Nom clar i específic que identifiqui de que permeti identificar el conjunt de dades dins l'ens local. | D36: Text
B37: Descripció | C37: Resumeix en una o dues frases què recull el conjunt de dades i per a què s'utilitza en el dia a dia. Indica els principals processos municipals on intervé i algun exemple d'ús, com ara informes, tramitació o atenció ciutadana. | D37: Text
B38: Domini de dades | C38: Indica el domini de dades al qual pertany el conjunt de dades, per exemple: serveis socials, via pública, hisenda o educació. | D38: Text
B39: Àrea propietària | C39: Tenint en compte la definició del domini de dades al que pertany, automàticament s'informa l'àrea organitzativa de l’ens local que assumeix la responsabilitat funcional i operativa de les dades. | D39: Calculat en funció del Domini de dades seleccionat
B40: Tipus conjunt de dades | C40: Indica el tipus de conjunt de dades, existeixen les següents possibilitats: - Dades de referència: dades amb la finalitat de facilitar la classificació i la gestió de la informació. - De negoci: dades que descriuen conceptes clau de l’ens local de manera precisa, estandarditzada i consistent. Aquests ajuden a contextualitzar les dades i asseguren que tots els usuaris tenen una comprensió comuna d’aquests. - Mestra: dades comunes i compartides a tota l’organització que descriuen conceptes clau per a l’ens local i proporcionen context per a la seva activitat. Representen perímetres determinats de dades, acotats de forma consensuada, i que serveixen com a referència transversal per a tota l'organització o una part. - Dades de referència / mestres no homogeneïtzades: dades que s'identifiquen com a rellevants per a ser considerades dades de referència / mestres, però que tenen un origen diferent a l'oficial. - Candidat a dades de referència / dades mestres: dada identificada com a possible dada de referència o mestra, que encara està en procés d'avaluació per determinar si compleix els criteris per ser-ho. | D40: Selecció
B41: Ús previst de les dades | C41: L'espai de treball on les dades són necessàries o es poden utilitzar, ja sigui dins un únic servei, compartides entre diverses àrees o en col·laboració amb entitats externes, indicant el nivell de coordinació que això comporta. L’abast organitzatiu pot ser: - Intern departamental - Intern transversal - Intern multiorganisme - Extern obert | D41: Selecció
B42: Conté dades personals? | C42: Marqueu "Sí" quan el conjunt de dades conté: - Noms, cognoms, DNI/NIF, adreça, telèfon, correu electrònic, matrícula, IP o qualsevol identificador d'expedient vinculat a una persona física concreta. - Dades pseudonimitzades o xifrades que l'ens pugui re-identificar amb informació addicional que ja posseeix. - Dades de contacte d'una persona física que actua en representació d'una persona jurídica (nom i cognoms del representant). | D42: Si / No
B43: Conté dades de gènere u orientació sexual? | C43: Marqueu "Sí" quan el conjunt de dades conté: - Registres de composició de meses electorals o participació política identificable. - Dades sobre creences religioses (p.e. menús escolars per motiu religiós, cementiris confessionals, cessió d'espais de culte). - Dades d'afiliació sindical (p.e. descompte de quota sindical en nòmina, crèdit horari sindical). - Dades de participació identificable en consultes o processos amb component ideològic explícit. | D43: Si / No
B44: Conté dades d'ideologia o creences? | C44: Marqueu "Sí" quan el conjunt de dades conté: - Dades específiques d'orientació sexual, identitat de gènere o nom sentit. - Dades recollides en serveis d'atenció LGTBI, protocols contra la LGTBI-fòbia o violència per raó d'orientació/identitat. - Informació sobre processos de transició de gènere. | D44: Si / No
B45: Conté dades biomètriques? | C45: Marqueu "Sí" quan el conjunt de dades conté: - Dades de control d'accés o de presència mitjançant empremta dactilar, reconeixement facial o de veu. - Signatura biomètrica dinàmica (captura de pressió, velocitat i traç, no una simple imatge escanejada). - Videovigilància únicament quan incorpora reconeixement facial automàtic actiu (identificació unívoca). | D45: Si / No
B46: Conté dades de salut? | C46: Marqueu "Sí" quan el conjunt de dades conté: - Certificats mèdics i informes de baixa laboral quan el motiu és identificable o se'n pot deduir el diagnòstic. - Graus de discapacitat o de dependència. - Dades de serveis socials relacionades amb addiccions, salut mental o atenció a la dependència. - Al·lèrgies o intoleràncies alimentàries en menjadors escolars o casals. - Dades de vacunació o d'aptitud física. | D46: Si / No
B47: Conté dades confidencials de l'ens local? | C47: Marqueu "Sí" quan el conjunt de dades conté: - Informes jurídics o dictàmens interns previs a una decisió, mentre no siguin públics. - Ofertes econòmiques d'empreses en processos de contractació encara no resolts. - Informes d'auditoria interna, control financer o intervenció amb detecció d'irregularitats. - Esborranys de pressupostos o plans urbanístics en fase d'estudi, previs a la seva aprovació. - Informació operativa de seguretat ciutadana no divulgable. | D47: Si / No
... B62: Reutilització de dades | C62: Si el conjunt es fa servir per a altres processos, serveis o informes, indiqueu a quins. | D62: Text
B63: Riscos associats | C63: Els riscos es defineixen segons la probabilitat i l’impacte que poden tenir: Probabilitat: - Baixa quan és improbable o no ha ocorregut en els darrers dos anys - Mitja quan és possible que el risc es materialitzi o ha ocorregut al menys un cop l'any. - Alta quan és altament probable o ha ocorregut diversos cops l'any. Impacte: - Baix quan l'impacte és assumible i no afecta dades sensibles. - Mig quan l'impacte és significatiu. - Alt quan l'impacte és greu i implica aturades de servei, costos econòmics o sancions, o afectació a dades sensibles.
B64: Incoherència de dades | C64: Existeix el risc de representar la mateixa dada de manera diferent en més d'un lloc? | D64: Selecció
B65: Informació desactualitzada | C65: Existeix el risc de que hi hagi dades que no reflecteixin la realitat actual? | D65: Selecció
B66: Publicació d'informació incorrecta | C66: Existeix el risc de que hi hagi dades que no hagin passat validacions de qualitat? | D66: Selecció
B67: Registres duplicats | C67: Existeix el risc de dades repetides? | D67: Selecció
B68: Accés a dades sensibles | C68: Existeix el risc de que algú, que no hagi de tenir accés, pugui accedir a dades sensibles? | D68: Selecció
B69: Accés o ús indegut | C69: Existeix el risc de algú pugui utilitzar les dades per a una finalitat diferent a l'autoritzada? | D69: Selecció
B70: Exposició de dades (menors, personals, sensibles o socials) | C70: Existeix el risc d'exposició indeguda de dades sensibles? | D70: Selecció
B71: Filtració o fuita de dades | C71: Existeix el risc de que les dades surtin de l'àmbit de control de l'ens local per error o per un atac? | D71: Selecció
B72: Indisponiblitat del sistema | C72: Existeix el risc de pèrdua de disponibilitat de les dades i dels sistemes? | D72: Selecció
B73: Pèrdua de dades | C73: Existeix el risc de pèrdua definitiva de dades? | D73: Selecció
B74: Falta de traçabilitat i evidències sobre la gestió de les dades | C74: Existeix el risc de no saber qui, quan i com s'ha fet un canvi a les dades? | D74: Selecció
B75: Falta de seguiment o auditories sobre accessos i usos | C75: Existeix el risc de que les dades i els accessos no siguin revisats o auditats de forma periòdica? | D75: Selecció
... B80: Núm. Dominis de dades | C80: Càlcul automàtic de si el dominis de dades relacionat al camp domini de dades és coherent amb els dominis de dades descrita a la pestanya "Dominis de dades". Les caselles en vermell corresponen als registres que descriuen conjunts de dades sense un domini de dades coherent. | D80: Calculat automàticament
B84: Entitats | D84: Format
B85: Nom Entitat | C85: Poseu un nom clar i fàcil d’entendre, que permeti identificar ràpidament de quina entitat es tracta sense haver de llegir cap detall addicional. | D85: Text
B86: Descripció | C86: Expliqueu en poques línies què representa aquesta entitat i en quin context del servei o procés es fa servir habitualment. | D86: Text
B87: És entitat global? | C87: Indiqueu si l’entitat és comuna a diversos àmbits o només s’utilitza en un context concret. | D87: Selecció
B88: Entitat global referida | C88: Quan no sigui global, especifiqueu a quina altra entitat queda vinculada o en depèn. | D88: Selecció de Entitat marcada com global
B89: Domini de dades principal | C89: Mostreu l’àmbit funcional o servei on aquesta entitat té sentit i on s’utilitza de forma natural. | D89: Selecció
B90: Àrea propietària principal | C90: Identifiqueu l’àrea o servei que vetlla perquè la informació sigui correcta i coherent amb les seves funcions. | D90: Calculat en funció del Domini de dades principal
B91: Sistema de dades d'orígen | C91: Escriviu el sistema principal del qual provenen les dades que formen aquesta entitat. | D91: Selecció
B92: Tipus d'informació | C92: Descriviu de manera general quin tipus d’informació conté: dades personals, operatives, organitzatives, etc. | D92: Selecció
B93: Responsable de l'entitat (Propietari de dades) | C93: Indiqueu qui és la persona que supervisa i valida el bon ús de la informació associada a l’entitat. | D93: Text
B94: Rol del responsable de l'entitat | C94: Expliqueu de manera breu quin paper té aquesta persona en la gestió, seguiment i qualitat de la informació. | D94: Text
B95: Nom del terme relacionat (Glossari) | C95: Poseu el terme del glossari que millor ajuda a comprendre què és l’entitat i com s’interpreta. | D95: Text
B96: Informació continguda | C96: Descriviu els elements principals que conté la informació i què aporten al servei o procés. | D96: Text
... B107: Reutilització de dades | C107: Expliqueu en quins processos, serveis o finalitats es reutilitzen aquestes dades habitualment. | D107: Text
B110: Relacions de Conjunts de dades amb entitats | D110: Format
B111: Conjunt de dades | C111: Indica l’àmbit o grup de dades al qual pertany la informació, normalment vinculat al procés o servei on es genera. | D111: Selecció
B112: Entitat | C112: Es refereix al tipus d’element implicat (persona, sol·licitud, documentació...). Ha de ser un concepte comprensible per qualsevol usuari. | D112: Selecció
B113: Descripció de la relació | C113: Explica amb una frase o dues quin és el vincle entre la dada i l’entitat. Ha de ser directe i evitar tecnicismes innecessaris. | D113: Text
B116: Atributs | D116: Format
B117: Nom Atribut | C117: Poseu un nom curt i entenedor que ajudi a identificar què és la dada dins l’entitat sense haver de revisar més camp detall. | D117: Text
B118: Descripció de l'atribut | C118: Expliqueu amb un parell de frases què representa la dada i en quin moment del procés és útil, pensant en algú que la vegi per primera vegada. | D118: Text
B119: Entitat | C119: Indiqueu a quina entitat pertany aquest atribut, és a dir, l’objecte principal del qual forma part (persona, sol·licitud, incidència…). | D119: Text
B120: Pertany a entitat global? | C120: Assenyaleu si aquest atribut forma part d'una entitat global o si és només complementari. | D120: Calculat en funció de l'Entitat
B121: És clau? | C121: Indiqueu si aquesta dada és imprescindible per identificar de manera única un registre dins l’entitat. | D121: Selecció
B122: Sistema | C122: Escriviu el sistema on es genera o manté el valor d’aquest atribut en el dia a dia. | D122: Selecció
B123: Tipus d'Atribut | C123: Descriviu breument el tipus general de la dada: text, número, data, codi… sense tecnicismes. | D123: Selecció
B124: Informació sensible | C124: Indiqueu si la dada pot contenir informació delicada segons la normativa o el seu contingut. | D124: Selecció
B125: Terme de negoci relacionat (Glossari) | C125: Escriviu el terme del glossari que ajuda a entendre millor el significat del camp. | D125: Text
B126: Format de base de dades | C126: Poseu el format tècnic que utilitza el sistema (ex.: text, número, data), només perquè l’usuari sàpiga què esperar. | D126: Text
B127: Admet valor nul? | C127: Indiqueu si el camp pot quedar buit en casos justificats o si sempre ha de tenir valor. | D127: Selecció
B128: Criteris de precisió | C128: Expliqueu quin grau d’exactitud o validació s’espera del valor perquè sigui correcte. | D128: Text
... B131: Criteris d'actualització | C131: Expliqueu en quines situacions es pot modificar la dada i cada quant pot canviar realment en el procés. | D131: Text
B132: Regla de validació | D132: Text
B133: Nivel qualitat esperada | D133: Text
B134: Catàleg de valors | D134: Text
B135: Origen | D135: Text
B136: Freqüència d'actualització | D136: Text
B137: Criticitat | D137: Selecció
B138: Usos principals de la dada | D138: Text
B139: Compartició amb altres sistemes | D139: Text
B160: Relacions entre Atributs
B161: Atribut | C161: Descripció | D161: Descripció
B162: Atribut d'origen | C162: Nom de l'atribut per al qual la relació serà SORTINT | D162: Nom de l'atribut per al qual la relació serà SORTINT
B163: Atribut de destinació | C163: Nom de l'atribut per al qual la relació serà ENTRANT | D163: Nom de l'atribut per al qual la relació serà ENTRANT
B164: Tipus relació | C164: Indica el tipus de relació que existeix entre els atributs origen i destinació | D164: Indica el tipus de relació que existeix entre els atributs origen i destinació
B165: Entitat d'origen | C165: Entitat a la què pertany l'atribut per al qual la relació serà SORTINT | D165: Entitat a la què pertany l'atribut per al qual la relació serà SORTINT
B166: Sistema d'origen | C166: Sistema on pertany l'entitat que conté l'atribut per al qual la relació serà SORTINT | D166: Sistema on pertany l'entitat que conté l'atribut per al qual la relació serà SORTINT
B167: Entitat de destinació | C167: Nom de l'entitat a la què pertany l'atribut per al qual la relació serà ENTRANT | D167: Nom de l'entitat a la què pertany l'atribut per al qual la relació serà ENTRANT
B168: Sistema de destinació | C168: Nom curt del sistema on pertany l'entitat que conté l'atribut per al qual la relació serà ENTRANT | D168: Nom curt del sistema on pertany l'entitat que conté l'atribut per al qual la relació serà ENTRANT

Sheet Relació inventaris
N1: Dominis de dades
B2: Relació inventaris | C2: I els atributs de l'inventari de la DIBA i de la GENE? I els que vam preveure nosaltres inicialment?
B4: Inventari | C4: Principal referència | D4: Detalls
B5: Sistemes | C5: Tarragona | D5: A Tarragona apareix de manera recurrent la columna “Sistema d’informació”, associada als conjunts de dades. Aquest patró es repeteix de forma implícita a Mataró (Sistema de Gestió de Bases de Dades, Tipus de sistema/aplicació) i a Sant Cugat (Sistema on es genera). El conjunt Sistemes recull aquesta coincidència transversal: el sistema sempre és present com a element clau. En aquest inventari hem inclòs la font de dades principal (sistema o aplicació de procedència), una descripció, així com informació tècnica i del proveïdor. Altres camps com l'administrador i rol del sistema, han estat inspirats en els camps Gestor, contacte_gestor, custodi, que apareixen a l'inventari de la DIBA
B6: Domini de dades | C6: Tarragona | D6: Tarragona disposa explícitament d’un inventari de Dominis de dades utilitzat per agrupar conjunts segons àmbits funcionals (padró, urbanisme, medi ambient, etc.). Allà podem trobar informació com Domini de dades, Descripció breu, Àrea municipal habitual que hem utilitzat per crear aquest inventari: Domini de dades, Descripció, Àrea propietària. Aquest mateix criteri de classificació funcional s’alinea amb enfocaments generals com els que promou DIBA. També s'inclouen altres termes com administrador i rol del sistema
B7: Conjunt de dades | C7: Tarragona + Mataró | D7: Tant Tarragona com Mataró treballen explícitament amb el concepte de conjunt de dades. A Tarragona forma part de l’inventari estructurat; a Mataró és l’eix central de l’Inventari de fonts d’informació, mitjançant el camp “Nom del conjunt de dades”, amb atributs de governança associats. Camps com Nom Conjunt de dades, Descripció, Domini de dades, Àrea propietària o Sistema d'informació d'origen principal, han estat agafats de l'inventari de Mataró. També s'inclouen altres termes com 'administrador i rol del conjunt de dades
B8: Entitats | C8: Sant Cugat | D8: L’inventari Entitats inclou diversos camps que no apareixen a cap dels inventaris de referència, ja que aquests treballen a nivell de domini o de conjunt de dades i no baixen al nivell d’unitat informativa. Entre aquests camps destaquen, per exemple: Entitat global referida, Sistema de dades d'orígen, etc. També s'inclouen altres termes com administrador i rol de l'entitat
B9: Rel.Conjunts-Entitats | C9: Elaboració pròpia | D9: Taula desenvolupada específicament per garantir la traçabilitat entre conjunts de dades i entitats, inspirada en les relacions de Sant Cugat i els criteris de traçabilitat de DIBA.
B10: Atributs | C10: Sant Cugat | D10: Sant Cugat descriu cada dada amb un conjunt ric de característiques: tipus de camp, obligatorietat, qualitat, dades personals, anonimització, reutilització, etc. Aquest nivell de detall coincideix plenament amb el concepte d’atribut.

Sheet Llistes
B1: Sistema de dades (CALCULAT - NO TOCAR) | D1: Domini de dades principal (CALCULAT - NO TOCAR) | F1: Conjunt de dades (CALCULAT - NO TOCAR) | H1: Tipus de servei | J1: Arquitectura Cloud | L1: Estat Sistema | N1: Sensibilitat de les dades | P1: Criticitat | R1: Àmbit | T1: Ús previst de les dades | V1: Tipus Conjunt de dades | X1: Tipus d'informació | AA1: Categoria alt valor | AC1: Cadència | AE1: Nivell d'accés | AG1: PERSISTENCIA | AI1: RETENCIO | AK1: Origen de les dades | AM1: Dades obertes | AO1: Categoria Conjunt de Dades | AQ1: És entitat global? | AS1: Entitat global referida | AU1: És Domini de dades principal? | AW1: És clau? | AY1: Tipus d'Atribut | BA1: Admet valor nul? | BC1: TipusRelEntitats | BE1: RelacióGlosari | BG1: Confidencialitat | BI1: Format | BK1: Seguretat | BM1: Sistemes d'informació | BO1: Reutilització de dades | BQ1: Prioritats | BS1: Anàlisi Riscos | BV1: Si No
B2: {=_xlfn._xlws.SORT(_xlfn.UNIQUE(Sistemes))} -> Catàleg de tràmits i eina de tramitació digital | D2: {=_xlfn._xlws.SORT(_xlfn.UNIQUE(Dominis))} -> Activitat administrativa | F2: {=_xlfn._xlws.SORT(_xlfn.UNIQUE(ConjuntsDades))} -> Abonaments de les instal·lacions esportives i piscines | H2: On-premise | J2: Pública | L2: En producció | N2: Baixa | P2: Baixa | R2: Govern i administració | T2: Intern departamental | V2: De negoci | X2: Dades personals | Y2: informen sobre persones físiques identificades o identificables (ciutadania, personal…) | AA2: Geoespacial | AC2: En temps real | AE2: Àrea | AG2: Dades transaccionals (es modifiquen constantment) | AI2: Arxiu després d'un període d'inactivitat | AK2: Declaracions de ciutadans | AM2: Si | AO2: Ajuntaments | AQ2: Si | AS2: <No aplica> | AU2: Si | AW2: Si | AY2: Dada mestre | BA2: Si | BC2: 1:1 | BE2: Jeràrquica (Un terme general (categoria) agrupa termes més específics) | BG2: No Personal | BI2: Text | BK2: Públic | BM2: BI | BO2: Planificació estratègica | BQ2: 1. Molt baixa | BS2: Probabilitat: Baixa Impacte: Baix (1) | BT2: 1 | BV2: Si
B3: Comptabilitat municipal | D3: Aigua i sanejament | F3: Accidents de trànsit urbà | H3: PaaS (plataforma com a servei) | J3: Híbrida | L3: Pendent d'actualització | N3: Mitjana | P3: Mitjana | R3: Gestió de l'espai públic | T3: Intern transversal | V3: Dades de referència | X3: Dades sensibles | Y3: dades amb impacte ètic, legal o reputacional si es divulguen (salut, orientació, menors…) | AA3: Observació de la terra i el medi ambient | AC3: Diària | AE3: Organització | AG3: Dades arxivades (ja no s'utilitzen activament, però es conserven) | AI3: Arxiu en un sistema separat | AK3: Sistemes municipals interns | AM3: No | AO3: Altres entitats | AQ3: No | AS3: {=_xlfn._xlws.SORT(_xlfn.UNIQUE(_xlfn._xlws.FILTER(Entitats,#REF!="Si")))} -> #NAME? | AU3: No | AW3: No | AY3: Dada de referència | BA3: No | BC3: 1:N | BE3: Àlies (Diferents termes que representen el mateix concepte dins del negoci) | BG3: Personal | BI3: Numèric | BK3: Intern | BM3: CRM ciutadà | BO3: Transparència | BQ3: 2. Baixa | BS3: Probabilitat: Baixa Impacte: Moderat (1) | BT3: 1 | BV3: No
B4: Control horari | D4: Atenció ciutadana | F4: Actes del ple i decrets d'Alcaldia | H4: IaaS (infraestructura com a servei) | J4: Privada | L4: Obsolet | N4: Alta (dades personals) | P4: Alta | R4: Serveis a les persones | T4: Intern multiorganisme | V4: Dades de referència / mestres no homogeneïtzades | X4: Dades públiques | Y4: informació no restringida, objecte de transparència o ús general | AA4: Meteorologia | AC4: Setmanal | AE4: Públiques | AG4: Dades històriques (es mantenen per consulta, però no es modifiquen) | AI4: Retenció segons normativa legal | AK4: Administracions supramunicipals | AM4: Parcialment | AO4: Anàlisi | AY4: Dada de negoci | BC4: N:1 | BE4: Dependència (Un terme només té sentit en funció d’un altre) | BG4: Personal privat | BI4: Decimal | BK4: Sensible | BM4: ERP | BO4: Optimització de serveis | BQ4: 3. Mitja | BS4: Probabilitat: Baixa Impacte: Alt (2) | BT4: 2 | BV4: Parcialment
B5: Eina de gestió de la participació | D5: Bon govern, transparència i participació | F5: Actuacions de desinfestació i control de plagues urbanes | H5: SaaS (software com a servei) | J5: On-premise | L5: Substitució planificada | N5: Alta (dades personals / bancàries) | R5: Corporatiu (Dades mestres i de referència) | T5: Extern obert | V5: Data mestra | X5: Dades financeres | Y5: rellevants per a gestió econòmica (pressupost, tributs, facturació, subvencions…) | AA5: Estadística | AC5: Quinzenal | AG5: No informat | AI5: Retenció per un període fix (ex. 1, 5, 10 anys) | AK5: Sensors o sistemes Iot | AM5: Previst a futur | AO5: Ciutadania | AY5: Metadada | BC5: N:M | BE5: Correspondència (Terme similar que pot tenir variacions en diferents departaments o sistemes) | BI5: Percentatge | BK5: Crític | BM5: Gestor d’activitats | BO5: Informes interns | BQ5: 4. Alta | BS5: Probabilitat: Mitja Impacte: Baix (1) | BT5: 1
B6: Eina per a la valoració de diagnosi social | D6: Cementiri i serveis funeraris | F6: Actuacions de manteniment en equipaments i via Pública | N6: Alta (dades especials) | V6: Candidat a dades de referència / dades mestres | X6: Dades de localització/geoespacials | Y6: referenciades a ubicació física (adreces, parcel·les, geoposicionament…) | AA6: Societats i propietat de societat | AC6: Mensual | AI6: Retenció segons polítiques internes | AK6: Empreses contractistes | AM6: Pendent d'anàlisi | AO6: Intern | AY6: Metadada de negoci | BI6: Fracció | BK6: Molt crític | BM6: Gestor del servei | BO6: Quadres de comandament | BQ6: 5. Molt alta | BS6: Probabilitat: Mitja Impacte: Moderat (3) | BT6: 3
B7: Eina per al càlcul del copagament SSAD i teleassistència | D7: Consum energètic | F7: Actuacions de millora i obres a la via pública | X7: Dades de servei/operacionals | Y7: relatives als serveis prestats, tràmits, processos o activitat interna | AA7: Mobilitat | AC7: Trimestral | AI7: Retenció indefinida (les dades no s'eliminen) | AK7: Varis | AY7: Metadada tècnica | BI7: Data | BM7: Inventari | BS7: Probabilitat: Mitja Impacte: Alt (4) | BT7: 4
B8: Enquesta retributiva per a ús municipal | D8: Contractació, convenis i subvencions | F8: Aforament i intensitat de trànsit al municipi | X8: Dades d’inventari/patrimoni | Y8: registres d’actius, equipaments, infraestructures, vehicles… | AA8: No aplica | AC8: Anual | AI8: No hi ha una política definida | AK8: No informat | AY8: Metadada operacional | BI8: Hora | BM8: Plataforma contractació | BS8: Probabilitat: Alta Impacte: Baix (3) | BT8: 3
B9: Gestió d'aparcaments | D9: Cultura i gestió del patrimoni cultural i històric (formulat anteriorment com Cultura i patrimoni) | F9: Agenda d'activitats i esdeveniments municipals | X9: Dades estadístiques/analítiques | Y9: formats agregats, anonimitzats o per a anàlisi, no directament identificables | AC9: Major a l'any | AI9: No informat | AY9: Metadada de qualitat | BI9: Data i Hora | BM9: Queixes i Suggeriments | BS9: Probabilitat: Alta Impacte: Moderat (4) | BT9: 4
B10: Gestió de cementiris | D10: Dades de referència (comú a tot l'ecosistema de dades de país) | F10: Atenció al col·lectiu LGTBI | X10: Dades d’organització/estructura | Y10: referides a organigrames, processos, rols o unitats | AY10: Metadada de seguretat/privadesa | BI10: Marca de temps | BM10: Sistema d'Informació Geogràfica | BS10: Probabilitat: Alta Impacte: Alt (4) | BT10: 4
B11: Gestió de l'inventari de bens mobles i inmobles | D11: Drets socials | F11: Atenció i intervenció en serveis socials | X11: Altres | Y11: si escau, especificar al camp “Observacions” | AY11: Metadada de govern | BI11: Booleà | BM11: Sistema operador
B12: Gestió de nòmines municipals | D12: Economia local, comerç i mercats | F12: Atenció Integral a les dones (Servei SIAD) | AY12: Dades de referència / mestres no homogeneïtzades
B13: Gestió de queixes i suggeriments | D13: Educació | F13: Avaluació i qualitat dels serveis públics | AY13: Candidata a dades de referència / dades mestres
B14: Gestió de representacions | D14: Esport | F14: Bústia de queixes, suggeriments i propostes
B15: Gestió de residus | D15: Formació i ocupació | F15: Calendari d'esdeveniments i curses esportives en el municipi
B16: Gestió de sancions | D16: Govern i organització | F16: Cartografia de la xarxa viària i carrers
B17: Gestió de serveis bibliotecaris | D17: Habitatge | F17: Catàleg d'aplicacions i llicències corporatives
B18: Gestió de subvencions | D18: Hisenda | F18: Catàleg de protecció del patrimoni arquitectònic i paisatgístic
B19: Gestió dels plans de protecció civil municipal | D19: Incidències de la via pública | F19: Cens d'activitas de risc i plans d'autoprotecció (PAU)
B20: Gestió dels sistemes de videovigilància | D20: Informació i comunicació | F20: Cens de locals comercials buits
B21: Gestió d'expedients atenció primària serveis socials | D21: Informació territorial i geoespacial | F21: Cens d'empreses, comerços i establiments
B22: Gestió d'incidències a la via pública i manteniment d'equipaments | D22: Medi ambient | F22: Cens d'instal·lacions esportives (públiques i privades)
B23: Gestió policial d'atestats | D23: Mobilitat i trànsit | F23: Control analític de fonts públiques i piscines
B24: GIAM | D24: Neteja viària | F24: Control analític de l'aigua de consum humà
B25: Padró municipal d’habitants | D25: Obres públiques i manteniment | F25: Dades d'alumnes d'escoles municipals
... B37: Sistema de gestió de personal | D37: Urbanisme i planejament | F37: Fonts locals, pous i punts d'Aigua
B38: Sistema de gestió d'impostos municipals | D38: 0 | F38: Gestió de la cita prèvia municipal | J38: Arquitectura Cloud
B39: Sistema per a la gestió de serveis locals d’ocupació (XALOC) | F39: Gestió de nòmines i costos de personal
B40: Tramitació d’expedients administratius | F40: Gestió de personal: plantilla i relació de llocs de treball (RLT)
B41: Web municipal | F41: Indicadors de l'atenció ciutadana presencial (OAC)
B42: 0 | F42: Indicadors de sostenibilitat: consums i canvi climàtic
F43: Infraestructura de vies ciclables i vehicles de mobilitat personal (VMP)
F44: Inscripcions i formació de treballadors públics
F45: Inspecció tècnica d'edificis (ITE)
F46: Inspeccions sanitàries d'establiments alimentaris i de consum
F47: Interaccions i consultes del conversador virtual (Chatbot)
F48: Intermediació en deutes de l'habitatge
F49: Inventari d'actius tecnològics (Actius TIC)
F50: Inventari d'activitats del municipi
F51: Inventari de béns culturals d'interès local (BCIL)
F52: Inventari de béns mobles, immobles i vehicles
F53: Inventari de finques agrícoles i forestals
F54: Inventari de l'arbrat urbà i zones verdes
... F112: Xarxes d'infraestructures de serveis i subministraments
F113: 0
