Workbook
Name AbastOrganitzatiu: Llistes!$T$2:$T$6
Name AccionsGD: [1]Llistes!#REF!
Name AccionsGD: [2]Llistes!#REF!
Name AltValor: Llistes!$AA$2:$AA$10
Name Àmbit: Llistes!$P$2:$P$6
Name AnàlisiRiscos: Llistes!$BS$2:$BS$10
Name AnàlisiRiscosGrau: [3]Llistes!$BT$2:$BT$10
Name Àrea: [1]Llistes!$G$3:$G$173
Name Àrea: Llistes!$N$5:$N$37
Name ArquitecturaCloud: Llistes!$F$2:$F$7
Name Atributs: #REF!
Name Cadencia: Llistes!$AC$2:$AC$10
Name Catàleg_de_protecció_del_patrimoni_arquitectònic_i_paisatgístic: 'Conjunts de dades'!$B$119
Name CategoriaConjuntDades: Llistes!$AO$2:$AO$7
Name Confidencialitat: Llistes!$BG$2:$BG$5
Name ConjuntsDades: 'Conjunts de dades'!$B$9:$B$112
Name Criticitat: Llistes!$L$2:$L$6
Name DadesObertes: Llistes!$AM$2:$AM$8
Name Dominis: 'Dominis de dades'!$B$9:$B$62
Name Dominis_a_Atributs: #REF!
Name Dominis_a_ConjuntsDades: 'Conjunts de dades'!$D$9:$D$112
Name Dominis_a_Entitats: #REF!
Name DominisDades: 'Dominis de dades'!$B$9:$E$62
Name Entitats: #REF!
Name Entitats_a_Atributs: #REF!
Name EntitatsGlobals: Llistes!$AS$2:$AS$38
Name EstatSistemes: Llistes!$H$2:$H$12
Name Format: Llistes!$BI$2:$BI$12
Name Impacte: [1]Llistes!$K$3:$K$5
Name Impacte: [2]Llistes!$K$3:$K$5
Name LlistaDominisDades: Llistes!$N$2:$N$37
Name NivellAccés: Llistes!$AE$2:$AE$10
Name Nom_Conjunt_de_dades: 'Conjunts de dades'!$B$8:$B$119
Name Origens: Llistes!$AK$2:$AK$9
Name Orígens: Llistes!$AK$2:$AK$7
Name Persistencia: Llistes!$AG$2:$AG$12
Name Prioritats: Llistes!$BQ$2:$BQ$6
Name Rel_ConjuntsDades_Entitats: 'Rel.Conjunts-Sistemes'!$B$9:$B$66
Name Rel_ConjuntsDades_Entitats: #REF!
Name Rel_Entitats_ConjuntsDades: 'Rel.Conjunts-Sistemes'!$D$9:$D$66
Name Rel_Entitats_ConjuntsDades: #REF!
Name Rel_Sistemes_Conjunts: 'Rel.Conjunts-Sistemes'!$D$9:$D$66
Name RelacióGlosari: Llistes!$BE$2:$BE$8
Name RelacionsConjuntsDades: 'Rel.Conjunts-Sistemes'!$B$9:$B$66
Name RelacionsConjuntsDades: #REF!
Name Retenció: Llistes!$AI$3:$AI$12
Name Reutilitzacio: Llistes!$BO$2:$BO$8
Name Riscos: #REF!
Name Seguretat: Llistes!$BK$2:$BK$7
Name SensibilitatDades: Llistes!$J$2:$J$8
Name SiNo: Llistes!$BV$2:$BV$3
Name SiNoParcialment: Llistes!$BV$2:$BV$4
Name Sistemes: Sistemes!$B$9:$B$67
Name Sistemes_a_Entitats: #REF!
Name TipusAtributs: Llistes!$AY$2:$AY$15
Name TipusConjunt: Llistes!$V$2:$V$7
Name TipusInformació: Llistes!$X$2:$X$12
Name TipusRelEntitats: Llistes!$BC$2:$BC$7
Name TipusServei: Llistes!$D$2:$D$7

Sheet Instruccions
B5: Instruccions
C8: La plantilla de l'inventari d'actius de dades s'organitza en les pestanyes següents:
D10: Sistemes: Registre i descripció dels sistemes d'informació de l'ens local vinculats a les dades.
D11: Dominis de dades: Recull els dominis de dades més habituals en un ens local. Per a cadascun cal completar la informació específica del domini. Es poden afegir dominis addicionals que no figurin a la proposta inicial.
D12: Conjunts de dades: Identificació, registre i descripció dels conjunts de dades associats a cada domini.
D13: Entitats: Identificació, registre i descripció de les entitats vinculades als conjunts de dades.
D14: Rel. Conjunts–Entitats: Documentació de les relacions entre conjunts de dades i entitats.
D15: Atributs: Registre i descripció dels atributs de cada entitat.
D16: Rel. Entitats–Entitats: Documentació de les relacions entre entitats.
D17: Qualitat: Avaluació de la completitud i la coherència de l'inventari.
D18: Llegenda: Instruccions per complimentar correctament totes les pestanyes.
D19: Relació inventaris: Fonts i referents tinguts en compte en el disseny de la plantilla.
D20: Llistes: Valors de referència vàlids per a les columnes amb valors restringits
C22: L'àmbit de suport en governança de dades municipal i el responsable de dades de l'ens local són els responsables de documentar, mantenir i gestionar l'inventari d'actius de dades.
C23: Dominis de dades. S'han agrupat en àmbits:
D25: Govern i administració: tot allò que té a veure amb la gestió administrativa.
D26: Gestió de l'espai públic: tot allò que te a veure amb la gestió de la ciutat (residus, clavegueram, informació geogràfica, etc.).
D27: Serveis a les persones: tot el que fa referència a serveis municipals.
D28: Corporatiu (dades mestres i de referència): Les dades de referència haurien de ser comunes a tot l'espai de dades

Sheet Sistemes
B5: Sistemes de dades
B7: =COUNTA(B$9:B$67) -> 41 | C7: =COUNTA(C$9:C$67)/$B$7 -> 0.48780488 | D7: =COUNTA(D$9:D$67)/$B$7 -> 0.6097561 | E7: =COUNTA(E$9:E$67)/$B$7 -> 0.95121951 | F7: =COUNTA(F$9:F$67)/$B$7 -> 0 | G7: =COUNTA(G$9:G$67)/$B$7 -> 0 | H7: =COUNTA(H$9:H$67)/$B$7 -> 0 | I7: =COUNTA(I$9:I$67)/$B$7 -> 0 | J7: =COUNTA(J$9:J$67)/$B$7 -> 0 | ... N7: =COUNTA(N$9:N$67)/$B$7 -> 0
B8: Sistema de dades | C8: Descripció | D8: Tecnologies principals | E8: Proveïdor | F8: Tipus de servei | G8: Arquitectura cloud | H8: Estat Sistema | I8: Data revisió estat | J8: Administrador del sistema (nom) | K8: Administrador del sistema (rol) | L8: Criticitat | M8: Integracions | N8: Model d’autenticació | O8: Núm. Conjunts de dades
B9: Padró municipal d’habitants | C9: Padró municipal d’habitants | D9: PMH - Berger levrault | E9: Diputació | O9: =IF(B9="","",COUNTIF('Rel.Conjunts-Sistemes'!$D:$D,$B9)) -> 0
B10: Enquesta retributiva per a ús municipal | C10: ERET Enquesta retributiva per a ús municipal | D10: Desenvolupament propi | E10: Diputació | O10: =IF(B10="","",COUNTIF('Rel.Conjunts-Sistemes'!$D:$D,$B10)) -> 0
B11: Tramitació d’expedients administratius | C11: SeTDIBA Registre i tramitació d’expedients als ajuntaments. | D11: Gestiona | E11: Diputació | O11: =IF(B11="","",COUNTIF('Rel.Conjunts-Sistemes'!$D:$D,$B11)) -> 0
B12: Registre d'entrada i sortida | C12: SeTDIBA-SECRETARIA Aplicació per gestionar els òrgans col·legiats | D12: Gestiona | E12: Diputació | O12: =IF(B12="","",COUNTIF('Rel.Conjunts-Sistemes'!$D:$D,$B12)) -> 0
B13: Registre d'analítiques de la qualitat de l’aigua | C13: ORALIMS Anàlisi de la qualitat de l’aigua | D13: ORACLE | E13: Diputació | O13: =IF(B13="","",COUNTIF('Rel.Conjunts-Sistemes'!$D:$D,$B13)) -> 1
B14: Gestió de nòmines municipals | C14: EPSILON Gestió de nòmines municipals | D14: EPSILOM | E14: Diputació | O14: =IF(B14="","",COUNTIF('Rel.Conjunts-Sistemes'!$D:$D,$B14)) -> 0
B15: Registre d'activitats econòmiques (GIA) | C15: GIA Expedients d’activitats econòmiques | D15: GIA - desenvolupament propi | E15: Diputació | O15: =IF(B15="","",COUNTIF('Rel.Conjunts-Sistemes'!$D:$D,$B15)) -> 1
B16: Gestió dels plans de protecció civil municipal | C16: PCOM Gestió dels plans de protecció civil municipal | D16: PCOM - desenvolupament propi | E16: Diputació | O16: =IF(B16="","",COUNTIF('Rel.Conjunts-Sistemes'!$D:$D,$B16)) -> 0
B17: Repositori imatges arxius municipals (IMAGINA ) | C17: IMAGINA Repositori imatges arxius municipals | D17: IMAGINA - desenvolupament propi | E17: Diputació | O17: =IF(B17="","",COUNTIF('Rel.Conjunts-Sistemes'!$D:$D,$B17)) -> 0
B18: Sistema per a la gestió de serveis locals d’ocupació (XALOC) | C18: XALOC Serveis locals d’ocupació | D18: XALOC - desenvolupament propi | E18: Diputació | O18: =IF(B18="","",COUNTIF('Rel.Conjunts-Sistemes'!$D:$D,$B18)) -> 3
B19: Comptabilitat municipal | C19: SICALWIN Comptabilitat per als ajuntaments | D19: SICALWIN - Berger Levrault | E19: Diputació | O19: =IF(B19="","",COUNTIF('Rel.Conjunts-Sistemes'!$D:$D,$B19)) -> 0
B20: Gestió de subvencions | C20: ACCEDE-SUB Subvencions | D20: ACCEDE-SUB - Berger Levrault | E20: Diputació | O20: =IF(B20="","",COUNTIF('Rel.Conjunts-Sistemes'!$D:$D,$B20)) -> 0
... B26: Sistema de gestió de les auditories pobresa energètica | C26: SIAPE Auditories pobresa energètica | D26: SIAPE - desenvolupament propi | E26: Diputació | O26: =IF(B26="","",COUNTIF('Rel.Conjunts-Sistemes'!$D:$D,$B26)) -> 0
B27: Portal de transparència municipal | E27: Consorci AOC | O27: =IF(B27="","",COUNTIF('Rel.Conjunts-Sistemes'!$D:$D,$B27)) -> 0
B28: Portal de dades obertes municipal | D28: CKAN | E28: Consorci AOC | O28: =IF(B28="","",COUNTIF('Rel.Conjunts-Sistemes'!$D:$D,$B28)) -> 0
B29: Catàleg de tràmits i eina de tramitació digital | D29: Gestiona | E29: Diputació | O29: =IF(B29="","",COUNTIF('Rel.Conjunts-Sistemes'!$D:$D,$B29)) -> 0
B30: Seu electrònica | E30: Consorci AOC | O30: =IF(B30="","",COUNTIF('Rel.Conjunts-Sistemes'!$D:$D,$B30)) -> 0
B31: Gestió de serveis bibliotecaris | C31: SIERRA - eina de gestió de serveis bibliotecaris | D31: SIERRA - desenvolupament propi | E31: Diputació | O31: =IF(B31="","",COUNTIF('Rel.Conjunts-Sistemes'!$D:$D,$B31)) -> 0
B32: GIAM | C32: Gestió de fons de l'arxiu municipal | D32: Base de dades Access | E32: Diputació | O32: =IF(B32="","",COUNTIF('Rel.Conjunts-Sistemes'!$D:$D,$B32)) -> 0
B33: Gestió de cementiris | E33: Ajuntament | O33: =IF(B33="","",COUNTIF('Rel.Conjunts-Sistemes'!$D:$D,$B33)) -> 0
B34: Gestió de queixes i suggeriments | E34: Ajuntament | O34: =IF(B34="","",COUNTIF('Rel.Conjunts-Sistemes'!$D:$D,$B34)) -> 0
B35: Gestió de representacions | D35: Representa | E35: Consorci AOC | O35: =IF(B35="","",COUNTIF('Rel.Conjunts-Sistemes'!$D:$D,$B35)) -> 0
B36: Sistema de cita prèvia | E36: Ajuntament | O36: =IF(B36="","",COUNTIF('Rel.Conjunts-Sistemes'!$D:$D,$B36)) -> 0
B37: Sistema de gestió d'impostos municipals | D37: ORGT | E37: Ajuntament | O37: =IF(B37="","",COUNTIF('Rel.Conjunts-Sistemes'!$D:$D,$B37)) -> 0
B38: Sistema de gestió de personal | E38: Ajuntament | O38: =IF(B38="","",COUNTIF('Rel.Conjunts-Sistemes'!$D:$D,$B38)) -> 0
B39: Control horari | E39: Ajuntament | O39: =IF(B39="","",COUNTIF('Rel.Conjunts-Sistemes'!$D:$D,$B39)) -> 0
B40: Gestió d'incidències a la via pública i manteniment d'equipaments | E40: Ajuntament | O40: =IF(B40="","",COUNTIF('Rel.Conjunts-Sistemes'!$D:$D,$B40)) -> 0
B41: Gestió de residus | E41: Ajuntament | O41: =IF(B41="","",COUNTIF('Rel.Conjunts-Sistemes'!$D:$D,$B41)) -> 0
B42: Gestió policial d'atestats | E42: Ajuntament | O42: =IF(B42="","",COUNTIF('Rel.Conjunts-Sistemes'!$D:$D,$B42)) -> 0
B43: Gestió dels sistemes de videovigilància | E43: Ajuntament | O43: =IF(B43="","",COUNTIF('Rel.Conjunts-Sistemes'!$D:$D,$B43)) -> 0
B44: Gestió de sancions | E44: Ajuntament | O44: =IF(B44="","",COUNTIF('Rel.Conjunts-Sistemes'!$D:$D,$B44)) -> 0
B45: Gestió d'aparcaments | E45: Ajuntament | O45: =IF(B45="","",COUNTIF('Rel.Conjunts-Sistemes'!$D:$D,$B45)) -> 0
B46: Web municipal | E46: Diputació | O46: =IF(B46="","",COUNTIF('Rel.Conjunts-Sistemes'!$D:$D,$B46)) -> 0
B47: Eina de gestió de la participació | D47: Participa311 | E47: Diputació | O47: =IF(B47="","",COUNTIF('Rel.Conjunts-Sistemes'!$D:$D,$B47)) -> 0
B48: Sistema de gestió | O48: =IF(B48="","",COUNTIF('Rel.Conjunts-Sistemes'!$D:$D,$B48)) -> 0
B49: Plataforma de gestió d'cnformació de sensors | O49: =IF(B49="","",COUNTIF('Rel.Conjunts-Sistemes'!$D:$D,$B49)) -> 0
O50: =IF(B50="","",COUNTIF('Rel.Conjunts-Sistemes'!$D:$D,$B50))
O51: =IF(B51="","",COUNTIF('Rel.Conjunts-Sistemes'!$D:$D,$B51))
O52: =IF(B52="","",COUNTIF('Rel.Conjunts-Sistemes'!$D:$D,$B52))
O53: =IF(B53="","",COUNTIF('Rel.Conjunts-Sistemes'!$D:$D,$B53))
O54: =IF(B54="","",COUNTIF('Rel.Conjunts-Sistemes'!$D:$D,$B54))
O55: =IF(B55="","",COUNTIF('Rel.Conjunts-Sistemes'!$D:$D,$B55))
O56: =IF(B56="","",COUNTIF('Rel.Conjunts-Sistemes'!$D:$D,$B56))
O57: =IF(B57="","",COUNTIF('Rel.Conjunts-Sistemes'!$D:$D,$B57))
O58: =IF(B58="","",COUNTIF('Rel.Conjunts-Sistemes'!$D:$D,$B58))
O59: =IF(B59="","",COUNTIF('Rel.Conjunts-Sistemes'!$D:$D,$B59))
O60: =IF(B60="","",COUNTIF('Rel.Conjunts-Sistemes'!$D:$D,$B60))
O61: =IF(B61="","",COUNTIF('Rel.Conjunts-Sistemes'!$D:$D,$B61))
... O67: =IF(B67="","",COUNTIF('Rel.Conjunts-Sistemes'!$D:$D,$B67))

Sheet Dominis de dades
B5: Dominis de dades
B6: =COUNTA(C$9:C$62) -> 34 | C6: =COUNTA(C$9:C$62)/$B$7 -> #VALUE! | D6: =COUNTA(D$9:D$62)/$B$7 -> #VALUE! | E6: =COUNTA(E$9:E$62)/$B$7 -> #VALUE!
B7: Domini de dades | C7: Descripció | D7: Àmbit | E7: Àrea propietària | F7: Núm. Conjunts de dades
B8: Patrimoni i actius municipals (nou) | C8: Inclou edificis, locals, solars, vehicles, equipaments, mobiliari urbà, punts enllumenat, inventari patrimonial, sensors, equip informàtic, llicències, etc. | D8: Corporatiu (Dades mestres i de referència) | E8: Obres i Manteniment | F8: =IF(B8="","",COUNTIF('Conjunts de dades'!$D:$D,$B8)) -> 11
B9: Padró i identitat ciutadana (antic Població) | C9: Inclou el padró, altes i baixes, canvis de domicili i certificats. És clau per a serveis municipals, estadística i finançament. Permet garantir adreces correctes i traçabilitat de moviments de veïns. | D9: Corporatiu (Dades mestres i de referència) | E9: Padró i Estadística | F9: =IF(B9="","",COUNTIF('Conjunts de dades'!$D:$D,$B9)) -> 1
B10: Dades de referència (comú a tot l'ecosistema de dades de país) | C10: Inclou codis, classificacions, declaració d'unitats administratives, països. Etc | D10: Corporatiu (Dades mestres i de referència) | E10: Padró i Estadística | F10: =IF(B10="","",COUNTIF('Conjunts de dades'!$D:$D,$B10)) -> 0
B11: Medi ambient | C11: Inclou controls de qualitat de l'aire i soroll, gestió d'espais naturals, permisos ambientals i seguiment de sancions. Permet planificar campanyes, gestionar denúncies i elaborar indicadors per a informes i transparència. | D11: Gestió de l'espai públic i serveis al territori | E11: Medi Ambient | F11: =IF(B11="","",COUNTIF('Conjunts de dades'!$D:$D,$B11)) -> 4
B12: Residus | C12: Inclou recollida, contenidors, rutes, incidències, inspeccions i dades de pes o volum. Ajuda a millorar el servei, controlar objectius de reciclatge i gestionar contractes i campanyes amb la ciutadania. | D12: Gestió de l'espai públic i serveis al territori | E12: Medi Ambient | F12: =IF(B12="","",COUNTIF('Conjunts de dades'!$D:$D,$B12)) -> 1
B13: Mobilitat i trànsit | C13: Recull regulació de trànsit, zones d'estacionament, sancions, incidències, aforaments i informació de transport. Ajuda a prendre decisions de circulació, millorar el servei i coordinar actuacions amb operadors i policia. | D13: Gestió de l'espai públic i serveis al territori | E13: Mobilitat | F13: =IF(B13="","",COUNTIF('Conjunts de dades'!$D:$D,$B13)) -> 6
B14: Obres públiques i manteniment | C14: Inventari de projectes d'obres municipals, plans de manteniment i afectacions a la via. Serveix per controlar terminis, pressupostos i coordinació amb serveis afectats, incloent empreses contractistes i permisos. | D14: Gestió de l'espai públic i serveis al territori | E14: Obres i Manteniment | F14: =IF(B14="","",COUNTIF('Conjunts de dades'!$D:$D,$B14)) -> 1
B15: Protecció civil i emergències | C15: Reuneix plans d'emergència, inventari de recursos, avisos, activacions i informes d'incidents. Ajuda a coordinar operatius, gestionar comunicacions amb altres cossos i conservar evidències per avaluar i millorar respostes. | D15: Gestió de l'espai públic i serveis al territori | E15: Protecció Civil | F15: =IF(B15="","",COUNTIF('Conjunts de dades'!$D:$D,$B15)) -> 2
B16: Aigua i sanejament | C16: Inclou dades d'abonats, comptadors, lectures, incidències de xarxa i actuacions de manteniment. Serveix per planificar reparacions, controlar el consum i coordinar les empreses concessionàries amb el servei municipal. | D16: Gestió de l'espai públic i serveis al territori | E16: Serveis Urbans | F16: =IF(B16="","",COUNTIF('Conjunts de dades'!$D:$D,$B16)) -> 2
B17: Consum energètic | C17: Conté informació de consums, avaries i ordres de treball. Ajuda a prioritzar reparacions, optimitzar energia i comprovar el compliment del contracte de manteniment. | D17: Gestió de l'espai públic i serveis al territori | E17: Serveis Urbans | F17: =IF(B17="","",COUNTIF('Conjunts de dades'!$D:$D,$B17)) -> 1
B18: Neteja viària | C18: Inclou rutes de neteja, planificació de torns, incidències, inspeccions i control de qualitat del servei. Permet fer seguiment del contracte, registrar queixes i ajustar recursos segons zones i esdeveniments. | D18: Gestió de l'espai públic i serveis al territori | E18: Serveis Urbans | F18: =IF(B18="","",COUNTIF('Conjunts de dades'!$D:$D,$B18)) -> 1
B19: Informació territorial i geoespacial | C19: Agrupa cartografia, carrers, adreces, parcel·les, equipaments i capes temàtiques. Serveix per suportar tràmits, planificació i consultes internes, i per compartir mapes amb altres organismes quan cal. | D19: Gestió de l'espai públic i serveis al territori | E19: Urbanisme | F19: =IF(B19="","",COUNTIF('Conjunts de dades'!$D:$D,$B19)) -> 4
... B42: Turisme i oci | C42: Inclou recursos turístics, agenda d'activitats, reserves de visites, consultes i estadístiques de demanda. Permet informar visitants, coordinar agents locals i avaluar l'impacte d'esdeveniments amb dades clares i comparables. | D42: Serveis a les persones | E42: Turisme | F42: =IF(B42="","",COUNTIF('Conjunts de dades'!$D:$D,$B42)) -> 2
B43: Un domini de dades és una classificació lògica que agrupa dades relacionades per un significat, tema o propòsit comú, independentment de l’aplicació
F44: =IF(B44="","",COUNTIF('Conjunts de dades'!$D:$D,$B44))
F45: =IF(B45="","",COUNTIF('Conjunts de dades'!$D:$D,$B45))
F46: =IF(B46="","",COUNTIF('Conjunts de dades'!$D:$D,$B46))
F47: =IF(B47="","",COUNTIF('Conjunts de dades'!$D:$D,$B47))
F48: =IF(B48="","",COUNTIF('Conjunts de dades'!$D:$D,$B48))
F49: =IF(B49="","",COUNTIF('Conjunts de dades'!$D:$D,$B49))
F50: =IF(B50="","",COUNTIF('Conjunts de dades'!$D:$D,$B50))
F51: =IF(B51="","",COUNTIF('Conjunts de dades'!$D:$D,$B51))
F52: =IF(B52="","",COUNTIF('Conjunts de dades'!$D:$D,$B52))
F53: =IF(B53="","",COUNTIF('Conjunts de dades'!$D:$D,$B53))
F54: =IF(B54="","",COUNTIF('Conjunts de dades'!$D:$D,$B54))
F55: =IF(B55="","",COUNTIF('Conjunts de dades'!$D:$D,$B55))
... F62: =IF(B62="","",COUNTIF('Conjunts de dades'!$D:$D,$B62))

Sheet Conjunts de dades
B5: Conjunts de dades
B6: =COUNTA(ConjuntsDades) -> 104 | C6: {=SUMPRODUCT(--(C$9:C$112<>""))/$B$6} -> 1 | D6: {=SUMPRODUCT(--(D$9:D$112<>""))/$B$6} -> 1 | F6: {=SUMPRODUCT(--(F$9:F$112<>""))/$B$6} -> 0.0096153846 | G6: {=SUMPRODUCT(--(G$9:G$112<>""))/$B$6} -> 0.0096153846 | H6: {=SUMPRODUCT(--(H$9:H$112<>""))/$B$6} -> 0 | I6: {=SUMPRODUCT(--(I$9:I$112<>""))/$B$6} -> 0 | J6: {=SUMPRODUCT(--(J$9:J$112<>""))/$B$6} -> 0 | K6: {=SUMPRODUCT(--(K$9:K$112<>""))/$B$6} -> 0 | L6: {=SUMPRODUCT(--(L$9:L$112<>""))/$B$6} -> 0 | M6: {=SUMPRODUCT(--(M$9:M$112<>""))/$B$6} -> 0 | ... AO6: {=SUMPRODUCT(--(AO$9:AO$112<>""))/$B$6} -> 0.019230769
H7: Sensibilitat de les dades | O7: Rols i responsabilitats | AC7: Riscos associats
B8: Nom Conjunt de dades | C8: Descripció | D8: Domini de dades | E8: Àrea propietària | F8: Tipus conjunt de dades | G8: Ús previst de les dades | H8: Conté dades personals? | I8: Conté dades de gènere u orientació sexual? | J8: Conté dades d'ideologia o creences? | K8: Conté dades biomètriques? | L8: Conté dades de salut? | M8: Conté dades confidencials de l'ens local? | N8: Conté dades de seguretat i accés? | O8: Nom del responsable del Conjunt de dades (Propietari de dades) | P8: Càrrec del responsable del conjunt de dades | Q8: Nom del gestor del Conjunt de dades | R8: Càrrec del gestor del conjunt de dades | S8: Nom del custodi del Conjunt de dades | T8: Càrrec del custodi del conjunt de dades | U8: Categoria de les dades d'alt valor | V8: Cadència d'actualització | W8: Origen de les dades | X8: Persistència | Y8: Retenció | Z8: Disponibilitat històrica | AA8: Restriccions dades obertes | AB8: Reutilització de dades | AC8: Incoherència de dades | AD8: Informació desactualitzada | AE8: Publicació d'informació incorrecta | AF8: Registres duplicats | AG8: Accés a dades sensibles | AH8: Accés o ús indegut | AI8: Exposició de dades (menors, personals, sensibles o socials) | AJ8: Filtració o fuita de dades | AK8: Indisponiblitat del sistema | AL8: Pèrdua de dades | AM8: Falta de traçabilitat i evidències sobre la gestió de les dades | AN8: Falta de seguiment o auditories sobre accessos i usos | AO8: Falta de pla de resposta a incidents | AP8: Nivell de risc general | AQ8: Observacions | AR8: Núm. Sistemes d'informació | AS8: Núm. Dominis de dades
B9: Sol·licitants d'ocupació del servei local d'ocupació | C9: Registre anonimitzat del perfil sociodemogràfic dels demandants d'ocupació (edat, gènere, nivell d'estudis, sector professional, temps en atur). | D9: Formació i ocupació | F9: Dades de referència / mestres no homogeneïtzades | G9: Intern transversal | AC9: Probabilitat: Baixa Impacte: Alt (2) | AD9: Probabilitat: Mitja Impacte: Baix (1) | AE9: Probabilitat: Mitja Impacte: Alt (4) | AG9: Probabilitat: Mitja Impacte: Moderat (3) | AH9: Probabilitat: Baixa Impacte: Alt (2) | AI9: Probabilitat: Mitja Impacte: Baix (1) | AJ9: Probabilitat: Baixa Impacte: Moderat (1) | AK9: Probabilitat: Mitja Impacte: Baix (1) | AL9: Probabilitat: Alta Impacte: Baix (3) | AM9: Probabilitat: Baixa Impacte: Alt (2) | AN9: Probabilitat: Baixa Impacte: Alt (2) | AO9: Probabilitat: Mitja Impacte: Moderat (3) | AP9: =AVERAGE(SUMIF(AnàlisiRiscos,AC9,AnàlisiRiscosGrau),SUMIF(AnàlisiRiscos,AD9,AnàlisiRiscosGrau),SUMIF(AnàlisiRiscos,AE9,AnàlisiRiscosGrau),SUMIF(AnàlisiRiscos,AF9,AnàlisiRiscosGrau),SUMIF(AnàlisiRiscos,AG9,AnàlisiRiscosGrau),SUMIF(AnàlisiRiscos,AH9,AnàlisiRiscosGrau),SUMIF(AnàlisiRiscos,AI9,AnàlisiRiscosGrau),SUMIF(AnàlisiRiscos,AJ9,AnàlisiRiscosGrau),SUMIF(AnàlisiRiscos,AK9,AnàlisiRiscosGrau),SUMIF(AnàlisiRiscos,AL9,AnàlisiRiscosGrau),SUMIF(AnàlisiRiscos,AM9,AnàlisiRiscosGrau),SUMIF(AnàlisiRiscos,AN9,AnàlisiRiscosGrau),SUMIF(AnàlisiRiscos,AO9,AnàlisiRiscosGrau)) -> #VALUE! | AR9: =IF(B9="","",COUNTIF('Rel.Conjunts-Sistemes'!$B:$B,$B9)) -> 1 | AS9: =IF(B9="","",COUNTIF('Dominis de dades'!$B:$B,$D9)) -> 1
B10: Ofertes de treball del servei local d'ocupació | C10: Detall de les ofertes gestionades (sector, tipus de contracte, requisits) i indicadors d'eficiència (temps mitjà per cobrir la vacant). | D10: Formació i ocupació | AC10: Probabilitat: Baixa Impacte: Alt (2) | AD10: Probabilitat: Mitja Impacte: Baix (1) | AE10: Probabilitat: Mitja Impacte: Alt (4) | AF10: Probabilitat: Alta Impacte: Alt (4) | AG10: Probabilitat: Mitja Impacte: Moderat (3) | AH10: Probabilitat: Baixa Impacte: Alt (2) | AJ10: Probabilitat: Baixa Impacte: Moderat (1) | AK10: Probabilitat: Mitja Impacte: Baix (1) | AL10: Probabilitat: Alta Impacte: Baix (3) | AM10: Probabilitat: Baixa Impacte: Alt (2) | AN10: Probabilitat: Baixa Impacte: Alt (2) | AO10: Probabilitat: Mitja Impacte: Moderat (3) | AP10: =AVERAGE(SUMIF(AnàlisiRiscos,AC10,AnàlisiRiscosGrau),SUMIF(AnàlisiRiscos,AD10,AnàlisiRiscosGrau),SUMIF(AnàlisiRiscos,AE10,AnàlisiRiscosGrau),SUMIF(AnàlisiRiscos,AF10,AnàlisiRiscosGrau),SUMIF(AnàlisiRiscos,AG10,AnàlisiRiscosGrau),SUMIF(AnàlisiRiscos,AH10,AnàlisiRiscosGrau),SUMIF(AnàlisiRiscos,AI10,AnàlisiRiscosGrau),SUMIF(AnàlisiRiscos,AJ10,AnàlisiRiscosGrau),SUMIF(AnàlisiRiscos,AK10,AnàlisiRiscosGrau),SUMIF(AnàlisiRiscos,AL10,AnàlisiRiscosGrau),SUMIF(AnàlisiRiscos,AM10,AnàlisiRiscosGrau),SUMIF(AnàlisiRiscos,AN10,AnàlisiRiscosGrau),SUMIF(AnàlisiRiscos,AO10,AnàlisiRiscosGrau)) -> #VALUE! | AR10: =IF(B10="","",COUNTIF('Rel.Conjunts-Sistemes'!$B:$B,$B10)) -> 1 | AS10: =IF(B10="","",COUNTIF('Dominis de dades'!$B:$B,$D10)) -> 1
B11: Cens de locals comercials buits | C11: Indicador econòmic i cens geolocalitzat dels establiments comercials sense activitat a peu de carrer, orientat a plans de dinamització comercial. | D11: Economia local, comerç i mercats | AP11: =AVERAGE(SUMIF(AnàlisiRiscos,AC11,AnàlisiRiscosGrau),SUMIF(AnàlisiRiscos,AD11,AnàlisiRiscosGrau),SUMIF(AnàlisiRiscos,AE11,AnàlisiRiscosGrau),SUMIF(AnàlisiRiscos,AF11,AnàlisiRiscosGrau),SUMIF(AnàlisiRiscos,AG11,AnàlisiRiscosGrau),SUMIF(AnàlisiRiscos,AH11,AnàlisiRiscosGrau),SUMIF(AnàlisiRiscos,AI11,AnàlisiRiscosGrau),SUMIF(AnàlisiRiscos,AJ11,AnàlisiRiscosGrau),SUMIF(AnàlisiRiscos,AK11,AnàlisiRiscosGrau),SUMIF(AnàlisiRiscos,AL11,AnàlisiRiscosGrau),SUMIF(AnàlisiRiscos,AM11,AnàlisiRiscosGrau),SUMIF(AnàlisiRiscos,AN11,AnàlisiRiscosGrau),SUMIF(AnàlisiRiscos,AO11,AnàlisiRiscosGrau)) -> #VALUE! | AR11: =IF(B11="","",COUNTIF('Rel.Conjunts-Sistemes'!$B:$B,$B11)) -> 1 | AS11: =IF(B11="","",COUNTIF('Dominis de dades'!$B:$B,$D11)) -> 1
B12: Cens d'empreses, comerços i establiments | C12: Registre d'activitats econòmiques de la ciutat actives a peu de carrer o en oficines, classificades per sector econòmic. | D12: Economia local, comerç i mercats | AP12: =AVERAGE(SUMIF(AnàlisiRiscos,AC12,AnàlisiRiscosGrau),SUMIF(AnàlisiRiscos,AD12,AnàlisiRiscosGrau),SUMIF(AnàlisiRiscos,AE12,AnàlisiRiscosGrau),SUMIF(AnàlisiRiscos,AF12,AnàlisiRiscosGrau),SUMIF(AnàlisiRiscos,AG12,AnàlisiRiscosGrau),SUMIF(AnàlisiRiscos,AH12,AnàlisiRiscosGrau),SUMIF(AnàlisiRiscos,AI12,AnàlisiRiscosGrau),SUMIF(AnàlisiRiscos,AJ12,AnàlisiRiscosGrau),SUMIF(AnàlisiRiscos,AK12,AnàlisiRiscosGrau),SUMIF(AnàlisiRiscos,AL12,AnàlisiRiscosGrau),SUMIF(AnàlisiRiscos,AM12,AnàlisiRiscosGrau),SUMIF(AnàlisiRiscos,AN12,AnàlisiRiscosGrau),SUMIF(AnàlisiRiscos,AO12,AnàlisiRiscosGrau)) -> #VALUE! | AR12: =IF(B12="","",COUNTIF('Rel.Conjunts-Sistemes'!$B:$B,$B12)) -> 1 | AS12: =IF(B12="","",COUNTIF('Dominis de dades'!$B:$B,$D12)) -> 1
B13: Polígons de l'activitat econòmica i industrial | C13: Delimitació geogràfica, parcel·lari, serveis disponibles i directori d'empreses ubicades a les zones industrials de la localitat. | D13: Economia local, comerç i mercats | AP13: =AVERAGE(SUMIF(AnàlisiRiscos,AC13,AnàlisiRiscosGrau),SUMIF(AnàlisiRiscos,AD13,AnàlisiRiscosGrau),SUMIF(AnàlisiRiscos,AE13,AnàlisiRiscosGrau),SUMIF(AnàlisiRiscos,AF13,AnàlisiRiscosGrau),SUMIF(AnàlisiRiscos,AG13,AnàlisiRiscosGrau),SUMIF(AnàlisiRiscos,AH13,AnàlisiRiscosGrau),SUMIF(AnàlisiRiscos,AI13,AnàlisiRiscosGrau),SUMIF(AnàlisiRiscos,AJ13,AnàlisiRiscosGrau),SUMIF(AnàlisiRiscos,AK13,AnàlisiRiscosGrau),SUMIF(AnàlisiRiscos,AL13,AnàlisiRiscosGrau),SUMIF(AnàlisiRiscos,AM13,AnàlisiRiscosGrau),SUMIF(AnàlisiRiscos,AN13,AnàlisiRiscosGrau),SUMIF(AnàlisiRiscos,AO13,AnàlisiRiscosGrau)) -> #VALUE! | AR13: =IF(B13="","",COUNTIF('Rel.Conjunts-Sistemes'!$B:$B,$B13)) -> 1 | AS13: =IF(B13="","",COUNTIF('Dominis de dades'!$B:$B,$D13)) -> 1
B14: Tramitació i expedients administratius | C14: Traçabilitat de la gestió interna: expedients oberts, procediment, sèrie documental, àrea responsable, terminis de resolució i estat actual. | D14: Secretaria | AP14: =AVERAGE(SUMIF(AnàlisiRiscos,AC14,AnàlisiRiscosGrau),SUMIF(AnàlisiRiscos,AD14,AnàlisiRiscosGrau),SUMIF(AnàlisiRiscos,AE14,AnàlisiRiscosGrau),SUMIF(AnàlisiRiscos,AF14,AnàlisiRiscosGrau),SUMIF(AnàlisiRiscos,AG14,AnàlisiRiscosGrau),SUMIF(AnàlisiRiscos,AH14,AnàlisiRiscosGrau),SUMIF(AnàlisiRiscos,AI14,AnàlisiRiscosGrau),SUMIF(AnàlisiRiscos,AJ14,AnàlisiRiscosGrau),SUMIF(AnàlisiRiscos,AK14,AnàlisiRiscosGrau),SUMIF(AnàlisiRiscos,AL14,AnàlisiRiscosGrau),SUMIF(AnàlisiRiscos,AM14,AnàlisiRiscosGrau),SUMIF(AnàlisiRiscos,AN14,AnàlisiRiscosGrau),SUMIF(AnàlisiRiscos,AO14,AnàlisiRiscosGrau)) -> #VALUE! | AR14: =IF(B14="","",COUNTIF('Rel.Conjunts-Sistemes'!$B:$B,$B14)) -> 1 | AS14: =IF(B14="","",COUNTIF('Dominis de dades'!$B:$B,$D14)) -> 1
B15: Registre general d'entrada i sortida de documents | C15: Flux de documents de la corporació (presencial i online) amb indicació del canal d'entrada/sortida, tipus de document i classificació. | D15: Activitat administrativa | AP15: =AVERAGE(SUMIF(AnàlisiRiscos,AC15,AnàlisiRiscosGrau),SUMIF(AnàlisiRiscos,AD15,AnàlisiRiscosGrau),SUMIF(AnàlisiRiscos,AE15,AnàlisiRiscosGrau),SUMIF(AnàlisiRiscos,AF15,AnàlisiRiscosGrau),SUMIF(AnàlisiRiscos,AG15,AnàlisiRiscosGrau),SUMIF(AnàlisiRiscos,AH15,AnàlisiRiscosGrau),SUMIF(AnàlisiRiscos,AI15,AnàlisiRiscosGrau),SUMIF(AnàlisiRiscos,AJ15,AnàlisiRiscosGrau),SUMIF(AnàlisiRiscos,AK15,AnàlisiRiscosGrau),SUMIF(AnàlisiRiscos,AL15,AnàlisiRiscosGrau),SUMIF(AnàlisiRiscos,AM15,AnàlisiRiscosGrau),SUMIF(AnàlisiRiscos,AN15,AnàlisiRiscosGrau),SUMIF(AnàlisiRiscos,AO15,AnàlisiRiscosGrau)) -> #VALUE! | AR15: =IF(B15="","",COUNTIF('Rel.Conjunts-Sistemes'!$B:$B,$B15)) -> 1 | AS15: =IF(B15="","",COUNTIF('Dominis de dades'!$B:$B,$D15)) -> 1
B16: Registre municipal de convenis i acords institucionals | C16: Llistat i detall de convenis signats per l'Ajuntament amb altres administracions, entitats del tercer sector o empreses. | D16: Secretaria | AP16: =AVERAGE(SUMIF(AnàlisiRiscos,AC16,AnàlisiRiscosGrau),SUMIF(AnàlisiRiscos,AD16,AnàlisiRiscosGrau),SUMIF(AnàlisiRiscos,AE16,AnàlisiRiscosGrau),SUMIF(AnàlisiRiscos,AF16,AnàlisiRiscosGrau),SUMIF(AnàlisiRiscos,AG16,AnàlisiRiscosGrau),SUMIF(AnàlisiRiscos,AH16,AnàlisiRiscosGrau),SUMIF(AnàlisiRiscos,AI16,AnàlisiRiscosGrau),SUMIF(AnàlisiRiscos,AJ16,AnàlisiRiscosGrau),SUMIF(AnàlisiRiscos,AK16,AnàlisiRiscosGrau),SUMIF(AnàlisiRiscos,AL16,AnàlisiRiscosGrau),SUMIF(AnàlisiRiscos,AM16,AnàlisiRiscosGrau),SUMIF(AnàlisiRiscos,AN16,AnàlisiRiscosGrau),SUMIF(AnàlisiRiscos,AO16,AnàlisiRiscosGrau)) -> #VALUE! | AR16: =IF(B16="","",COUNTIF('Rel.Conjunts-Sistemes'!$B:$B,$B16)) -> 1 | AS16: =IF(B16="","",COUNTIF('Dominis de dades'!$B:$B,$D16)) -> 1
B17: Taulell d'anuncis i edictes oficials | C17: Registre de les publicacions obligatòries, ordenances aprovades, anuncis de licitació i notificacions exposades al tauler digital. | D17: Secretaria | AP17: =AVERAGE(SUMIF(AnàlisiRiscos,AC17,AnàlisiRiscosGrau),SUMIF(AnàlisiRiscos,AD17,AnàlisiRiscosGrau),SUMIF(AnàlisiRiscos,AE17,AnàlisiRiscosGrau),SUMIF(AnàlisiRiscos,AF17,AnàlisiRiscosGrau),SUMIF(AnàlisiRiscos,AG17,AnàlisiRiscosGrau),SUMIF(AnàlisiRiscos,AH17,AnàlisiRiscosGrau),SUMIF(AnàlisiRiscos,AI17,AnàlisiRiscosGrau),SUMIF(AnàlisiRiscos,AJ17,AnàlisiRiscosGrau),SUMIF(AnàlisiRiscos,AK17,AnàlisiRiscosGrau),SUMIF(AnàlisiRiscos,AL17,AnàlisiRiscosGrau),SUMIF(AnàlisiRiscos,AM17,AnàlisiRiscosGrau),SUMIF(AnàlisiRiscos,AN17,AnàlisiRiscosGrau),SUMIF(AnàlisiRiscos,AO17,AnàlisiRiscosGrau)) -> #VALUE! | AR17: =IF(B17="","",COUNTIF('Rel.Conjunts-Sistemes'!$B:$B,$B17)) -> 1 | AS17: =IF(B17="","",COUNTIF('Dominis de dades'!$B:$B,$D17)) -> 1
B18: Quadre de classificació documental | C18: Estructura jeràrquica de referència utilitzada per a l'organització, codificació i emmagatzematgede la informació dins de l'organització. | D18: Secretaria | AP18: =AVERAGE(SUMIF(AnàlisiRiscos,AC18,AnàlisiRiscosGrau),SUMIF(AnàlisiRiscos,AD18,AnàlisiRiscosGrau),SUMIF(AnàlisiRiscos,AE18,AnàlisiRiscosGrau),SUMIF(AnàlisiRiscos,AF18,AnàlisiRiscosGrau),SUMIF(AnàlisiRiscos,AG18,AnàlisiRiscosGrau),SUMIF(AnàlisiRiscos,AH18,AnàlisiRiscosGrau),SUMIF(AnàlisiRiscos,AI18,AnàlisiRiscosGrau),SUMIF(AnàlisiRiscos,AJ18,AnàlisiRiscosGrau),SUMIF(AnàlisiRiscos,AK18,AnàlisiRiscosGrau),SUMIF(AnàlisiRiscos,AL18,AnàlisiRiscosGrau),SUMIF(AnàlisiRiscos,AM18,AnàlisiRiscosGrau),SUMIF(AnàlisiRiscos,AN18,AnàlisiRiscosGrau),SUMIF(AnàlisiRiscos,AO18,AnàlisiRiscosGrau)) -> #VALUE! | AR18: =IF(B18="","",COUNTIF('Rel.Conjunts-Sistemes'!$B:$B,$B18)) -> 1 | AS18: =IF(B18="","",COUNTIF('Dominis de dades'!$B:$B,$D18)) -> 1
B19: Resultats electorals per mesa i secció censal | C19: Resultats històrics d'eleccions (municipals, autonòmiques, generals) desglossats per partits, vots en blanc, nuls i abstenció per mesa. | D19: Secretaria | AP19: =AVERAGE(SUMIF(AnàlisiRiscos,AC19,AnàlisiRiscosGrau),SUMIF(AnàlisiRiscos,AD19,AnàlisiRiscosGrau),SUMIF(AnàlisiRiscos,AE19,AnàlisiRiscosGrau),SUMIF(AnàlisiRiscos,AF19,AnàlisiRiscosGrau),SUMIF(AnàlisiRiscos,AG19,AnàlisiRiscosGrau),SUMIF(AnàlisiRiscos,AH19,AnàlisiRiscosGrau),SUMIF(AnàlisiRiscos,AI19,AnàlisiRiscosGrau),SUMIF(AnàlisiRiscos,AJ19,AnàlisiRiscosGrau),SUMIF(AnàlisiRiscos,AK19,AnàlisiRiscosGrau),SUMIF(AnàlisiRiscos,AL19,AnàlisiRiscosGrau),SUMIF(AnàlisiRiscos,AM19,AnàlisiRiscosGrau),SUMIF(AnàlisiRiscos,AN19,AnàlisiRiscosGrau),SUMIF(AnàlisiRiscos,AO19,AnàlisiRiscosGrau)) -> #VALUE! | AR19: =IF(B19="","",COUNTIF('Rel.Conjunts-Sistemes'!$B:$B,$B19)) -> 1 | AS19: =IF(B19="","",COUNTIF('Dominis de dades'!$B:$B,$D19)) -> 1
B20: Registre municipal de parelles de fet | C20: Llistat històric i vigent de les inscripcions d'unions civils no matrimonials formalitzades a l'ajuntament. | D20: Secretaria | AP20: =AVERAGE(SUMIF(AnàlisiRiscos,AC20,AnàlisiRiscosGrau),SUMIF(AnàlisiRiscos,AD20,AnàlisiRiscosGrau),SUMIF(AnàlisiRiscos,AE20,AnàlisiRiscosGrau),SUMIF(AnàlisiRiscos,AF20,AnàlisiRiscosGrau),SUMIF(AnàlisiRiscos,AG20,AnàlisiRiscosGrau),SUMIF(AnàlisiRiscos,AH20,AnàlisiRiscosGrau),SUMIF(AnàlisiRiscos,AI20,AnàlisiRiscosGrau),SUMIF(AnàlisiRiscos,AJ20,AnàlisiRiscosGrau),SUMIF(AnàlisiRiscos,AK20,AnàlisiRiscosGrau),SUMIF(AnàlisiRiscos,AL20,AnàlisiRiscosGrau),SUMIF(AnàlisiRiscos,AM20,AnàlisiRiscosGrau),SUMIF(AnàlisiRiscos,AN20,AnàlisiRiscosGrau),SUMIF(AnàlisiRiscos,AO20,AnàlisiRiscosGrau)) -> #VALUE! | AR20: =IF(B20="","",COUNTIF('Rel.Conjunts-Sistemes'!$B:$B,$B20)) -> 1 | AS20: =IF(B20="","",COUNTIF('Dominis de dades'!$B:$B,$D20)) -> 1
B21: Subvencions i ajuts atorgats | C21: Registre oficial de subvencions concedides a entitats i ciutadans, estructurat segons els camps de la Base de Dades Nacional de Subvencions (BDNS). | D21: Contractació, convenis i subvencions | AP21: =AVERAGE(SUMIF(AnàlisiRiscos,AC21,AnàlisiRiscosGrau),SUMIF(AnàlisiRiscos,AD21,AnàlisiRiscosGrau),SUMIF(AnàlisiRiscos,AE21,AnàlisiRiscosGrau),SUMIF(AnàlisiRiscos,AF21,AnàlisiRiscosGrau),SUMIF(AnàlisiRiscos,AG21,AnàlisiRiscosGrau),SUMIF(AnàlisiRiscos,AH21,AnàlisiRiscosGrau),SUMIF(AnàlisiRiscos,AI21,AnàlisiRiscosGrau),SUMIF(AnàlisiRiscos,AJ21,AnàlisiRiscosGrau),SUMIF(AnàlisiRiscos,AK21,AnàlisiRiscosGrau),SUMIF(AnàlisiRiscos,AL21,AnàlisiRiscosGrau),SUMIF(AnàlisiRiscos,AM21,AnàlisiRiscosGrau),SUMIF(AnàlisiRiscos,AN21,AnàlisiRiscosGrau),SUMIF(AnàlisiRiscos,AO21,AnàlisiRiscosGrau)) -> #VALUE! | AR21: =IF(B21="","",COUNTIF('Rel.Conjunts-Sistemes'!$B:$B,$B21)) -> 1 | AS21: =IF(B21="","",COUNTIF('Dominis de dades'!$B:$B,$D21)) -> 1
B22: Tresoreria: pagaments, ingressos i indicador de morositat | C22: Dades financeres de pagaments, amb informació de temps mig de pagament a proveïdors i ingressos. | D22: Hisenda | AP22: =AVERAGE(SUMIF(AnàlisiRiscos,AC22,AnàlisiRiscosGrau),SUMIF(AnàlisiRiscos,AD22,AnàlisiRiscosGrau),SUMIF(AnàlisiRiscos,AE22,AnàlisiRiscosGrau),SUMIF(AnàlisiRiscos,AF22,AnàlisiRiscosGrau),SUMIF(AnàlisiRiscos,AG22,AnàlisiRiscosGrau),SUMIF(AnàlisiRiscos,AH22,AnàlisiRiscosGrau),SUMIF(AnàlisiRiscos,AI22,AnàlisiRiscosGrau),SUMIF(AnàlisiRiscos,AJ22,AnàlisiRiscosGrau),SUMIF(AnàlisiRiscos,AK22,AnàlisiRiscosGrau),SUMIF(AnàlisiRiscos,AL22,AnàlisiRiscosGrau),SUMIF(AnàlisiRiscos,AM22,AnàlisiRiscosGrau),SUMIF(AnàlisiRiscos,AN22,AnàlisiRiscosGrau),SUMIF(AnàlisiRiscos,AO22,AnàlisiRiscosGrau)) -> #VALUE! | AR22: =IF(B22="","",COUNTIF('Rel.Conjunts-Sistemes'!$B:$B,$B22)) -> 1 | AS22: =IF(B22="","",COUNTIF('Dominis de dades'!$B:$B,$D22)) -> 1
... B112: Registre de concessions funeràries | C112: Relació de les concessions administratives atorgades per a l'ús privatiu de sepultures, amb informació sobre titularitat, termini de vigència, renovacions i situació administrativa. | D112: Cementiri i serveis funeraris | AP112: =AVERAGE(SUMIF(AnàlisiRiscos,AC112,AnàlisiRiscosGrau),SUMIF(AnàlisiRiscos,AD112,AnàlisiRiscosGrau),SUMIF(AnàlisiRiscos,AE112,AnàlisiRiscosGrau),SUMIF(AnàlisiRiscos,AF112,AnàlisiRiscosGrau),SUMIF(AnàlisiRiscos,AG112,AnàlisiRiscosGrau),SUMIF(AnàlisiRiscos,AH112,AnàlisiRiscosGrau),SUMIF(AnàlisiRiscos,AI112,AnàlisiRiscosGrau),SUMIF(AnàlisiRiscos,AJ112,AnàlisiRiscosGrau),SUMIF(AnàlisiRiscos,AK112,AnàlisiRiscosGrau),SUMIF(AnàlisiRiscos,AL112,AnàlisiRiscosGrau),SUMIF(AnàlisiRiscos,AM112,AnàlisiRiscosGrau),SUMIF(AnàlisiRiscos,AN112,AnàlisiRiscosGrau),SUMIF(AnàlisiRiscos,AO112,AnàlisiRiscosGrau)) -> #VALUE! | AR112: =IF(B112="","",COUNTIF('Rel.Conjunts-Sistemes'!$B:$B,$B112)) -> 0 | AS112: =IF(B112="","",COUNTIF('Dominis de dades'!$B:$B,$D112)) -> 1
B113: Titulars de drets funeraris | C113: Registre de persones físiques o jurídiques titulars de concessions funeràries i dels drets associats a les unitats d'enterrament. | D113: Cementiri i serveis funeraris
B114: Persones difuntes inhumades | C114: Registre de les persones enterrades al cementiri municipal, amb informació sobre la sepultura ocupada, dates d'inhumació i, si escau, exhumació o trasllat. | D114: Cementiri i serveis funeraris
B115: Dades de consum energètic dels equipaments municipals | C115: Informació dels consums energètics dels edificis, equipaments i instal·lacions municipals, incloent electricitat, gas i altres fonts d'energia. Permet fer el seguiment dels consums, controlar la despesa energètica, identificar oportunitats d'estalvi i avaluar les polítiques d'eficiència energètica municipal. | D115: Consum energètic
B116: Dades de consum d'aigua dels equipaments municipals | C116: Conjunt de dades que recull la informació dels consums d'aigua dels edificis, equipaments i instal·lacions municipals. Permet monitorar l'ús dels recursos hídrics, detectar consums anòmals o fuites, optimitzar la despesa associada al servei i impulsar mesures d'estalvi i sostenibilitat. | D116: Aigua i sanejament
B117: Rutes de neteja viària | C117: Conjunt de dades que recull la planificació i els itineraris dels serveis de neteja viària en els diferents carrers, places i espais públics del municipi. Permet organitzar els recursos del servei, garantir la cobertura territorial i optimitzar la prestació de les tasques de neteja. | D117: Neteja viària
B118: Projectes d'obres municipals i projectes de manteniment | C118: Conjunt de dades que recull la informació dels projectes d'obra promoguts per l'ajuntament, incloent objecte de l'actuació, ubicació, pressupost, termini d'execució i estat de tramitació. Permet fer el seguiment de les inversions municipals i de l'execució de les obres. | D118: Obres públiques i manteniment
B119: Tramitació administrativa | C119: Conjunt de dades amb el detall dels expedients administratius, el seu estat, tipus d'interessat, sèrie documental, temps de resolució entre d'altres | D119: Activitat administrativa

Sheet Rel.Conjunts-Sistemes
B4: Relacions de Conjunts de dades amb sistemes | F4: PENDENTS DE DADES COHERENTS
B8: Conjunt de dades | C8: Enllaç al conjunt de dades | D8: Sistema de dades | E8: Descripció de la relació | F8: Control conjunts de dades | G8: Control sistemes d'informació
B9: Sol·licitants d'ocupació del servei local d'ocupació | D9: Sistema per a la gestió de serveis locals d’ocupació (XALOC) | E9: Ajut | F9: =IF('Rel.Conjunts-Sistemes'!B9="","",IF(COUNTIF(ConjuntsDades,'Rel.Conjunts-Sistemes'!B9)>0,"OK","Conjunt de dades erroni")) -> OK | G9: =IF('Rel.Conjunts-Sistemes'!D9="","",IF(COUNTIF(Sistemes,'Rel.Conjunts-Sistemes'!D9)>0,"OK","Conjunt de dades erroni")) -> OK
B10: Ofertes de treball del servei local d'ocupació | D10: Sistema per a la gestió de serveis locals d’ocupació (XALOC) | E10: Sol·licitud d'ajut | F10: =IF('Rel.Conjunts-Sistemes'!B10="","",IF(COUNTIF(ConjuntsDades,'Rel.Conjunts-Sistemes'!B10)>0,"OK","Conjunt de dades erroni")) -> OK | G10: =IF('Rel.Conjunts-Sistemes'!D10="","",IF(COUNTIF(Sistemes,'Rel.Conjunts-Sistemes'!D10)>0,"OK","Conjunt de dades erroni")) -> OK
B11: Cens de locals comercials buits | D11: Eina per al càlcul del copagament SSAD i teleassistència | E11: Persona sol·licitant d'ajut | F11: =IF('Rel.Conjunts-Sistemes'!B11="","",IF(COUNTIF(ConjuntsDades,'Rel.Conjunts-Sistemes'!B11)>0,"OK","Conjunt de dades erroni")) -> OK | G11: =IF('Rel.Conjunts-Sistemes'!D11="","",IF(COUNTIF(Sistemes,'Rel.Conjunts-Sistemes'!D11)>0,"OK","Conjunt de dades erroni")) -> OK
B12: Cens d'empreses, comerços i establiments | D12: Eina per al càlcul del copagament SSAD i teleassistència | E12: Persones que estan inscrites al registre de voluntaris | F12: =IF('Rel.Conjunts-Sistemes'!B12="","",IF(COUNTIF(ConjuntsDades,'Rel.Conjunts-Sistemes'!B12)>0,"OK","Conjunt de dades erroni")) -> OK | G12: =IF('Rel.Conjunts-Sistemes'!D12="","",IF(COUNTIF(Sistemes,'Rel.Conjunts-Sistemes'!D12)>0,"OK","Conjunt de dades erroni")) -> OK
B13: Polígons de l'activitat econòmica i industrial | D13: Registre d'activitats econòmiques (GIA) | E13: Documentació ajut aportada | F13: =IF('Rel.Conjunts-Sistemes'!B13="","",IF(COUNTIF(ConjuntsDades,'Rel.Conjunts-Sistemes'!B13)>0,"OK","Conjunt de dades erroni")) -> OK | G13: =IF('Rel.Conjunts-Sistemes'!D13="","",IF(COUNTIF(Sistemes,'Rel.Conjunts-Sistemes'!D13)>0,"OK","Conjunt de dades erroni")) -> OK
B14: Tramitació i expedients administratius | D14: Registre d'analítiques de la qualitat de l’aigua | E14: Resolució ajut | F14: =IF('Rel.Conjunts-Sistemes'!B14="","",IF(COUNTIF(ConjuntsDades,'Rel.Conjunts-Sistemes'!B14)>0,"OK","Conjunt de dades erroni")) -> OK | G14: =IF('Rel.Conjunts-Sistemes'!D14="","",IF(COUNTIF(Sistemes,'Rel.Conjunts-Sistemes'!D14)>0,"OK","Conjunt de dades erroni")) -> OK
B15: Registre general d'entrada i sortida de documents | D15: Sistema per a la gestió de serveis locals d’ocupació (XALOC) | F15: =IF('Rel.Conjunts-Sistemes'!B15="","",IF(COUNTIF(ConjuntsDades,'Rel.Conjunts-Sistemes'!B15)>0,"OK","Conjunt de dades erroni")) -> OK | G15: =IF('Rel.Conjunts-Sistemes'!D15="","",IF(COUNTIF(Sistemes,'Rel.Conjunts-Sistemes'!D15)>0,"OK","Conjunt de dades erroni")) -> OK
B16: Registre municipal de convenis i acords institucionals | F16: =IF('Rel.Conjunts-Sistemes'!B16="","",IF(COUNTIF(ConjuntsDades,'Rel.Conjunts-Sistemes'!B16)>0,"OK","Conjunt de dades erroni")) -> OK | G16: =IF('Rel.Conjunts-Sistemes'!D16="","",IF(COUNTIF(Sistemes,'Rel.Conjunts-Sistemes'!D16)>0,"OK","Conjunt de dades erroni"))
B17: Taulell d'anuncis i edictes oficials | F17: =IF('Rel.Conjunts-Sistemes'!B17="","",IF(COUNTIF(ConjuntsDades,'Rel.Conjunts-Sistemes'!B17)>0,"OK","Conjunt de dades erroni")) -> OK | G17: =IF('Rel.Conjunts-Sistemes'!D17="","",IF(COUNTIF(Sistemes,'Rel.Conjunts-Sistemes'!D17)>0,"OK","Conjunt de dades erroni"))
B18: Quadre de classificació documental | F18: =IF('Rel.Conjunts-Sistemes'!B18="","",IF(COUNTIF(ConjuntsDades,'Rel.Conjunts-Sistemes'!B18)>0,"OK","Conjunt de dades erroni")) -> OK | G18: =IF('Rel.Conjunts-Sistemes'!D18="","",IF(COUNTIF(Sistemes,'Rel.Conjunts-Sistemes'!D18)>0,"OK","Conjunt de dades erroni"))
B19: Resultats electorals per mesa i secció censal | F19: =IF('Rel.Conjunts-Sistemes'!B19="","",IF(COUNTIF(ConjuntsDades,'Rel.Conjunts-Sistemes'!B19)>0,"OK","Conjunt de dades erroni")) -> OK | G19: =IF('Rel.Conjunts-Sistemes'!D19="","",IF(COUNTIF(Sistemes,'Rel.Conjunts-Sistemes'!D19)>0,"OK","Conjunt de dades erroni"))
B20: Registre Municipal de Parelles de Fet | F20: =IF('Rel.Conjunts-Sistemes'!B20="","",IF(COUNTIF(ConjuntsDades,'Rel.Conjunts-Sistemes'!B20)>0,"OK","Conjunt de dades erroni")) -> OK | G20: =IF('Rel.Conjunts-Sistemes'!D20="","",IF(COUNTIF(Sistemes,'Rel.Conjunts-Sistemes'!D20)>0,"OK","Conjunt de dades erroni"))
B21: Subvencions i ajuts Atorgats | F21: =IF('Rel.Conjunts-Sistemes'!B21="","",IF(COUNTIF(ConjuntsDades,'Rel.Conjunts-Sistemes'!B21)>0,"OK","Conjunt de dades erroni")) -> OK | G21: =IF('Rel.Conjunts-Sistemes'!D21="","",IF(COUNTIF(Sistemes,'Rel.Conjunts-Sistemes'!D21)>0,"OK","Conjunt de dades erroni"))
B22: Tresoreria: pagaments, ingressos i indicador de morositat | F22: =IF('Rel.Conjunts-Sistemes'!B22="","",IF(COUNTIF(ConjuntsDades,'Rel.Conjunts-Sistemes'!B22)>0,"OK","Conjunt de dades erroni")) -> OK | G22: =IF('Rel.Conjunts-Sistemes'!D22="","",IF(COUNTIF(Sistemes,'Rel.Conjunts-Sistemes'!D22)>0,"OK","Conjunt de dades erroni"))
B23: Pressupost municipal i previsions financeres | F23: =IF('Rel.Conjunts-Sistemes'!B23="","",IF(COUNTIF(ConjuntsDades,'Rel.Conjunts-Sistemes'!B23)>0,"OK","Conjunt de dades erroni")) -> OK | G23: =IF('Rel.Conjunts-Sistemes'!D23="","",IF(COUNTIF(Sistemes,'Rel.Conjunts-Sistemes'!D23)>0,"OK","Conjunt de dades erroni"))
B24: Execució del presupost municipal | F24: =IF('Rel.Conjunts-Sistemes'!B24="","",IF(COUNTIF(ConjuntsDades,'Rel.Conjunts-Sistemes'!B24)>0,"OK","Conjunt de dades erroni")) -> OK | G24: =IF('Rel.Conjunts-Sistemes'!D24="","",IF(COUNTIF(Sistemes,'Rel.Conjunts-Sistemes'!D24)>0,"OK","Conjunt de dades erroni"))
B25: Padrons fiscals i tributs Locall | F25: =IF('Rel.Conjunts-Sistemes'!B25="","",IF(COUNTIF(ConjuntsDades,'Rel.Conjunts-Sistemes'!B25)>0,"OK","Conjunt de dades erroni")) -> Conjunt de dades erroni | G25: =IF('Rel.Conjunts-Sistemes'!D25="","",IF(COUNTIF(Sistemes,'Rel.Conjunts-Sistemes'!D25)>0,"OK","Conjunt de dades erroni"))
B26: Relació de contractes menors | F26: =IF('Rel.Conjunts-Sistemes'!B26="","",IF(COUNTIF(ConjuntsDades,'Rel.Conjunts-Sistemes'!B26)>0,"OK","Conjunt de dades erroni")) -> OK | G26: =IF('Rel.Conjunts-Sistemes'!D26="","",IF(COUNTIF(Sistemes,'Rel.Conjunts-Sistemes'!D26)>0,"OK","Conjunt de dades erroni"))
B27: Licitacions de l'ens local | F27: =IF('Rel.Conjunts-Sistemes'!B27="","",IF(COUNTIF(ConjuntsDades,'Rel.Conjunts-Sistemes'!B27)>0,"OK","Conjunt de dades erroni")) -> OK | G27: =IF('Rel.Conjunts-Sistemes'!D27="","",IF(COUNTIF(Sistemes,'Rel.Conjunts-Sistemes'!D27)>0,"OK","Conjunt de dades erroni"))
... B66: Inventari de l'Enllumenat Públic | F66: =IF('Rel.Conjunts-Sistemes'!B66="","",IF(COUNTIF(ConjuntsDades,'Rel.Conjunts-Sistemes'!B66)>0,"OK","Conjunt de dades erroni")) -> OK | G66: =IF('Rel.Conjunts-Sistemes'!D66="","",IF(COUNTIF(Sistemes,'Rel.Conjunts-Sistemes'!D66)>0,"OK","Conjunt de dades erroni"))
B67: Inventari de Béns Mobles, Immobles i Vehicles
B68: Atenció i Intervenció en Serveis Socials
B69: Prestacions de Protecció Social per Unitat Familiar
B70: Dades del Servei d'Atenció Domiciliària (SAD)
B71: Dades del Servei de Teleassistència Municipal
B72: Atenció Integral a les Dones (Servei SIAD)
B73: Atenció al Col·lectiu LGTBI (Servei SAI)
B74: Reclamacions i Denúncies de Consum (OMIC)
B75: Registre d'Habitatges d'Ús Turístic (HUT)
B76: Ocupacions del Sòl i Terrasses a la Via Pública
B77: Oferta Formativa i Educació al Municipi
B78: Dades d'Alumnes d'Escoles Municipals
... B111: Cens d'Activitats de Risc i Plans d'Autoprotecció (PAU)

Sheet Qualitat
B5: Qualitat i completitut de l'inventari d'actius de dades
C7: Conjunts de dades
D8: Conjunts de dades identificats | E8: =COUNTA(ConjuntsDades) -> 104
D9: Completitut informació | E9: =AVERAGE('Conjunts de dades'!C6:AB6) -> 0.080769231
D10: Dominis no vàlids | E10: {=IFERROR(_xlfn.LET(_xlpm.a,_xlfn._xlws.FILTER(Dominis_a_ConjuntsDades,Dominis_a_ConjuntsDades<>""),_xlpm.u,_xlfn.UNIQUE(_xlpm.a),SUM(--ISNA(MATCH(_xlpm.u,Dominis,0)))),0)} -> 1 | F10: =IF(E10=0,"","Hi ha "&E10&" Conjunts de dades sense Domini vàlid") -> Hi ha 1 Conjunts de dades sense Domini vàlid
D11: Dominis sense cap Conjunt de dades | E11: =E19-E21 -> 6 | F11: =IF(E19>E21,"Hi ha "&E19-E21&" dominis sense cap entitat identificalda") -> Hi ha 6 dominis sense cap entitat identificalda
D12: Sistemes sense cap Sistema | E12: =E28-E29 -> 37 | F12: =IF(E28>E29,"Hi ha "&E28-E29&" sistemes sense cap Conjunt de dades identificat") -> Hi ha 37 sistemes sense cap Conjunt de dades identificat
D15: Relacionats amb Entitats | E15: =COUNTA(_xlfn.UNIQUE(Rel_ConjuntsDades_Entitats))-1 -> 0 | F15: =IF(E8>E15,"Hi ha "&E8-E15&" conjunts de dades no relacionats amb cap entitat") -> Hi ha 104 conjunts de dades no relacionats amb cap entitat
C18: Dominis de dades
D19: Dominis identificats | E19: =COUNTA(Dominis) -> 35
D20: Completitut informació | E20: =AVERAGE('Dominis de dades'!C7:E7) -> #DIV/0!
D21: Dominis amb conjunts de dades | E21: =COUNTA(_xlfn.UNIQUE(Dominis_a_ConjuntsDades))-1 -> 29
D22: Dominis sense cap Conjunt de dades | E22: =E19-E21 -> 6 | F22: =IF(E19>E21,"Hi ha "&E19-E21&" dominis sense cap entitat identificalda") -> Hi ha 6 dominis sense cap entitat identificalda
D23: Dominis amb entitats | E23: =COUNTA(_xlfn.UNIQUE(Dominis_a_Entitats))-1 -> 0 | F23: =IF(E19>E23,"Hi ha "&E19-E23&" dominis sense cap entitat identificalda") -> Hi ha 35 dominis sense cap entitat identificalda
D24: Dominis amb atributs | E24: =COUNTA(_xlfn.UNIQUE(Dominis_a_Atributs))-1 -> 0 | F24: =IF(E19>E24,"Hi ha "&E19-E24&" dominis sense cap atribut identificat") -> Hi ha 35 dominis sense cap atribut identificat
C27: Sistemes
D28: Sistemes identificats | E28: =COUNTA(Sistemes) -> 41
D29: Sistemes amb Conjunts de dades | E29: =COUNTA(_xlfn.UNIQUE(Rel_Sistemes_Conjunts))-1 -> 4
D30: Sistemes sense cap Conjunt de dades | E30: =E28-E29 -> 37 | F30: =IF(E28>E29,"Hi ha "&E28-E29&" sistemes sense cap Conjunt de dades identificat") -> Hi ha 37 sistemes sense cap Conjunt de dades identificat
D31: Completitut | E31: =AVERAGE(Sistemes!C7:N7) -> 0.17073171
C34: Entitats
D35: Entitats identificades | E35: =COUNTA(Entitats) -> 1
D36: Relacionats amb Entitats | E36: =COUNTA(_xlfn.UNIQUE(Rel_Entitats_ConjuntsDades))-1 -> 0 | F36: =IF(E35>E36,"Hi ha "&E35-E36&" entitats no relacionades amb cap conjunt de dades") -> Hi ha 1 entitats no relacionades amb cap conjunt de dades
D37: Entitats amb atributs | E37: =COUNTA(_xlfn.UNIQUE(Entitats_a_Atributs))-1 -> 0 | F37: =IF(E35>E37,"Hi ha "&E35-E37&" entitats sense cap atribut identificat") -> Hi ha 1 entitats sense cap atribut identificat
D38: Entitats de Dominis no vàlids | E38: {=IFERROR(_xlfn.LET(_xlpm.a,_xlfn._xlws.FILTER(Dominis_a_Entitats,Dominis_a_Entitats<>""),_xlpm.u,_xlfn.UNIQUE(_xlpm.a),SUM(--ISNA(MATCH(_xlpm.u,Dominis,0)))),0)} -> 0 | F38: =IF(E38=0,"","Hi ha "&E38&" Entitats sense Domini vàlid")
D39: Completitut | E39: =AVERAGE('Conjunts de dades'!C6:T6) -> 0.11877828
C42: Atributs
D43: Atributs identificats | E43: =COUNTA(Atributs) -> 1
D44: Atributs d'Entitats no vàlides | E44: {=IFERROR(_xlfn.LET(_xlpm.a,_xlfn._xlws.FILTER(Entitats_a_Atributs,Entitats_a_Atributs<>""),_xlpm.u,_xlfn.UNIQUE(_xlpm.a),SUM(--ISNA(MATCH(_xlpm.u,Entitats,0)))),0)} -> 0 | F44: =IF(E44=0,"","Hi ha "&E44&" Atributs sense Entitat vàlida")
D45: Completitut | E45: =AVERAGE(#REF!) -> #REF!

Sheet Llegenda
B4: Llegenda
B7: Sistemes d'informació | D7: Format
B8: Sistema de dades | C8: Nom amb què s’identifica el sistema o aplicació dins de l’organització. Ha de ser clar i recognoscible per a tots els equips. | D8: Text
B9: Descripció | C9: Explicació breu i entenedora de per a què serveix el sistema i quins processos o serveis municipals hi dona suport. Indica també des de quan conté dades. | D9: Text
B10: Tecnologies principals | C10: Tecnologies, programes, o plataformes principals utilitza el sistema. Això dona una idea senzilla del seu entorn tècnic. | D10: Text
B11: Proveïdor | C11: Nom de l’empresa o entitat que subministra el sistema, el manté o dona suport tècnic, addicionalment es pot afegeix el NIF. | D11: Text
B12: Tipus de servei | C12: Model de provisió i responsabilitat amb què es presta o s’utilitza el sistema, indicant el nivell de gestió que recau internament i quin sobre proveïdors externs. El tipus de servei pot ser: - On-premise, si es basa en infraestructura pròpia i l’ens local assumeix la gestió completa de maquinari, programari i dades. - IaaS, si un proveïdor extern facilita la infraestructura bàsica (servidors virtuals, emmagatzematge i xarxa), i l’ens local gestiona el sistema operatiu, el programari i les dades. - PaaS, si un proveïdor extern facilita la infraestructura i l’entorn de la plataforma (bàsica (sistema operatiu, bases de dades, entorns d'execució), i l’ens local gestiona el programari i les dades. - SaaS, si un proveïdor extern gestiona la totalitat de la solució, incloent-hi el programari. | D12: Selecció
B13: Arquitectura cloud | C13: Indica on s’allotja el sistema: en servidors municipals (local), en plataformes de núvol (cloud) o en un model mixt (híbrid). L’arquitectura pot ser: - On-premise (local), si el sistema s’allotja en servidors propis de l’ens local gestionats per ells mateixos i les dades no surten en cap moment de la infraestructura pròpia. - Pública (núvol públic), si el sistema s’allotja a la infraestructura d’un proveïdor de serveis al núvol de manera compartida amb altres clients amb un aïllament lògic. - Privada (núvol privat), si el sistema s’allotja a la infraestructura d’un proveïdor de serveis al núvol de dedicada en exclusiva a l’ens local. - Híbrida, si el sistema combina components allotjats de manera local amb components al núvol (públic o privat). | D13: Selecció
B14: Estat Sistema | C14: Situació actual del sistema dins del seu cicle de vida, indicant si està operatiu o en una altra fase. | D14: Selecció
B15: Data revisió estat | C15: Data en què es va revisar per última vegada l’estat del sistema, per garantir que la informació és actualitzada. | D15: Data
B16: És extern? | C16: El sistema d'informació és propi i l'administra l'ens local? | D16: Si / No
B17: Administrador del sistema (nom) | C17: Nom de la persona que gestiona i administra el sistema de dades actualment. És qui pot resoldre dubtes o incidències. | D17: Text
B18: Administrador del sistema (rol) | C18: Funció o responsabilitat que exerceix la persona administradora del sistema dins de l'organització. | D18: Text
B19: Sensibilitat de les dades | C19: Nivell de sensibilitat de la informació que tracta el sistema, rellevant per a la protecció de dades i el compliment normatiu. | D19: Selecció
... B24: Núm. Conjunts de dades | C24: Càlcul automàtic de quants conjunts de dades hi ha relacionats amb el sistema d'informació, es calcula a partir de les dades de la pestanya "Rel.Conjunts-Sistemes". Les caselles en vermell corresponen als registres que descriuen sistemes d'informació sense cap conjunt de dades relacionat. | D24: Calculat automàticament
B27: Dominis de dades | D27: Format
B28: Domini de dades | C28: Nom de la classificació lògica que permeten agrupar Conjunts de dades que comparteixen un mateix significat, àmbit temàtic o propòsit funcional. | D28: Text
B29: Descripció | C29: Una explicació clara i sintètica que ajuda a comprendre per què existeix el domini de dades i quin tipus d'informació recull, de manera que qualsevol persona el pugui interpretar sense dificultat. | D29: Text
B30: Àmbit | C30: És la categoria d’alt nivell que indica l’àmbit general al qual pertany el domini de dades, aquest pot agrupar més d'un domini de dades. | D30: Text
B31: Àrea propietària | C31: És l'àrea organitzativa de l’ens local que assumeix la responsabilitat funcional i operativa de les dades, més enllà del lloc on es trobin allotjades o gestionades. | D31: Text
B32: Núm. Conjunts de dades | C32: Càlcul automàtic de quants conjunts de dades hi ha relacionats amb el domini de dades, es calcula a partir de les dades de la pestanya "Conjunts de dades". Les caselles en vermell corresponen als registres que descriuen dominis de dades sense cap conjunt de dades relacionat. | D32: Calculat automàticament
B35: Conjunts de dades | D35: Format
B36: Nom Conjunt de dades | C36: Nom clar i específic que identifiqui de que permeti identificar el conjunt de dades dins l'ens local. | D36: Text
B37: Descripció | C37: Resumeix en una o dues frases què recull el conjunt de dades i per a què s'utilitza en el dia a dia. Indica els principals processos municipals on intervé i algun exemple d'ús, com ara informes, tramitació o atenció ciutadana. | D37: Text
B38: Domini de dades | C38: Indica el domini de dades al qual pertany el conjunt de dades, per exemple: serveis socials, via pública, hisenda o educació. | D38: Text
B39: Àrea propietària | C39: Tenint en compte la definició del domini de dades al que pertany, automàticament s'informa l'àrea organitzativa de l’ens local que assumeix la responsabilitat funcional i operativa de les dades. | D39: Calculat en funció del Domini de dades seleccionat
B40: Tipus conjunt de dades | C40: Indica el tipus de conjunt de dades, existeixen les següents possibilitats: - Dades de referència: dades amb la finalitat de facilitar la classificació i la gestió de la informació. - De negoci: dades que descriuen conceptes clau de l’ens local de manera precisa, estandarditzada i consistent. Aquests ajuden a contextualitzar les dades i asseguren que tots els usuaris tenen una comprensió comuna d’aquests. - Mestra: dades comunes i compartides a tota l’organització que descriuen conceptes clau per a l’ens local i proporcionen context per a la seva activitat. Representen perímetres determinats de dades, acotats de forma consensuada, i que serveixen com a referència transversal per a tota l'organització o una part. - Dades de referència / mestres no homogeneïtzades: dades que s'identifiquen com a rellevants per a ser considerades dades de referència / mestres, però que tenen un origen diferent a l'oficial. - Candidat a dades de referència / dades mestres: dada identificada com a possible dada de referència o mestra, que encara està en procés d'avaluació per determinar si compleix els criteris per ser-ho. | D40: Selecció
B41: Ús previst de les dades | C41: L'espai de treball on les dades són necessàries o es poden utilitzar, ja sigui dins un únic servei, compartides entre diverses àrees o en col·laboració amb entitats externes, indicant el nivell de coordinació que això comporta. L’abast organitzatiu pot ser: - Intern departamental - Intern transversal - Intern multiorganisme - Extern obert | D41: Selecció
B42: Conté dades personals? | C42: Marqueu "Sí" quan el conjunt de dades conté: - Noms, cognoms, DNI/NIF, adreça, telèfon, correu electrònic, matrícula, IP o qualsevol identificador d'expedient vinculat a una persona física concreta. - Dades pseudonimitzades o xifrades que l'ens pugui re-identificar amb informació addicional que ja posseeix. - Dades de contacte d'una persona física que actua en representació d'una persona jurídica (nom i cognoms del representant). | D42: Si / No
B43: Conté dades de gènere u orientació sexual? | C43: Marqueu "Sí" quan el conjunt de dades conté: - Registres de composició de meses electorals o participació política identificable. - Dades sobre creences religioses (p.e. menús escolars per motiu religiós, cementiris confessionals, cessió d'espais de culte). - Dades d'afiliació sindical (p.e. descompte de quota sindical en nòmina, crèdit horari sindical). - Dades de participació identificable en consultes o processos amb component ideològic explícit. | D43: Si / No
B44: Conté dades d'ideologia o creences? | C44: Marqueu "Sí" quan el conjunt de dades conté: - Dades específiques d'orientació sexual, identitat de gènere o nom sentit. - Dades recollides en serveis d'atenció LGTBI, protocols contra la LGTBI-fòbia o violència per raó d'orientació/identitat. - Informació sobre processos de transició de gènere. | D44: Si / No
B45: Conté dades biomètriques? | C45: Marqueu "Sí" quan el conjunt de dades conté: - Dades de control d'accés o de presència mitjançant empremta dactilar, reconeixement facial o de veu. - Signatura biomètrica dinàmica (captura de pressió, velocitat i traç, no una simple imatge escanejada). - Videovigilància únicament quan incorpora reconeixement facial automàtic actiu (identificació unívoca). | D45: Si / No
B46: Conté dades de salut? | C46: Marqueu "Sí" quan el conjunt de dades conté: - Certificats mèdics i informes de baixa laboral quan el motiu és identificable o se'n pot deduir el diagnòstic. - Graus de discapacitat o de dependència. - Dades de serveis socials relacionades amb addiccions, salut mental o atenció a la dependència. - Al·lèrgies o intoleràncies alimentàries en menjadors escolars o casals. - Dades de vacunació o d'aptitud física. | D46: Si / No
B47: Conté dades confidencials de l'ens local? | C47: Marqueu "Sí" quan el conjunt de dades conté: - Informes jurídics o dictàmens interns previs a una decisió, mentre no siguin públics. - Ofertes econòmiques d'empreses en processos de contractació encara no resolts. - Informes d'auditoria interna, control financer o intervenció amb detecció d'irregularitats. - Esborranys de pressupostos o plans urbanístics en fase d'estudi, previs a la seva aprovació. - Informació operativa de seguretat ciutadana no divulgable. | D47: Si / No
... B62: Reutilització de dades | C62: Si el conjunt es fa servir per a altres processos, serveis o informes, indiqueu a quins. | D62: Text
B63: Riscos associats | C63: Els riscos es defineixen segons la probabilitat i l’impacte que poden tenir: Probabilitat: - Baixa quan és improbable o no ha ocorregut en els darrers dos anys - Mitja quan és possible que el risc es materialitzi o ha ocorregut al menys un cop l'any. - Alta quan és altament probable o ha ocorregut diversos cops l'any. Impacte: - Baix quan l'impacte és assumible i no afecta dades sensibles. - Mig quan l'impacte és significatiu. - Alt quan l'impacte és greu i implica aturades de servei, costos econòmics o sancions, o afectació a dades sensibles.
B64: Incoherència de dades | C64: Existeix el risc de representar la mateixa dada de manera diferent en més d'un lloc? | D64: Selecció
B65: Informació desactualitzada | C65: Existeix el risc de que hi hagi dades que no reflecteixin la realitat actual? | D65: Selecció
B66: Publicació d'informació incorrecta | C66: Existeix el risc de que hi hagi dades que no hagin passat validacions de qualitat? | D66: Selecció
B67: Registres duplicats | C67: Existeix el risc de dades repetides? | D67: Selecció
B68: Accés a dades sensibles | C68: Existeix el risc de que algú, que no hagi de tenir accés, pugui accedir a dades sensibles? | D68: Selecció
B69: Accés o ús indegut | C69: Existeix el risc de algú pugui utilitzar les dades per a una finalitat diferent a l'autoritzada? | D69: Selecció
B70: Exposició de dades (menors, personals, sensibles o socials) | C70: Existeix el risc d'exposició indeguda de dades sensibles? | D70: Selecció
B71: Filtració o fuita de dades | C71: Existeix el risc de que les dades surtin de l'àmbit de control de l'ens local per error o per un atac? | D71: Selecció
B72: Indisponiblitat del sistema | C72: Existeix el risc de pèrdua de disponibilitat de les dades i dels sistemes? | D72: Selecció
B73: Pèrdua de dades | C73: Existeix el risc de pèrdua definitiva de dades? | D73: Selecció
B74: Falta de traçabilitat i evidències sobre la gestió de les dades | C74: Existeix el risc de no saber qui, quan i com s'ha fet un canvi a les dades? | D74: Selecció
B75: Falta de seguiment o auditories sobre accessos i usos | C75: Existeix el risc de que les dades i els accessos no siguin revisats o auditats de forma periòdica? | D75: Selecció
... B80: Núm. Dominis de dades | C80: Càlcul automàtic de si el dominis de dades relacionat al camp domini de dades és coherent amb els dominis de dades descrita a la pestanya "Dominis de dades". Les caselles en vermell corresponen als registres que descriuen conjunts de dades sense un domini de dades coherent. | D80: Calculat automàticament
B84: Entitats | D84: Format
B85: Nom Entitat | C85: Poseu un nom clar i fàcil d’entendre, que permeti identificar ràpidament de quina entitat es tracta sense haver de llegir cap detall addicional. | D85: Text
B86: Descripció | C86: Expliqueu en poques línies què representa aquesta entitat i en quin context del servei o procés es fa servir habitualment. | D86: Text
B87: És entitat global? | C87: Indiqueu si l’entitat és comuna a diversos àmbits o només s’utilitza en un context concret. | D87: Selecció
B88: Entitat global referida | C88: Quan no sigui global, especifiqueu a quina altra entitat queda vinculada o en depèn. | D88: Selecció de Entitat marcada com global
B89: Domini de dades principal | C89: Mostreu l’àmbit funcional o servei on aquesta entitat té sentit i on s’utilitza de forma natural. | D89: Selecció
B90: Àrea propietària principal | C90: Identifiqueu l’àrea o servei que vetlla perquè la informació sigui correcta i coherent amb les seves funcions. | D90: Calculat en funció del Domini de dades principal
B91: Sistema de dades d'orígen | C91: Escriviu el sistema principal del qual provenen les dades que formen aquesta entitat. | D91: Selecció
B92: Tipus d'informació | C92: Descriviu de manera general quin tipus d’informació conté: dades personals, operatives, organitzatives, etc. | D92: Selecció
B93: Responsable de l'entitat (Propietari de dades) | C93: Indiqueu qui és la persona que supervisa i valida el bon ús de la informació associada a l’entitat. | D93: Text
B94: Rol del responsable de l'entitat | C94: Expliqueu de manera breu quin paper té aquesta persona en la gestió, seguiment i qualitat de la informació. | D94: Text
B95: Nom del terme relacionat (Glossari) | C95: Poseu el terme del glossari que millor ajuda a comprendre què és l’entitat i com s’interpreta. | D95: Text
B96: Informació continguda | C96: Descriviu els elements principals que conté la informació i què aporten al servei o procés. | D96: Text
... B107: Reutilització de dades | C107: Expliqueu en quins processos, serveis o finalitats es reutilitzen aquestes dades habitualment. | D107: Text
B110: Relacions de Conjunts de dades amb entitats | D110: Format
B111: Conjunt de dades | C111: Indica l’àmbit o grup de dades al qual pertany la informació, normalment vinculat al procés o servei on es genera. | D111: Selecció
B112: Entitat | C112: Es refereix al tipus d’element implicat (persona, sol·licitud, documentació...). Ha de ser un concepte comprensible per qualsevol usuari. | D112: Selecció
B113: Descripció de la relació | C113: Explica amb una frase o dues quin és el vincle entre la dada i l’entitat. Ha de ser directe i evitar tecnicismes innecessaris. | D113: Text
B116: Atributs | D116: Format
B117: Nom Atribut | C117: Poseu un nom curt i entenedor que ajudi a identificar què és la dada dins l’entitat sense haver de revisar més camp detall. | D117: Text
B118: Descripció de l'atribut | C118: Expliqueu amb un parell de frases què representa la dada i en quin moment del procés és útil, pensant en algú que la vegi per primera vegada. | D118: Text
B119: Entitat | C119: Indiqueu a quina entitat pertany aquest atribut, és a dir, l’objecte principal del qual forma part (persona, sol·licitud, incidència…). | D119: Text
B120: Pertany a entitat global? | C120: Assenyaleu si aquest atribut forma part d'una entitat global o si és només complementari. | D120: Calculat en funció de l'Entitat
B121: És clau? | C121: Indiqueu si aquesta dada és imprescindible per identificar de manera única un registre dins l’entitat. | D121: Selecció
B122: Sistema | C122: Escriviu el sistema on es genera o manté el valor d’aquest atribut en el dia a dia. | D122: Selecció
B123: Tipus d'Atribut | C123: Descriviu breument el tipus general de la dada: text, número, data, codi… sense tecnicismes. | D123: Selecció
B124: Informació sensible | C124: Indiqueu si la dada pot contenir informació delicada segons la normativa o el seu contingut. | D124: Selecció
B125: Terme de negoci relacionat (Glossari) | C125: Escriviu el terme del glossari que ajuda a entendre millor el significat del camp. | D125: Text
B126: Format de base de dades | C126: Poseu el format tècnic que utilitza el sistema (ex.: text, número, data), només perquè l’usuari sàpiga què esperar. | D126: Text
B127: Admet valor nul? | C127: Indiqueu si el camp pot quedar buit en casos justificats o si sempre ha de tenir valor. | D127: Selecció
B128: Criteris de precisió | C128: Expliqueu quin grau d’exactitud o validació s’espera del valor perquè sigui correcte. | D128: Text
... B131: Criteris d'actualització | C131: Expliqueu en quines situacions es pot modificar la dada i cada quant pot canviar realment en el procés. | D131: Text
B132: Regla de validació | D132: Text
B133: Nivel qualitat esperada | D133: Text
B134: Catàleg de valors | D134: Text
B135: Origen | D135: Text
B136: Freqüència d'actualització | D136: Text
B137: Criticitat | D137: Selecció
B138: Usos principals de la dada | D138: Text
B139: Compartició amb altres sistemes | D139: Text
B160: Relacions entre Atributs
B161: Atribut | C161: Descripció | D161: Descripció
B162: Atribut d'origen | C162: Nom de l'atribut per al qual la relació serà SORTINT | D162: Nom de l'atribut per al qual la relació serà SORTINT
B163: Atribut de destinació | C163: Nom de l'atribut per al qual la relació serà ENTRANT | D163: Nom de l'atribut per al qual la relació serà ENTRANT
B164: Tipus relació | C164: Indica el tipus de relació que existeix entre els atributs origen i destinació | D164: Indica el tipus de relació que existeix entre els atributs origen i destinació
B165: Entitat d'origen | C165: Entitat a la què pertany l'atribut per al qual la relació serà SORTINT | D165: Entitat a la què pertany l'atribut per al qual la relació serà SORTINT
B166: Sistema d'origen | C166: Sistema on pertany l'entitat que conté l'atribut per al qual la relació serà SORTINT | D166: Sistema on pertany l'entitat que conté l'atribut per al qual la relació serà SORTINT
B167: Entitat de destinació | C167: Nom de l'entitat a la què pertany l'atribut per al qual la relació serà ENTRANT | D167: Nom de l'entitat a la què pertany l'atribut per al qual la relació serà ENTRANT
B168: Sistema de destinació | C168: Nom curt del sistema on pertany l'entitat que conté l'atribut per al qual la relació serà ENTRANT | D168: Nom curt del sistema on pertany l'entitat que conté l'atribut per al qual la relació serà ENTRANT

Sheet Relació inventaris
N1: Dominis de dades
B2: Relació inventaris | C2: I els atributs de l'inventari de la DIBA i de la GENE? I els que vam preveure nosaltres inicialment?
B4: Inventari | C4: Principal referència | D4: Detalls
B5: Sistemes | C5: Tarragona | D5: A Tarragona apareix de manera recurrent la columna “Sistema d’informació”, associada als conjunts de dades. Aquest patró es repeteix de forma implícita a Mataró (Sistema de Gestió de Bases de Dades, Tipus de sistema/aplicació) i a Sant Cugat (Sistema on es genera). El conjunt Sistemes recull aquesta coincidència transversal: el sistema sempre és present com a element clau. En aquest inventari hem inclòs la font de dades principal (sistema o aplicació de procedència), una descripció, així com informació tècnica i del proveïdor. Altres camps com l'administrador i rol del sistema, han estat inspirats en els camps Gestor, contacte_gestor, custodi, que apareixen a l'inventari de la DIBA
B6: Domini de dades | C6: Tarragona | D6: Tarragona disposa explícitament d’un inventari de Dominis de dades utilitzat per agrupar conjunts segons àmbits funcionals (padró, urbanisme, medi ambient, etc.). Allà podem trobar informació com Domini de dades, Descripció breu, Àrea municipal habitual que hem utilitzat per crear aquest inventari: Domini de dades, Descripció, Àrea propietària. Aquest mateix criteri de classificació funcional s’alinea amb enfocaments generals com els que promou DIBA. També s'inclouen altres termes com administrador i rol del sistema
B7: Conjunt de dades | C7: Tarragona + Mataró | D7: Tant Tarragona com Mataró treballen explícitament amb el concepte de conjunt de dades. A Tarragona forma part de l’inventari estructurat; a Mataró és l’eix central de l’Inventari de fonts d’informació, mitjançant el camp “Nom del conjunt de dades”, amb atributs de governança associats. Camps com Nom Conjunt de dades, Descripció, Domini de dades, Àrea propietària o Sistema d'informació d'origen principal, han estat agafats de l'inventari de Mataró. També s'inclouen altres termes com 'administrador i rol del conjunt de dades
B8: Entitats | C8: Sant Cugat | D8: L’inventari Entitats inclou diversos camps que no apareixen a cap dels inventaris de referència, ja que aquests treballen a nivell de domini o de conjunt de dades i no baixen al nivell d’unitat informativa. Entre aquests camps destaquen, per exemple: Entitat global referida, Sistema de dades d'orígen, etc. També s'inclouen altres termes com administrador i rol de l'entitat
B9: Rel.Conjunts-Entitats | C9: Elaboració pròpia | D9: Taula desenvolupada específicament per garantir la traçabilitat entre conjunts de dades i entitats, inspirada en les relacions de Sant Cugat i els criteris de traçabilitat de DIBA.
B10: Atributs | C10: Sant Cugat | D10: Sant Cugat descriu cada dada amb un conjunt ric de característiques: tipus de camp, obligatorietat, qualitat, dades personals, anonimització, reutilització, etc. Aquest nivell de detall coincideix plenament amb el concepte d’atribut.

Sheet Llistes
B1: Sistema de dades | D1: Tipus de servei | F1: Arquitectura Cloud | H1: Estat Sistema | J1: Sensibilitat de les dades | L1: Criticitat | N1: Domini de dades principal | P1: Àmbit | R1: Conjunt de dades | T1: Ús previst de les dades | V1: Tipus Conjunt de dades | X1: Tipus d'informació | AA1: Categoria alt valor | AC1: Cadència | AE1: Nivell d'accés | AG1: PERSISTENCIA | AI1: RETENCIO | AK1: Origen de les dades | AM1: Dades obertes | AO1: Categoria Conjunt de Dades | AQ1: És entitat global? | AS1: Entitat global referida | AU1: És Domini de dades principal? | AW1: És clau? | AY1: Tipus d'Atribut | BA1: Admet valor nul? | BC1: TipusRelEntitats | BE1: RelacióGlosari | BG1: Confidencialitat | BI1: Format | BK1: Seguretat | BM1: Sistemes d'informació | BO1: Reutilització de dades | BQ1: Prioritats | BS1: Anàlisi Riscos | BV1: Si No
B2: {=_xlfn._xlws.SORT(_xlfn.UNIQUE(Sistemes))} -> Catàleg de tràmits i eina de tramitació digital | D2: On-premise | F2: Pública | H2: En producció | J2: Baixa | L2: Baixa | N2: Activitat administrativa | P2: Govern i administració | R2: Sol·licitants d'ocupació del servei local d'ocupació | T2: Intern departamental | V2: De negoci | X2: Dades personals | Y2: informen sobre persones físiques identificades o identificables (ciutadania, personal…) | AA2: Geoespacial | AC2: En temps real | AE2: Àrea | AG2: Dades transaccionals (es modifiquen constantment) | AI2: Arxiu després d'un període d'inactivitat | AK2: Declaracions de ciutadans | AM2: Si | AO2: Ajuntaments | AQ2: Si | AS2: <No aplica> | AU2: Si | AW2: Si | AY2: Dada mestre | BA2: Si | BC2: 1:1 | BE2: Jeràrquica (Un terme general (categoria) agrupa termes més específics) | BG2: No Personal | BI2: Text | BK2: Públic | BM2: BI | BO2: Planificació estratègica | BQ2: 1. Molt baixa | BS2: Probabilitat: Baixa Impacte: Baix (1) | BT2: 1 | BV2: Si
B3: Comptabilitat municipal | D3: PaaS (plataforma com a servei) | F3: Híbrida | H3: Pendent d'actualització | J3: Mitjana | L3: Mitjana | N3: Aigua i sanejament | P3: Gestió de l'espai públic | R3: Ofertes de treball del servei local d'ocupació | T3: Intern transversal | V3: Dades de referència | X3: Dades sensibles | Y3: dades amb impacte ètic, legal o reputacional si es divulguen (salut, orientació, menors…) | AA3: Observació de la terra i el medi ambient | AC3: Diària | AE3: Organització | AG3: Dades arxivades (ja no s'utilitzen activament, però es conserven) | AI3: Arxiu en un sistema separat | AK3: Sistemes municipals interns | AM3: No | AO3: Altres entitats | AQ3: No | AS3: {=_xlfn._xlws.SORT(_xlfn.UNIQUE(_xlfn._xlws.FILTER(Entitats,#REF!="Si")))} -> #REF! | AU3: No | AW3: No | AY3: Dada de referència | BA3: No | BC3: 1:N | BE3: Àlies (Diferents termes que representen el mateix concepte dins del negoci) | BG3: Personal | BI3: Numèric | BK3: Intern | BM3: CRM ciutadà | BO3: Transparència | BQ3: 2. Baixa | BS3: Probabilitat: Baixa Impacte: Moderat (1) | BT3: 1 | BV3: No
B4: Control horari | D4: IaaS (infraestructura com a servei) | F4: Privada | H4: Obsolet | J4: Alta (dades personals) | L4: Alta | N4: Atenció ciutadana | P4: Serveis a les persones | R4: Cens de locals comercials buits | T4: Intern multiorganisme | V4: Dades de referència / mestres no homogeneïtzades | X4: Dades públiques | Y4: informació no restringida, objecte de transparència o ús general | AA4: Meteorologia | AC4: Setmanal | AE4: Públiques | AG4: Dades històriques (es mantenen per consulta, però no es modifiquen) | AI4: Retenció segons normativa legal | AK4: Administracions supramunicipals | AM4: Parcialment | AO4: Anàlisi | AY4: Dada de negoci | BC4: N:1 | BE4: Dependència (Un terme només té sentit en funció d’un altre) | BG4: Personal privat | BI4: Decimal | BK4: Sensible | BM4: ERP | BO4: Optimització de serveis | BQ4: 3. Mitja | BS4: Probabilitat: Baixa Impacte: Alt (2) | BT4: 2 | BV4: Parcialment
B5: Eina de gestió de la participació | D5: SaaS (software com a servei) | F5: On-premise | H5: Substitució planificada | J5: Alta (dades personals / bancàries) | N5: Bon govern, transparència i participació | P5: Corporatiu (Dades mestres i de referència) | R5: Cens d'empreses, comerços i establiments | T5: Extern obert | V5: Data mestra | X5: Dades financeres | Y5: rellevants per a gestió econòmica (pressupost, tributs, facturació, subvencions…) | AA5: Estadística | AC5: Quinzenal | AG5: No informat | AI5: Retenció per un període fix (ex. 1, 5, 10 anys) | AK5: Sensors o sistemes Iot | AM5: Previst a futur | AO5: Ciutadania | AY5: Metadada | BC5: N:M | BE5: Correspondència (Terme similar que pot tenir variacions en diferents departaments o sistemes) | BI5: Percentatge | BK5: Crític | BM5: Gestor d’activitats | BO5: Informes interns | BQ5: 4. Alta | BS5: Probabilitat: Mitja Impacte: Baix (1) | BT5: 1
B6: Eina per a la valoració de diagnosi social | J6: Alta (dades especials) | N6: Cementiri i serveis funeraris | R6: Polígons de l'activitat econòmica i industrial | V6: Candidat a dades de referència / dades mestres | X6: Dades de localització/geoespacials | Y6: referenciades a ubicació física (adreces, parcel·les, geoposicionament…) | AA6: Societats i propietat de societat | AC6: Mensual | AI6: Retenció segons polítiques internes | AK6: Empreses contractistes | AM6: Pendent d'anàlisi | AO6: Intern | AY6: Metadada de negoci | BI6: Fracció | BK6: Molt crític | BM6: Gestor del servei | BO6: Quadres de comandament | BQ6: 5. Molt alta | BS6: Probabilitat: Mitja Impacte: Moderat (3) | BT6: 3
B7: Eina per al càlcul del copagament SSAD i teleassistència | N7: Consum energètic | R7: Tramitació i expedients administratius | X7: Dades de servei/operacionals | Y7: relatives als serveis prestats, tràmits, processos o activitat interna | AA7: Mobilitat | AC7: Trimestral | AI7: Retenció indefinida (les dades no s'eliminen) | AK7: Varis | AY7: Metadada tècnica | BI7: Data | BM7: Inventari | BS7: Probabilitat: Mitja Impacte: Alt (4) | BT7: 4
B8: Enquesta retributiva per a ús municipal | N8: Contractació, convenis i subvencions | R8: Registre general d'entrada i sortida de documents | X8: Dades d’inventari/patrimoni | Y8: registres d’actius, equipaments, infraestructures, vehicles… | AA8: No aplica | AC8: Anual | AI8: No hi ha una política definida | AK8: No informat | AY8: Metadada operacional | BI8: Hora | BM8: Plataforma contractació | BS8: Probabilitat: Alta Impacte: Baix (3) | BT8: 3
B9: Gestió d'aparcaments | N9: Cultura i gestió del patrimoni cultural i històric (formulat anteriorment com Cultura i patrimoni) | R9: Registre municipal de convenis i acords institucionals | X9: Dades estadístiques/analítiques | Y9: formats agregats, anonimitzats o per a anàlisi, no directament identificables | AC9: Major a l'any | AI9: No informat | AY9: Metadada de qualitat | BI9: Data i Hora | BM9: Queixes i Suggeriments | BS9: Probabilitat: Alta Impacte: Moderat (4) | BT9: 4
B10: Gestió de cementiris | N10: Dades de referència (comú a tot l'ecosistema de dades de país) | R10: Taulell d'anuncis i edictes oficials | X10: Dades d’organització/estructura | Y10: referides a organigrames, processos, rols o unitats | AY10: Metadada de seguretat/privadesa | BI10: Marca de temps | BM10: Sistema d'Informació Geogràfica | BS10: Probabilitat: Alta Impacte: Alt (4) | BT10: 4
B11: Gestió de l'inventari de bens mobles i inmobles | N11: Drets socials | R11: Quadre de classificació documental | X11: Altres | Y11: si escau, especificar al camp “Observacions” | AY11: Metadada de govern | BI11: Booleà | BM11: Sistema operador
B12: Gestió de nòmines municipals | N12: Economia local, comerç i mercats | R12: Resultats electorals per mesa i secció censal | AY12: Dades de referència / mestres no homogeneïtzades
B13: Gestió de queixes i suggeriments | N13: Educació | R13: Registre Municipal de Parelles de Fet | AY13: Candidata a dades de referència / dades mestres
B14: Gestió de representacions | N14: Esport | R14: Subvencions i ajuts Atorgats
B15: Gestió de residus | N15: Formació i ocupació | R15: Tresoreria: pagaments, ingressos i indicador de morositat
B16: Gestió de sancions | N16: Govern i organització | R16: Pressupost municipal i previsions financeres
B17: Gestió de serveis bibliotecaris | N17: Habitatge | R17: Execució del presupost municipal
B18: Gestió de subvencions | N18: Hisenda | R18: Padrons fiscals i tributs Locall
B19: Gestió dels plans de protecció civil municipal | N19: Incidències de la via pública | R19: Relació de contractes menors
B20: Gestió dels sistemes de videovigilància | N20: Informació i comunicació | R20: Licitacions de l'ens local
B21: Gestió d'expedients atenció primària serveis socials | N21: Informació territorial i geoespacial | R21: Processos participatius i pressupostos participatius
B22: Gestió d'incidències a la via pública i manteniment d'equipaments | N22: Medi ambient | R22: Registre de l'agenda d'alts càrrecs amb grups d'Interès
B23: Gestió policial d'atestats | N23: Mobilitat i trànsit | R23: Organigrama polític i declaració de béns
B24: GIAM | N24: Neteja viària | R24: Actes del ple i decrets d'Alcaldia
B25: Padró municipal d’habitants | N25: Obres públiques i manteniment | R25: Dades de cadastre municipal
... B36: Sistema de gestió | N36: Urbanisme i planejament | R36: Padró Municipal d'Habitants i Demografia
B37: Sistema de gestió de les auditories pobresa energètica | R37: Nomenclàtor de Vies Públiques i Numeració Postal
B38: Sistema de gestió de personal | F38: Arquitectura Cloud | R38: Cartografia de la Xarxa Viària i Carrers
B39: Sistema de gestió d'impostos municipals | R39: Elements Tècnics del Pla de Protecció Civil (DUPROCIM)
B40: Sistema per a la gestió de serveis locals d’ocupació (XALOC) | R40: Cens d'Activitas de Risc i Plans d'Autoprotecció (PAU)
B41: Tramitació d’expedients administratius | R41: Inscripcions i Formació de Treballadors Públics
B42: Web municipal | R42: Gestió de Nòmines i Costos de Personal
B43: 0 | R43: Gestió de Personal: Plantilla i Relació de Llocs de Treball (RLT)
R44: Sinistralitat i Accidents Laborals de la Plantilla
R45: Directori de Contacte del Personal de l'Ens Local
R46: Indicadors de Sostenibilitat: Consums i Canvi Climàtic
R47: Recollida i Gestió de Residus Municipals
R48: Inventari de l'Arbrat Urbà i Zones Verdes
R49: Inventari i Cartografia de Camins Públics i Forestals
R50: Inventari de Finques Agrícoles i Forestals
R51: Registre d'Animals de Companyia
R52: Registre d'Animals Potencialment Perillosos (GPP)
R53: Fons Documental de l'Arxiu Municipal
R54: Fons Fotogràfic i Audiovisual de l'Arxiu
R55: Inventari de Béns Culturals d'Interès Local (BCIL)
... R106: Cens d'Activitats de Risc i Plans d'Autoprotecció (PAU)
